Workbook
Name Geology: #REF!
Name Geology: #REF!
Name Geology: Geology!$D$12:$D$17
Name ListedSubstances: #REF!
Name OpenAreas: #REF!
Name OpenAreas: 'MA - Open Areas'!$D$13:$D$51
Name OpenAreas: #REF!
Name tanks: 'CWF - Fuel Tanks'!$D$11:$D$37
Name VehicleClass: 'CWF-Plant and Equipment-Diesel'!$C$94:$C$164

Sheet Title
D14: Ravenswood Gold Pty Ltd
G15: If you have any queries please contact:
D16: DATA COLLECTION SHEET | G16: Account Lead: | H16: Laura Orozco
G17: Email: | H17: lorozco@greenbase.com.au
G18: Office: | H18: (08) 9322 9966
D19: Ravenswood Operations | G19: Level 2, 41 St Georges Terrace, Perth WA | PO Box Z5451, St Georges Terrace WA 6831
D20: 01/07/2023 - 30/06/2024 | G20: Website: | H20: https://www.greenbase.com.au/
D22: Checklist | G22: Report Requirements
D24: Relevant Worksheet | E24: Responsibility | G24: NGER | H24: NPI | I24: Administration
D25: Site Attributes | E25: GC | I25: X
D26: Additional Data Entry | E26: GC | H26: X
D27: Cleaner Production | E27: GC | I27: X
D28: Feedback | E28: ALL | I28: X
D29: Production Stats | E29: GC | G29: X | I29: X
D30: Fuel Tanks | E30: CWF | H30: X | I30: X
D31: Point Source Energy | E31: CWF | G31: X | H31: X
D32: Plant and Equipment-Diesel | E32: CWF | G32: X | H32: X
D33: Plant and Equipment-Other Fuels | E33: CWF | G33: X | H33: X
D34: Drilling and Explosives | E34: ES | G34: X | H34: X
D35: Geology | E35: GC | H35: X
D36: Open Areas | E36: MA / CWF | H36: X
D37: Material Transfers | E37: GC | H37: X
D38: TSF | E38: GG / CWF | H38: X
D39: Leach Tanks and Heap Leach | E39: GG / CWF | H39: X
D40: Materials and Chemicals | E40: CWF | G40: X | H40: X
D41: Discharge | E41: GG / CWF | H41: X
D42: Spills | E42: JS | G42: X | H42: X
D43: Waste Transfers | E43: JS | H43: X
D44: Fuel Balance | E44: Greenbase | G44: X | I44: X
D46: Greenbase Service | E46: About the Reporting Program | K46: Website
D47: NPI | E47: The National Pollutant Inventory (NPI) is a pollutant release and transfer register, established by the Australian government via the National Environment Protection Measures (NEPM) legislation in 1998. The goal of the NPI is to ensure the community has access to information about the emission and transfer of toxic substances that may affect them locally in accordance with the principle of 'Community right to know'. | K47: http://www.npi.gov.au/
D48: NGER | E48: The National Greenhouse and Energy Reporting Act (NGER) was legislated by the Federal Government in 2007. The act requires companies to estimate their greenhouse gas emissions and report their energy production and energy consumption as well as other specified information. The data reported in the NGER program are used to inform government policy, inform the public, help meet Australia's international reporting obligation and assist Commonwealth, state and territory government programmes and activities. | K48: http://www.cleanenergyregulator.gov.au/Pages/default.aspx
D49: Sustainability | E49: The GRI framework is overseen by an independent organisation, and is intended to serve as a generally accepted framework for reporting an organisation's environmental, social and economic performance with a focus on rigour and quality. SASB Standards guide the disclosure of financially material sustainability information by companies to their investors. Available for 77 industries, the Standards identify the subset of environmental, social, and governance (ESG) issues most relevant to financial performance in each industry. | K49: https://www.globalreporting.org/Pages/default.aspx https://www.sasb.org/
D51: Complimentary Half Day Training | E51: Training at the Greenbase office is offered to clients as a part of the standard reporting service. This offering covers the basic understanding needed to complete reports, such as background on the NPI and NGER programmes, how to fill in the data collection templates and how to use the Greenbase system (estimated at 2 hours). | K51: https://www.greenbase.com.au/ (through secure login)
D52: Datasheet Training | E52: Training videos covering how to fill in the data collection template are available on the Greenbase website, through secure login. Please contact your Greenbase Account Lead if you do not have a login. | K52: https://www.greenbase.com.au/ (through secure login)
D54: Instructions:
E56: Note: Greenbase accepts no responsibility for the authenticity and accuracy of any numbers supplied.
D57: Cells with a | E57: white | F57: or green | H57: background require values to be entered
D58: Cells with a | E58: orange | F58: background require options to be selected from a suggested list. If a representative option is not available feel free to type in your own description
D59: Cells with a | E59: blue | F59: background require options to be selected from a suggested list, and have had an option or value entered
D60: Cells with a | E60: purple | F60: background are optional information that may help us to calculate or verify other information.
D61: Cells with a | E61: yellow | F61: background are annual values that will be automatically generated from monthly data. If monthly data is not available, enter the annual figure in the yellow cell
D62: Cells with a | E62: grey | F62: background are for information only.
D65: LOR
D66: Task ID:
D67: 48113
D68: ANZIC
D69: 01xx Agriculture
D70: 02xx Aquaculture
D71: 03xx Forestry and logging
D72: 04xx Fishing, hunting and trapping
D73: 05xx Agriculture, forestry and fishing support services
D74: 060x Coal mining
D75: 070x Oil and gas extraction
D76: 080x Metal ore mining
D77: 091x Construction material mining
D78: 099x Other non‑metallic mineral mining and quarrying
D79: 101x Exploration
... D260: 96xx Private households employing staff and undifferentiated goods‑and‑service‑producing activities of households for own use

Sheet Data Source Tracking
C3: Ravenswood Operations | E3: The information in this tab will not be reported, but is rather used to record the source of data to assist with the data collection process
C4: 01/07/2023 - 30/06/2024 | E4: Examples are provided - please amend and add relevant information as applicable
C6: Data Source Tracking
C8: Tab | D8: Data Item / Parameter | E8: Frequency (e.g. monthly, quarterly, annually) | F8: Data Source | H8: Details of person collecting data | K8: Other Notes
F9: File Name | G9: Location | H9: Department | I9: Position | J9: Name
C10: Site Attributes | D10: Number of personnel
C11: Production Statistics | D11: Electricity purchased
C12: Production Statistics | D12: Ore mined
C13: Production Statistics | D13: Ore processed
C14: Production Statistics | D14: Waste mined
C15: Production Statistics | D15: Gold produced
C16: Fuel Tanks | D16: Primary tanks
C17: Fuel Tanks | D17: Service truck
C18: Point Source Energy | D18: Fuel use by other point sources
C19: Plant and Equipment - Diesel | D19: Vehicles and unmetered engines diesel use
C20: Plant and Equipment - Diesel | D20: Percent on site
C21: Plant and Equipment - Diesel | D21: Working area
... C48: Landfill | D48: Waste sent landfill
C49: [select]
C50: [select]
C51: [select]
C52: [select]
C53: [select]
C54: [select]
C55: [select]
C56: [select]
C57: [select]
C58: [select]
C59: [select]
C62: [select]
... C79: Invoices

Sheet Site Attributes
C3: Ravenswood Operations
C4: 01/07/2023 - 30/06/2024
C6: Site Attributes
C8: Personnel Employed
C9: Total number of personnel employed at site | D9: 455
C11: Weather Details
C12: Nearest BOM weather station | D12: Charters Towers Airport (034084)
C14: Facility Information
C15: Street Address | D15: 1 Macrossan Street
D16: Ravenswood, QLD
C17: Postcode | D17: 4816
C18: Environment Agency Licence No.(s) | D18: EPML00979013
C19: Other than for lighting or motive purposes is the facility's maximum power consumption ≥20MW? (1) | D19: [select]
C20: Is ≥1tonne of fuel burnt in an hour? | D20: [select]
C21: Australian New Zealand Standard Industrial Classification (ANZSIC) Code | D21: 0804 Gold Ore Mining
C23: Location
C24: Latitude (South) | D24: -20.6.45 S
C25: Longitude (East) | D25: 146.54.11 E
C27: Site Description
C32: For Public Enquires (NPI)
C33: Name | D33: Michael Limpus
C34: Management Position | D34: Environment, Approvals and Community Manager
C35: Telephone Number | D35: 07 4736 9206
C36: Postal Address | D36: PO Box 5802 Townsville, QLD
C38: Postcode | D38: 4810
C39: Public email address (if applicable) | D39: info@ravenswoodgold.com
C40: Web Address (if applicable) for hotlink from NPI internet database | D40: https://www.ravenswoodgold.com/
C42: For Technical Enquires (NPI)
C43: Name | D43: Michael Limpus
C44: Management Position | D44: Environment, Approvals and Community Manager
C45: Postal Address | D45: PO Box 5802 Townsville, QLD
C47: Postcode | D47: 4810
C48: Telephone number | D48: 07 4736 9206
C49: Email address (if applicable) | D49: info@ravenswoodgold.com
C51: Details of Facility Occupier (NPI)
C52: Name
C53: Management Position
C55: Resources Incurred (NPI)
C56: Internal Costs
C57: External Costs (Consultants, Analysis)
C59: Comments to NPI Unit (specify public and/or private) | D59: [select]
C63: (1) As per the NPI Guide ‘Motive means producing physical or mechanical motion. Electrical motive equipment includes pumps, fans compressors, conveyor belts etc. Electrical non-motive equipment includes arcing furnaces, heaters, ovens etc.’
C64: [select]
C65: 0600 Coal Mining
C66: 0700 Oil and Gas Extraction
C67: 0801 Iron Ore Mining
C68: 0802 Bauxite Mining
C69: 0803 Copper Ore Mining
C70: 0804 Gold Ore Mining
C71: 0805 Mineral Sand Mining
C72: 0806 Nickel Ore Mining
C73: 0807 Silver-Lead-Zinc Ore Mining
C74: 0809 Other Metal Ore Mining
... C130: 753x Local government administration (NGER Only)

Sheet Additional Data Entry
C3: Ravenswood Operations
C4: 01/07/2023 - 30/06/2024
C6: Fuel Properties
C7: Fuel Type | D7: Density | F7: Sulphur Content
C8: Diesel | D8: 0.836 | E8: kg/L | F8: 0.001 | G8: %
C9: ULP (Gasoline) | D9: 0.735 | E9: kg/L | F9: 0.015 | G9: %
C10: LPG (Propane) | D10: 0.51 | E10: kg/L | F10: 0.01 | G10: %
C11: PNG (Natural Gas) | E11: kg/m3 | F11: 4 | G11: mg/m3
C13: Meteorological Station Data
C14: Parameter Name | F14: Value | G14: Unit | H14: Data Source
C15: Meteorological Station Name (if applicable) | F15: Nolans Weather Station | G15: Text
C16: Atmospheric pressure | F16: 10.72 | G16: kPa
C17: Climatic zone | F17: Zone 7 (North Central QLD) | G17: Option | H17: Onsite weather station at Nolans
C18: Number of rain days | F18: 56 | G18: day | H18: Onsite weather station at Nolans
C19: Wind speed | F19: 983.53 | G19: m/s | H19: Onsite weather station at Nolans
C21: Other
C22: Type | D22: Value | E22: Unit
C23: Reporting period | D23: 366 | E23: days
C25: Climatic zone
C26: [select]
C27: Zone 1 (South Central Australia)
C28: Zone 2 (South Western Australia)
C29: Zone 3 (Pilbara)
C30: Zone 4 (Top End)
C31: Zone 5 (Central Australia)
C32: Zone 6 (Cape York)
C33: Zone 7 (North Central QLD)
C34: Zone 8 (South Central QLD)
C35: Zone 9 (South QLD)
C36: Zone 10 (NSW)
... C38: Zone 12 (Tasmania)

Sheet Cleaner Production
C3: Ravenswood Operations | D3: It is optional to tick the corresponding boxes if your facility commenced any of the
C4: 01/07/2023 - 30/06/2024 | D4: source reduction techniques, however a date implemented needs to be provided.
C7: Cleaner Production Activities
D9: Used | E9: Comments
C10: Changed from solvent based to aqueous based raw materials
C11: Changed product specifications
C12: Changed production schedules to minimise equipment/feedstock changeovers
C13: Community consultative committee
C14: Dust suppression - water sprays/chemical suppression | D14: Yes | E14: Fixed plant has dust sprays installed on conveyors, crushers, screens and stockpiles. Water carts used on roadways. Water carts water down dig faces to increase moisture content of hauled material. Dust suppression chemical used in water carts.
C15: Dust suppression - wind breaks/covered/enclosed stockpiles | D15: Yes | E15: Hoods/windbreaks/scrubbers installed on transfer points. Enclosed sections on select conveyors.
C16: Implemented inspection or monitoring program for potential spill or leak sources | D16: Yes | E16: Pre-wet season preparations - ensuring bund capacity to prevent overtopping, general housekeeping, chemical storage
C17: Improved maintenance scheduling, record keeping, or procedures
C18: Improved procedures for loading, unloading or transfer operations | D18: Yes | E18: Real-time dust monitoring used to inform dust mitigation actions
C19: Installed high-pressure/low-volume cleaning equipment
C20: Installed overflow alarms or automatic shut-off valves
C21: Installed vapour recovery systems (VRS)
C22: Modified packaging
C23: Modified process, equipment, layout, or piping | E23: Dust collector on BRW crusher - GC confirm with Pual Botman.
C24: Use of cleaner raw materials
C25: Other modifications/practices (please specify)
C28: Installation of Pollution Control Equipment
D30: Used | E30: Year Installed | F30: Comments
C31: Activated carbon filter
C32: Bio scrubber
C33: Biofilter
C34: Cyclone/mutlicyclone
C35: Dry scrubber
C36: Dust monitor | D36: Yes | E36: 2017, 2018, 2020 | F36: Dust monitors are used to collect real-time data and inform dust mitigation actions. PM10 BAM installed 2017, PM2.5 BAM and TSP installed 2018, second PM10 BAM installed 2020.
C37: Electrostatic Precipitator
C38: Fabric filter/baghouse
C39: Incineration/afterburner
C40: Low NOx burner
C41: Mist eliminator
C42: Opacity monitor
C43: Thermal oxidiser
C44: Wastewater treatment
C45: Wet scrubber
C46: Other (please specify)

Sheet Feedback
C3: Ravenswood Operations | G3: This tab is used to record the queries and data sent between site and the Greenbase Account Lead to support the data during audits
C4: 01/07/2023 - 30/06/2024
C6: Feedback
C8: Questions/Queries
C10: Item No. | D10: Date | E10: Tab | F10: Raised By | G10: Query Raised | H10: Response Date | I10: Query Response By | J10: Query Response | K10: Status
C28: Raw Datasheet References
D30: Date | E30: Tab | F30: Sent By | G30: Description of Raw Data | H30: Cell Reference
C40: Phone Call Logs
D42: Date & Time | E42: Caller | F42: Recipient | G42: Description of Phone Call

Sheet GC - Production Stats
C3: Ravenswood Operations | E3: Method: Production Statistics Data: E-mail Rebecca.Caswell@ravenswooggold.com and ask for the "Operations and Metrics" excel file for the FY. The sheet runs off a calendar year, so you will need both the preceding and current years' sheets. refer to the "Data Source/Supplier" column below to find and copy/paste the relevant data from the Operations and Metrics excel file. Ergon & CS Energy Data: E-mail Carole.Anderson@ravenswoodgold.com to obtain the Ergon and CS Energy invoices for the FY. Open each invoice and find the kWh for each month (include both Tarrif 11 and Tariff 33). Make note of any properties which have solar, as well as the solar contribution, in a comment. NPE Dredge & Power Station Data: E-mail RGL.PowerstationOps@nationalpump.com.au the data table for the dredge and power station and ask if they can fill out each months' kWh, as well as send through the log sheet for data QAQC. Brisbane office: e-mail louise.mettam-minas@ravenswoodgold.com and ask if she can send through the Brisbane office invoices, which include the power use.
C4: 01/07/2023 - 30/06/2024
E5: Grey cells are residential, so are excluded from NGERS reporting (outside operational control)
C6: Production Statistics
H7: Monthly Total
D8: Data Source/ Supplier | E8: FY2023 | F8: FY2024 | G8: Unit | H8: Jul | I8: Aug | J8: Sep | K8: Oct | L8: Nov | M8: Dec | N8: Jan | O8: Feb | P8: Mar | Q8: Apr | R8: May | S8: Jun
C9: High Grade Ore Mined (BRW) | D9: Intranet --> Monthly Sheet --> Month End --> 7. Jul 24 --> Operations and Metrics Jul 24-Site.xlsx/Input-R/Mining/ | E9: 7347387.1 | F9: =SUM(H9:S9) -> 5776718.7 | G9: Dry Tonnes | H9: =SUM(H73, H75) -> 515235.55 | I9: =SUM(I73, I75) -> 763533.16 | J9: =SUM(J73, J75) -> 817076.15 | K9: =SUM(K73, K75) -> 354957.75 | L9: =SUM(L73, L75) -> 475054.76 | M9: =SUM(M73, M75) -> 331188.76 | N9: =SUM(N73, N75) -> 284776.63 | O9: =SUM(O73, O75) -> 394157.33 | ... S9: =SUM(S73, S75) -> 140308.49
C10: Medium Grade Ore Mined (BRW) | D10: Intranet --> Monthly Sheet --> Month End --> 7. Jul 24 --> Operations and Metrics Jul 24-Site.xlsx/Input-R/Mining/ | E10: - | F10: =SUM(H10:S10) -> 1148492.6 | G10: Dry Tonnes | H10: =H76 -> 0 | I10: =I76 -> 0 | J10: =J76 -> 0 | K10: =K76 -> 0 | L10: =L76 -> 0 | M10: =M76 -> 0 | N10: =N76 -> 133648.03 | O10: =O76 -> 118494.18 | ... S10: =S76 -> 331457.05
C11: Low Grade Ore Mined (BRW) | D11: Intranet --> Monthly Sheet --> Month End --> 7. Jul 24 --> Operations and Metrics Jul 24-Site.xlsx/Input-R/Mining/ | E11: 4630014 | F11: =SUM(H11:S11) -> 3252665.2 | G11: Dry Tonnes | H11: =SUM(H74, H77) -> 354642.03 | I11: =SUM(I74, I77) -> 406755.88 | J11: =SUM(J74, J77) -> 425750.19 | K11: =SUM(K74, K77) -> 410280 | L11: =SUM(L74, L77) -> 427113.79 | M11: =SUM(M74, M77) -> 374721.4 | N11: =SUM(N74, N77) -> 182972.36 | O11: =SUM(O74, O77) -> 147451.87 | ... S11: =SUM(S74, S77) -> 47793.416
C12: Very Low Grade Ore Mined (BRW) | D12: Intranet --> Monthly Sheet --> Month End --> 7. Jul 24 --> Operations and Metrics Jul 24-Site.xlsx/Input-R/Mining/ | E12: - | F12: =SUM(H12:S12) -> 522039.19 | G12: Dry Tonnes | H12: =H78 -> 0 | I12: =I78 -> 0 | J12: =J78 -> 0 | K12: =K78 -> 0 | L12: =L78 -> 0 | M12: =M78 -> 0 | N12: =N78 -> 32524.695 | O12: =O78 -> 90539.6 | ... S12: =S78 -> 177821.5
C13: High Grade Ore Mined (SAR) | D13: Intranet --> Monthly Sheet --> Month End --> 7. Jul 24 --> Operations and Metrics Jul 24-Site.xlsx/Input-R/Mining/ | E13: 7347387.1 | F13: =SUM(H13:S13) -> 0 | G13: Dry Tonnes | H13: =H79 | I13: =I79 -> - | J13: =J79 | K13: =K79 | L13: =L79 | M13: =M79 | N13: =N79 -> - | O13: =O79 -> - | ... S13: =S79 -> -
C14: Medium Grade Ore Mined (SAR) | D14: Intranet --> Monthly Sheet --> Month End --> 7. Jul 24 --> Operations and Metrics Jul 24-Site.xlsx/Input-R/Mining/ | E14: - | F14: =SUM(H14:S14) -> 212868.1 | G14: Dry Tonnes | H14: =H80 -> 0 | I14: =I80 -> 0 | J14: =J80 -> 0 | K14: =K80 -> 0 | L14: =L80 -> 0 | M14: =M80 -> 0 | N14: =N80 -> 117570.79 | O14: =O80 -> 32018.227 | ... S14: =S80 -> -
C15: Low Grade Ore Mined (SAR) | D15: Intranet --> Monthly Sheet --> Month End --> 7. Jul 24 --> Operations and Metrics Jul 24-Site.xlsx/Input-R/Mining/ | E15: 4630014 | F15: =SUM(H15:S15) -> 477907.8 | G15: Dry Tonnes | H15: =H81 -> 0 | I15: =I81 -> 8272.8764 | J15: =J81 -> 0 | K15: =K81 -> 65093.641 | L15: =L81 -> 28024.093 | M15: =M81 -> 88405.763 | N15: =N81 -> 51172.795 | O15: =O81 -> 30482.235 | ... S15: =S81 -> 77072.854
C16: Very Low Grade Ore Mined (SAR) | D16: Intranet --> Monthly Sheet --> Month End --> 7. Jul 24 --> Operations and Metrics Jul 24-Site.xlsx/Input-R/Mining/ | E16: - | F16: =SUM(H16:S16) -> 233878.8 | G16: Dry Tonnes | H16: =H82 -> 0 | I16: =I82 -> 0 | J16: =J82 -> 0 | K16: =K82 -> 0 | L16: =L82 -> 0 | M16: =M82 -> 0 | N16: =N82 -> - | O16: =O82 -> - | ... S16: =S82 -> -
C17: Ore Mined | D17: Intranet --> Monthly Sheet --> Month End --> 7. Jul 24 --> Operations and Metrics Jul 24-Site.xlsx/Input-R/Mining/Open Pit Ore Mined (t) | E17: 11728016 | F17: =SUM(H17:S17) -> 11624570 | G17: Dry Tonnes | H17: 869878 | I17: 1178562 | J17: 1242826 | K17: 830331 | L17: 930193 | M17: 794316 | N17: 802665 | O17: 813143 | P17: 924674 | Q17: 1144807 | R17: 1318722 | S17: 774453
C18: Waste Mined | D18: Intranet --> Monthly Sheet --> Month End --> 7. Jul 24 --> Operations and Metrics Jul 24-Site.xlsx/Input-R/Mining/Total Waste Mined (t) | E18: 20832862 | F18: =SUM(H18:S18) -> 18559743 | G18: Dry Tonnes | H18: =H85 -> 1491689 | I18: =I85 -> 1285904 | J18: =J85 -> 1254104 | K18: =K85 -> 2044595 | L18: =L85 -> 1816547 | M18: =M85 -> 1880825 | N18: =N85 -> 1684063 | O18: =O85 -> 1629074 | ... S18: =S85 -> 1700313
C19: Ore Processed | D19: Intranet --> Monthly Sheet --> Month End --> 7. Jul 24 --> Operations and Metrics Jul 24-Site.xlsx/Input-R/Milling/Ore Milled (t) | E19: 5083091.4 | F19: =SUM(H19:S19) -> 7099788 | G19: Dry Tonnes | H19: =H88 -> 598983 | I19: =I88 -> 527565 | J19: =J88 -> 537161 | K19: =K88 -> 685313 | L19: =L88 -> 567254 | M19: =M88 -> 660870 | N19: =N88 -> 584835 | O19: =O88 -> 567444 | ... S19: =S88 -> 565189
C20: Waste Moved | D20: Greenbase | E20: 20832862 | F20: =SUM(H20:S20) -> 0 | G20: Dry Tonnes
C21: Ore Moved | D21: Greenbase | F21: =SUM(H21:S21) -> 0 | G21: Tonne
C23: Total Gold Produced | D23: Intranet --> Monthly Sheet --> Month End --> 7. Jul 24 --> Operations and Metrics Jul 24-Site.xlsx/Input-R/Milling/Gold Poured (oz.) | E23: 149454.17 | F23: =SUM(H23:S23) -> 176597 | G23: Troy oz | H23: =H91 -> 9772 | I23: =I91 -> 14285 | J23: =J91 -> 15721 | K23: =K91 -> 19981 | L23: =L91 -> 15809 | M23: =M91 -> 14479 | N23: =N91 -> 18770 | O23: =O91 -> 11814 | ... S23: =S91 -> 14028
C25: Electricity Purchased
H26: Monthly Total
D27: Data Source/ Supplier | E27: Residential or business | F27: Annual | G27: units | H27: Jul | I27: Aug | J27: Sep | K27: Oct | L27: Nov | M27: Dec | N27: Jan | O27: Feb | P27: Mar | Q27: Apr | R27: May | S27: Jun
C28: Electricity Purchased | D28: ERGON NMI: 30337828149 (91214562) - 19 Robert St (STP) (G:Accounting\End of Month\20## End of Month\##. MMM YY) | E28: Business | F28: =SUM(H28:S28) -> 185520.64 | G28: kWh | H28: 15955 | I28: =6422.9+7706 -> 14128.9 | J28: 13966.63 | K28: 16022.11 | L28: 15163.58 | M28: 16411.075 | N28: 16009.47 | O28: 16750.14 | P28: 15238.06 | Q28: 15501.12 | R28: 14598.63 | S28: 15775.92
D29: ERGON NMI: 30518901604 (91610919) - Sandy Creek Rd (G:Accounting\End of Month\20## End of Month\##. MMM YY) | E29: Business | F29: =SUM(H29:S29) -> 884301.7 | G29: kWh | H29: 46284.1 | I29: 43853.9 | J29: 66521.2 | K29: 63617.3 | L29: 67446 | M29: 58857.9 | N29: 61401.8 | O29: 88620 | P29: =116041.6 -> 116041.6 | Q29: =81440.6 -> 81440.6 | R29: =102324.4 -> 102324.4 | S29: =87892.9 -> 87892.9
D30: ERGON NMI: 30500014267 (91010964) - Suhrs Creek Rd (SCD) (G:Accounting\End of Month\20## End of Month\##. MMM YY) | E30: Business | F30: =SUM(H30:S30) -> 788709.66 | G30: kWh | H30: 65569.91 | I30: 66904.72 | J30: 63446.84 | K30: 66641.5 | L30: 59701.31 | M30: 59809 | N30: 61286.44 | O30: 56406.98 | P30: 0 | Q30: 134725.1 | R30: =79806.74 -> 79806.74 | S30: 74411.12
D31: ERGON NMI: 3053093335 (217041068) 11 ELLIOTT ST | E31: Business | F31: =SUM(H31:S31) -> 3486.879 | G31: kWh | H31: 276.57 | I31: 261.48 | J31: 233.66 | K31: 312.17 | L31: 332.749 | M31: 336.1 | N31: 318.74 | O31: 289.02 | P31: 471.52 | Q31: 278.08 | R31: 266.64 | S31: 110.15
D32: ERGON NMI: 3033782881 (90301081) SANDY CK ROAD | E32: Business | F32: =SUM(H32:S32) -> 72726.88 | G32: kWh | H32: =1082.92+3829.79+2067.43 -> 6980.14 | I32: =1269.66+4037.99+2312.8 -> 7620.45 | J32: 7851.18 | K32: 8449.87 | L32: 7537.37 | M32: 6538.92 | N32: 6360.23 | O32: 5512.79 | P32: =1022.38+1790.62+3227.69 -> 6040.69 | Q32: =1001.23+1714.3+3205.29 -> 5920.82 | R32: =300.93+580.81+1116.11 -> 1997.85 | S32: =265.58+556.99+1094 -> 1916.57
D33: ERGON NMI: 30337828651 - 20 TOWNSVILLE ST | E33: Residential | F33: =SUM(H33:S33) -> 9623.62 | G33: kWh | H33: 586.62 | I33: 0 | J33: 0 | K33: 0 | L33: 2394 | M33: 0 | N33: 0 | O33: 3187 | P33: 0 | Q33: 0 | R33: =3017+439 -> 3456 | S33: 0
D34: ERGON NMI: 30337829971 - 23 SCOTIA ST | E34: Residential | F34: =SUM(H34:S34) -> 9691.4 | G34: kWh | H34: 570.4 | I34: 0 | J34: 0 | K34: 0 | L34: 2319 | M34: 0 | N34: 0 | O34: 3589 | P34: 0 | Q34: 0 | R34: 3213 | S34: 0
D35: ERGON NMI: 3034225404 - 26 SCOTIA ST | E35: Residential | F35: =SUM(H35:S35) -> 9578.77 | G35: kWh | H35: 876.77 | I35: 0 | J35: 0 | K35: 0 | L35: 2001 | M35: 0 | N35: 0 | O35: 3404 | P35: 0 | Q35: 0 | R35: 3297 | S35: 0
D36: ERGON NMI: 30337863212 - 5 CECIL ST | E36: Residential | F36: =SUM(H36:S36) -> 6812.53 | G36: kWh | H36: 924.53 | I36: 0 | J36: 0 | K36: 0 | L36: 2556 | M36: 0 | N36: 0 | O36: 0 | P36: 0 | Q36: 0 | R36: 3332 | S36: 0
D37: ERGON NMI: 30337764822 - SANDY CK RD | E37: Business | F37: =SUM(H37:S37) -> 2690.68 | G37: kWh | H37: 218.68 | I37: 0 | J37: 0 | K37: 0 | L37: 828 | M37: 0 | N37: 0 | O37: 1042 | P37: 0 | Q37: 0 | R37: 602 | S37: 0
D38: ERGON NMI: 30337850079 - 28 SCOTIA ST | E38: Residential | F38: =SUM(H38:S38) -> 11739.631 | G38: kWh | H38: =166.19+153.59 -> 319.78 | I38: =280.89+446.48 -> 727.37 | J38: =161.333+531.474 -> 692.807 | K38: 760.92 | L38: 1156.86 | M38: 1324.63 | N38: 1578.58 | O38: 1301.554 | P38: 1942.74 | Q38: =121.94+787.72 -> 909.66 | R38: =545.31+172.08 -> 717.39 | S38: =89.24+218.1 -> 307.34
D39: ERGON NMI: 3033785104 - DEIGHTON ST | E39: Business | F39: =SUM(H39:S39) -> 23485.57 | G39: kWh | H39: 3092.57 | I39: 0 | J39: 0 | K39: 0 | L39: 6700 | M39: 0 | N39: 0 | O39: 7079 | P39: 0 | Q39: 0 | R39: 6614 | S39: 0
D40: ERGON NMI: 30337830121 - 12 TOWNSVILLE ST | E40: Residential | F40: =SUM(H40:S40) -> 5894.05 | G40: kWh | H40: 496.05 | I40: 0 | J40: 0 | K40: 0 | L40: 2464 | M40: 0 | N40: 0 | O40: 2934 | P40: 0 | Q40: 0 | R40: 0 | S40: 0
D41: ERGON NMI: 3033786267 - 69 MURRAY ST | E41: Residential | F41: =SUM(H41:S41) -> 16702.96 | G41: kWh | H41: 373.96 | I41: 0 | J41: 0 | K41: 0 | L41: 964 | M41: 0 | N41: 0 | O41: 3148 | P41: 0 | Q41: 0 | R41: 12217 | S41: 0
D42: ERGON NMI: 3034101161 - LONDON ST | E42: Business | F42: =SUM(H42:S42) -> 1453.96 | G42: kWh | H42: 250.96 | I42: 0 | J42: 0 | K42: 0 | L42: 354 | M42: 0 | N42: 0 | O42: 426 | P42: 0 | Q42: 0 | R42: 423 | S42: 0
D43: ERGON NMI: 3033782831 - 18 TOWNSVILLE ST | E43: Residential | F43: =SUM(H43:S43) -> 6245.19 | G43: kWh | H43: 235.19 | I43: 0 | J43: 0 | K43: 0 | L43: 1418 | M43: 0 | N43: 0 | O43: 2602 | P43: 0 | Q43: 0 | R43: 1990 | S43: 0
D44: ERGON NMI: 3033783021 - 25 SCOTIA ST | E44: Residential | F44: =SUM(H44:S44) -> 9188.32 | G44: kWh | H44: 589.32 | I44: 0 | J44: 0 | K44: 0 | L44: 2210 | M44: 0 | N44: 0 | O44: 2168 | P44: 0 | Q44: 0 | R44: 4221 | S44: 0
D45: ERGON NMI: 3033786143 - 1 MURRAY ST | E45: Residential | F45: =SUM(H45:S45) -> 3135.91 | G45: kWh | H45: 2428.91 | I45: 0 | J45: 0 | K45: 707 | L45: 0 | M45: 0 | N45: 0 | O45: 0 | P45: 0 | Q45: 0 | R45: 0 | S45: 0
D46: ERGON NMI: 3033782822 - 45 ROBERT ST | E46: Business | F46: =SUM(H46:S46) -> 1339.285 | G46: kWh | H46: 90.31 | I46: 118.34 | J46: 136.65 | K46: 62.175 | L46: 64.85 | M46: 55.01 | N46: 57.98 | O46: 77.95 | P46: 111.14 | Q46: 195.44 | R46: 119.11 | S46: 250.33
D47: ERGON NMI: 30337766448 - 100 MACROSSAN ST | E47: Business | F47: =SUM(H47:S47) -> 0 | G47: kWh | H47: 0 | I47: 0 | J47: 0 | K47: 0 | L47: 0 | M47: 0 | N47: 0 | O47: 0 | P47: 0 | Q47: 0 | R47: 0 | S47: 0
D48: ERGON NMI: 3033775958 - 72 DEIGHTON ST | E48: Residential | F48: =SUM(H48:S48) -> 214.628 | G48: kWh | H48: 83.65 | I48: 0 | J48: =70.755+1.193 -> 71.948 | K48: 16.73 | L48: 5.29 | M48: 5.42 | N48: 5.38 | O48: 5.04 | P48: 8.33 | Q48: =1.21+4 -> 5.21 | R48: =4.14+1.24 -> 5.38 | S48: =0.52+1.73 -> 2.25
D49: ERGON NMI: 30531308262 - 74 37 ELPHINSTONE ST | E49: Business | F49: =SUM(H49:S49) -> 10583.66 | G49: kWh | H49: 624.44 | I49: 705.21 | J49: 690.46 | K49: 982.94 | L49: 1083.2 | M49: 862.75 | N49: 1364.27 | O49: 951.56 | P49: 733.63 | Q49: 1016.98 | R49: 778.06 | S49: 790.16
D50: ERGON NMI: 30337759915 - 92 DEIGHTON ST | E50: Residential | F50: =SUM(H50:S50) -> 795.6 | G50: kWh | H50: 106.67 | I50: =0.88+0.37 -> 1.25 | J50: 0 | K50: 0 | L50: 0 | M50: 0 | N50: 0 | O50: 0 | P50: 0 | Q50: 0 | R50: =382.77+95.54 -> 478.31 | S50: =164.1+45.27 -> 209.37
D51: ERGON NMI: 3051630231 - 18 RAVEN ST | E51: Residential | F51: =SUM(H51:S51) -> 0.02 | G51: kWh | H51: 0 | I51: 0 | J51: 0 | K51: 0 | L51: 0.02 | M51: 0 | N51: 0 | O51: 0 | P51: 0 | Q51: 0 | R51: 0 | S51: 0
D52: ERGON NMI: 3033775761 - 11 PAIGE ST | E52: Residential | F52: =SUM(H52:S52) -> 5147 | G52: kWh | H52: =479.12+392.88 -> 872 | I52: 0 | J52: 0 | K52: 0 | L52: 898 | M52: 0 | N52: 0 | O52: 1995 | P52: 0 | Q52: 0 | R52: 1382 | S52: 0
D53: ERGON NMI: 3033776245 - 2 CREEK ST | E53: Residential | F53: =SUM(H53:S53) -> 12757.803 | G53: kWh | H53: 99.82 | I53: =222.52+228.3 -> 450.82 | J53: =439.849+135.064 -> 574.913 | K53: 1497.84 | L53: 1397.42 | M53: 1464.77 | N53: 1569.89 | O53: 1283.66 | P53: 2131.04 | Q53: =499.83+534.6 -> 1034.43 | R53: =395.44+424.13 -> 819.57 | S53: =202.37+231.26 -> 433.63
D54: ERGON NMI: 3053239955 - Stuart Office | E54: Business | F54: =SUM(H54:S54) -> 33510.117 | G54: kWh | H54: 3826.29 | I54: 3793.37 | J54: 4432.17 | K54: 4843.5 | L54: 4365.207 | M54: 4534.31 | N54: 3801.04 | O54: 3914.23 | P54: 0 | Q54: 0 | R54: 0 | S54: 0
D55: ERGON NMI: 30337833577 - 11 SCOTIA ST | E55: Residential | F55: =SUM(H55:S55) -> 4991.87 | G55: kWh | H55: 752.87 | I55: 0 | J55: 0 | K55: 0 | L55: 1151 | M55: 0 | N55: 0 | O55: 1630 | P55: 0 | Q55: 0 | R55: 1458 | S55: 0
D56: ERGON NMI: 30337763858 - 46 JAMES ST | E56: Residential | F56: =SUM(H56:S56) -> 0 | G56: kWh | H56: 0 | I56: 0 | J56: 0 | K56: 0 | L56: 0 | M56: 0 | N56: 0 | O56: 0 | P56: 0 | Q56: 0 | R56: 0 | S56: 0
D57: TOTAL from small facilities (added by KBond) | F57: =SUM(F28:F32, F37, F39, F42, F46:F47, F49, F54) -> 2007809 | G57: kWh | H57: =SUM(H28:H32, H37, H39, H42, H46:H47, H49, H54) -> 143168.97 | I57: =SUM(I28:I32, I37, I39, I42, I46:I47, I49, I54) -> 137386.37 | J57: =SUM(J28:J32, J37, J39, J42, J46:J47, J49, J54) -> 157278.79 | K57: =SUM(K28:K32, K37, K39, K42, K46:K47, K49, K54) -> 160931.57 | L57: =SUM(L28:L32, L37, L39, L42, L46:L47, L49, L54) -> 163576.27 | M57: =SUM(M28:M32, M37, M39, M42, M46:M47, M49, M54) -> 147405.07 | N57: =SUM(N28:N32, N37, N39, N42, N46:N47, N49, N54) -> 150599.97 | O57: =SUM(O28:O32, O37, O39, O42, O46:O47, O49, O54) -> 181069.67 | ... S57: =SUM(S28:S32, S37, S39, S42, S46:S47, S49, S54) -> 181147.15
H59: Monthly Total
D60: Data Source/ Supplier | E60: Residential or business | F60: Annual | G60: units | H60: Jul | I60: Aug | J60: Sep | K60: Oct | L60: Nov | M60: Dec | N60: Jan | O60: Feb | P60: Mar | Q60: Apr | R60: May | S60: Jun
C61: Electricity Purchased | D61: CS ENERGY NMI 3053231962 | E61: Business | F61: =SUM(H61:S61) -> 10413.537 | G61: kWh | H61: 677.291 | I61: 730.332 | J61: 789.385 | K61: 908.381 | L61: 940.43 | M61: 1015.688 | N61: 1065.24 | O61: 965 | P61: 995.43 | Q61: 882.95 | R61: 780.12 | S61: 663.29
D62: CS ENERGY NMI 3053186668 | E62: Business | F62: =SUM(H62:S62) -> 1.1696389e+08 | G62: kWh | H62: 10551692 | I62: 9043034.7 | J62: 9156158.2 | K62: 10220137 | L62: 9628599.1 | M62: 10421024 | N62: 9650192.4 | O62: 9004569 | P62: 9808853.2 | Q62: 10100881 | R62: 10110773 | S62: 9267973.8
D63: NPE Dredge - E-mail NPE for this data | E63: Business | F63: =SUM(H63:S63) -> 11508751 | G63: kWh | H63: 669075 | I63: 780725 | J63: 992750 | K63: 728750 | L63: 748825 | M63: 582175 | N63: 1022643 | O63: 924385 | P63: 1167403 | Q63: 1814395 | R63: 1222485 | S63: 855140
D64: Power Station 2 - G:\Accounting\End of Month\2023 FY End of Month\06 Jun 23\Power - refer e-mail from NPE (allan.grant@nationalpump.com.au) to Gerry Maguire. Rebecca Caswell supplied her spreadsheet - GenSet | E64: Business | F64: =SUM(H64:S64) -> 90031327 | G64: kWh | H64: 6799820 | I64: 5019007 | J64: 5822000 | K64: 7769000 | L64: 8156000 | M64: 8231000 | N64: 7691800 | O64: 7892400 | P64: 6567500 | Q64: 9311300 | R64: 7696800 | S64: 9074700
D65: Total | F65: =SUM(H65:S65) -> 2.1851438e+08 | G65: kWh | H65: =SUM(H61:H64) -> 18021264 | I65: =SUM(I61:I64) -> 14843497 | J65: =SUM(J61:J64) -> 15971698 | K65: =SUM(K61:K64) -> 18718796 | L65: =SUM(L61:L64) -> 18534365 | M65: =SUM(M61:M64) -> 19235215 | N65: =SUM(N61:N64) -> 18365701 | O65: =SUM(O61:O64) -> 17822319 | ... S65: =SUM(S61:S64) -> 19198477
C67: Electricity Purchased | D67: 307 Queen Street, L17 S3, Meter No. 78N171129 (Total from Brisbane Office). E-mail Louise Mettam-Minas for invoices | E67: Business | F67: =SUM(H67:S67) -> 11717 | G67: kWh | H67: 1102 | I67: 1120 | J67: 968 | K67: - | L67: 1158 | M67: - | N67: 1453 | O67: 1348 | P67: 1445 | Q67: 1522 | R67: 1601 | S67: -
C70: Raw Data
H71: 45496 | I71: 45527 | J71: 45558 | K71: 45588 | L71: 45619 | M71: 45649 | N71: 45315 | O71: 45346 | P71: 45375 | Q71: 45406 | R71: 45436 | S71: 45467
F72: Open Pit Ore Mined | H72: 869877.59 | I72: 1178561.9 | J72: 1242826.3 | K72: 830331.39 | L72: 930192.64 | M72: 794315.92 | N72: 802665.3 | O72: 813143.43 | P72: 924673.79 | Q72: 1144807.2 | R72: 1318721.6 | S72: 774453.31
F73: Buck Reef West - HG | H73: 356184.74 | I73: 511899.32 | J73: 488556.43 | K73: 258159.38 | L73: 443086.29 | M73: 185499.12 | N73: 284776.63 | O73: 394157.33 | P73: 497667.95 | Q73: 729178.84 | R73: 473583.32 | S73: 116580.44
F74: Buck Reef West - LG
F75: BRW Beneficiated Ore - HG | H75: 159050.81 | I75: 251633.84 | J75: 328519.72 | K75: 96798.377 | L75: 31968.463 | M75: 145689.64 | R75: - | S75: 23728.05
F76: BRW Beneficiated Ore - MG | N76: 133648.03 | O76: 118494.18 | P76: 117265.66 | Q76: 173332.07 | R76: 274295.63 | S76: 331457.05
F77: BRW Beneficiated Ore - LG | H77: 354642.03 | I77: 406755.88 | J77: 425750.19 | K77: 410280 | L77: 427113.79 | M77: 374721.4 | N77: 182972.36 | O77: 147451.87 | P77: 154570.81 | Q77: 137949.37 | R77: 182664.1 | S77: 47793.416
F78: BRW Beneficiated Ore - VLG | N78: 32524.695 | O78: 90539.6 | P78: 90431.2 | Q78: 65574.9 | R78: 65147.3 | S78: 177821.5
F79: Sarsfield Beneficiated Ore - HG | I79: - | N79: - | O79: - | P79: - | Q79: - | R79: - | S79: -
F80: Sarsfield Beneficiated Ore - MG | N80: 117570.79 | O80: 32018.227 | P80: 32986.969 | Q80: 30292.11 | R80: - | S80: -
F81: Sarsfield Beneficiated Ore - LG | I81: 8272.8764 | K81: 65093.641 | L81: 28024.093 | M81: 88405.763 | N81: 51172.795 | O81: 30482.235 | P81: 31751.205 | Q81: 4890.0994 | R81: 92742.243 | S81: 77072.854
F82: Sarsfield Beneficiated Ore - VLG | N82: - | O82: - | P82: - | Q82: 3589.8 | R82: 230289 | S82: -
F85: Total Waste Mined (t) | H85: 1491689 | I85: 1285904 | J85: 1254104 | K85: 2044595 | L85: 1816547 | M85: 1880825 | N85: 1684063 | O85: 1629074 | P85: 1717721 | Q85: 1273079 | R85: 781829 | S85: 1700313
F88: Ore Milled | H88: 598983 | I88: 527565 | J88: 537161 | K88: 685313 | L88: 567254 | M88: 660870 | N88: 584835 | O88: 567444 | P88: 544278 | Q88: 671052 | R88: 589844 | S88: 565189
F91: Gold Poured | H91: 9772 | I91: 14285 | J91: 15721 | K91: 19981 | L91: 15809 | M91: 14479 | N91: 18770 | O91: 11814 | P91: 12578 | Q91: 15711 | R91: 13649 | S91: 14028

Sheet CWF - Fuel Tanks
C3: Ravenswood Operations | K3: Enter all tanks that have been used during the year. Volatilisation from tanks can be a significant source of hydrocarbon related substances to the atmosphere. Where tanks are not Fixed Roof Storage, please specify
C4: 01/07/2023 - 30/06/2024 | K4: Diesel which is loaded into a fuel pod on a service truck should be entered as a secondary tank
K5: Once you have the fuel database data from Carole, group the data for each tank (e.g., "POD 851837"), then create a pivot table to determine the fuel use for each tank. Update the values in red.
C6: Diesel Storage in Fixed Roof Storage Tanks
L7: Data Sources: | N7: RG Fuel Database - Carole, Fuel invoices - Julie/Carole (need these for QAQC)
D9: Tank name or code number | E9: Fuel Type | F9: FY2023 Throughput | G9: FY2024 Throughput | I9: FY2023 Deliveries | J9: FY2024 Deliveries | K9: Unit | L9: Jul Opening Balance | N9: Monthly Deliveries | AA9: Jun Closing Balance | AC9: Orientation/ Buried | AD9: Capacity | AE9: Unit
N10: Jul | O10: Aug | P10: Sep | Q10: Oct | R10: Nov | S10: Dec | T10: Jan | U10: Feb | V10: Mar | W10: Apr | X10: May | Y10: Jun
C11: Primary Tanks | D11: Sarsfield (self-bunded) | E11: Diesel | F11: 24346568 | G11: =J11+L11 -> 24165678 | I11: 24244168 | J11: =SUM(N11:Y11) -> 24159478 | K11: L | L11: 6200 | N11: 2007687 | O11: 1863936 | P11: 1986870 | Q11: 1970499 | R11: 2139412 | S11: 2062816 | T11: 2077029 | U11: 1842639 | V11: 2043938 | W11: 2171280 | X11: 2099708 | Y11: 1893664 | AA11: 108000 | AC11: Horizontal | AD11: =54000+69600 -> 123600 | AE11: L
D12: Nolans Diesel Tank | E12: Diesel | F12: 259559 | G12: =J12+L12 -> 293555 | I12: 255109 | J12: =SUM(N12:Y12) -> 285855 | K12: L | L12: 7700 | N12: 27548 | O12: 18168 | P12: 21215 | Q12: 22469 | R12: 21751 | S12: 16001 | T12: 31992 | U12: 24981 | V12: 30872 | W12: 23173 | X12: 24048 | Y12: 23637 | AA12: 6800 | AC12: Horizontal | AD12: 15000 | AE12: L
D13: Pensar | E13: Diesel | F13: 1205284 | G13: =J13+L13 -> 1511138 | I13: 1170184 | J13: =SUM(N13:Y13) -> 1469438 | K13: L | L13: 41700 | N13: 67979 | O13: 75232 | P13: 58375 | Q13: 166677 | R13: 125571 | S13: 92463 | T13: 139506 | U13: 111511 | V13: 165707 | W13: 197452 | X13: 142483 | Y13: 126482 | AA13: 48000 | AC13: Horizontal | AD13: 65570 | AE13: L
D14: RG Power Station | E14: Diesel | F14: 17614711 | G14: =J14+L14 -> 24736632 | I14: 17493811 | J14: =SUM(N14:Y14) -> 24391382 | K14: L | L14: 345250 | N14: 1913069 | O14: 1478560 | P14: 1846962 | Q14: 2390616 | R14: 2212561 | S14: 2236883 | T14: 2018078 | U14: 2024285 | V14: 1660743 | W14: 2388446 | X14: 2161047 | Y14: 2060132 | AA14: 68000 | AC14: Horizontal | AD14: 124000 | AE14: L
E15: Diesel | G15: =J15+L15 -> 0 | J15: =SUM(N15:Y15) -> 0 | K15: [select] | AC15: [select] | AE15: [select]
E16: Diesel | G16: =J16+L16 -> 0 | J16: =SUM(N16:Y16) -> 0 | K16: [select] | AC16: [select] | AE16: [select]
C18: Total Deliveries | F18: 43426122 | G18: =SUM(G11:G16) -> 50707003 | I18: 43163272 | J18: =SUM(J11:J16) -> 50306153 | L18: =SUM(L11:L16) -> 400850 | N18: =SUM(N11:N16) -> 4016283 | O18: =SUM(O11:O16) -> 3435896 | P18: =SUM(P11:P16) -> 3913422 | Q18: =SUM(Q11:Q16) -> 4550261 | R18: =SUM(R11:R16) -> 4499295 | S18: =SUM(S11:S16) -> 4408163 | T18: =SUM(T11:T16) -> 4266605 | U18: =SUM(U11:U16) -> 4003416 | ... Y18: =SUM(Y11:Y16) -> 4103915 | AA18: =SUM(AA11:AA16) -> 230800
C20: Secondary Tanks | D20: Eagle Drilling Fuel Pod | E20: Diesel | F20: 35268.61 | G20: =J20+L20 -> 51429.04 | I20: 35268.61 | J20: =SUM(N20:Y20) -> 51429.04 | K20: L | Q20: 7942.14 | R20: 15976.63 | U20: 15038.21 | V20: 6665.18 | W20: 3249.15 | X20: =132.33+66.75 -> 199.08 | Y20: 2358.65 | AC20: Horizontal | AE20: [select]
D21: Fuel Pods | E21: Diesel | F21: 373615.77 | G21: =J21+L21 -> 206178.19 | I21: 373615.77 | J21: =SUM(N21:Y21) -> 206178.19 | K21: L | N21: =5164.81+1260.72+186.9+321.63 -> 6934.06 | O21: =399.27+265.54+898.51+6063+228.79+770.57 -> 8625.68 | P21: =109.74+440+843.48+186.56+179.62+199.14+327.51+244.93+217.54+5811.69 -> 8560.21 | Q21: =1697 -> 1697 | R21: =2042.29+401.55+216.73+430 -> 3090.57 | S21: =1356.79+403.3+53.73+308.46 -> 2122.28 | T21: =1661.73+3175+35+308.41 -> 5180.14 | U21: =1337.77+4750+12.63+305.53+3962.34 -> 10368.27 | V21: =310+7765+2680.29+39.27+358.92+3220+783.76+1134.17+1343.6 -> 17635.01 | W21: =22442+4724.68+410.2+297.98+1940+4550+3315+2862.67 -> 40542.53 | X21: =23736+16690+6961.16+197.91+135.84+2510+280+9900+1180+2950+137.92 -> 64678.83 | Y21: =27277+787.61+1520+5759+1400 -> 36743.61 | AC21: Horizontal | AE21: [select]
D22: POD 851837 NPE | E22: Diesel | F22: 72196 | G22: =J22+L22 -> 212687 | I22: 72196 | J22: =SUM(N22:Y22) -> 212687 | K22: L | N22: 13635 | O22: 14920 | P22: 11290 | Q22: 12128 | R22: 10280 | S22: 9497 | T22: 17966 | U22: 13706 | V22: 23280 | W22: 39455 | X22: 24480 | Y22: 22050 | AC22: Horizontal | AE22: [select]
D23: POD 851839 NPE | E23: Diesel | F23: 108456 | G23: =J23+L23 -> 303158 | I23: 108456 | J23: =SUM(N23:Y23) -> 303158 | K23: L | N23: 15930 | O23: 13690 | P23: 22530 | Q23: 13640 | R23: 18980 | S23: 17847 | T23: 28683 | U23: 22220 | V23: 32640 | W23: 53115 | X23: 37153 | Y23: 26730 | AC23: Horizontal | AE23: [select]
D24: POD 851828 NPE | E24: Diesel | F24: 55922 | G24: =J24+L24 -> 158141.61 | I24: 55922 | J24: =SUM(N24:Y24) -> 158141.61 | K24: L | N24: 8128 | O24: 7970 | P24: 9871.61 | Q24: 9734 | R24: 10610 | S24: 9198 | T24: 17477 | U24: 8980 | V24: 16995 | W24: 22225 | X24: 19290 | Y24: 17663 | AC24: Horizontal | AE24: [select]
D25: POD/PUMP 554404 | E25: Diesel | F25: 21418 | G25: =J25+L25 -> 12510 | I25: 21418 | J25: =SUM(N25:Y25) -> 12510 | K25: L | N25: 910 | O25: 1680 | P25: 580 | Q25: 1111 | R25: 2079 | S25: 1290 | T25: 480 | U25: 2300 | V25: 2080 | AC25: Horizontal | AE25: [select]
D26: RMS BULK TANK | E26: Diesel | F26: 150939.1 | G26: =J26+L26 -> 0 | I26: 150939.1 | J26: =SUM(N26:Y26) -> 0 | K26: L | AC26: Horizontal | AE26: [select]
D27: ST522 | E27: Diesel | F27: 300 | G27: =J27+L27 -> 0 | I27: 300 | J27: =SUM(N27:Y27) -> 0 | K27: L | AC27: Horizontal | AE27: [select]
D28: ST551 | E28: Diesel | F28: 118825.36 | G28: =J28+L28 -> 147354.9 | I28: 118825.36 | J28: =SUM(N28:Y28) -> 147354.9 | K28: L | N28: 630 | O28: 830 | P28: 730 | Q28: 380 | R28: 600 | S28: 540 | T28: 780 | U28: 110 | V28: 142276.98 | W28: 340 | X28: 137.92 | AC28: Horizontal | AE28: [select]
D29: ST08 | E29: Diesel | F29: 11916.57 | G29: =J29+L29 -> 0 | I29: 11916.57 | J29: =SUM(N29:Y29) -> 0 | K29: L | AC29: Horizontal | AE29: [select]
D30: SDH67 TRAILER POD DYNA - SDH67 | E30: Diesel | F30: 38192.95 | G30: =J30+L30 -> 222.39 | I30: 38192.95 | J30: =SUM(N30:Y30) -> 222.39 | K30: L | V30: 222.39 | AC30: Horizontal | AE30: [select]
D31: TK200 12000LT BULK TANK - CIRCUIT 1 | E31: Diesel | F31: 98401.3 | G31: =J31+L31 -> 0 | I31: 98401.3 | J31: =SUM(N31:Y31) -> 0 | K31: L | AC31: Horizontal | AE31: [select]
D32: TK201 DIESEL FUEL POD | E32: Diesel | F32: 91575.63 | G32: =J32+L32 -> 185350.28 | I32: 91575.63 | J32: =SUM(N32:Y32) -> 185350.28 | K32: L | N32: 13094.55 | O32: 20549.33 | P32: 20480.13 | Q32: 17091.97 | R32: 22693.51 | S32: 11976.27 | T32: 28764.91 | U32: 12881.22 | V32: 15306.38 | W32: 13172.45 | X32: 8454.16 | Y32: 885.4 | AC32: Horizontal | AE32: [select]
D33: SDH85 POD - 686HBQ | E33: Diesel | F33: 4045.62 | G33: =J33+L33 -> 2258.25 | I33: 4045.62 | J33: =SUM(N33:Y33) -> 2258.25 | K33: L | P33: 2258.25 | AC33: Horizontal | AE33: [select]
D34: ST801 SPARE 30,000L FILL FOB - ST801 | E34: Diesel | F34: 184057.9 | G34: =J34+L34 -> 76479.25 | I34: 184057.9 | J34: =SUM(N34:Y34) -> 76479.25 | K34: L | N34: 6458.7 | O34: 3995.9 | P34: 2049.5 | Q34: 7368.3 | R34: 1774.1 | S34: 8499.8 | T34: 37668.95 | U34: 4923.2 | V34: 1336.6 | W34: 1361.1 | X34: 665.5 | Y34: 377.6 | AC34: Horizontal | AE34: [select]
D35: ST04 Roc-Drill | E35: Diesel | G35: =J35+L35 -> 1165807.7 | J35: =SUM(N35:Y35) -> 1165807.7 | K35: L | N35: 110233.93 | O35: 108477.17 | P35: 130024.08 | Q35: 155403.16 | R35: 168922.7 | S35: 136532.41 | T35: 143072.07 | U35: 127175.18 | V35: 56592.34 | W35: 27427.02 | X35: 1368.06 | Y35: 579.53 | AC35: [select] | AE35: [select]
D36: ST550 | E36: Diesel | G36: =J36+L36 -> 0 | J36: =SUM(N36:Y36) -> 0 | K36: L | AC36: [select] | AE36: [select]
D37: Pensar Fuel Pod 022A23 | E37: Diesel | G37: =J37+L37 -> 62907.38 | J37: =SUM(N37:Y37) -> 62907.38 | K37: L | S37: 62907.38 | AC37: [select] | AE37: [select]
C39: Total Secondary Tank Throughput | F39: 1365130.8 | G39: =SUM(G20:G37) -> 2584483.9 | I39: 1365130.8 | J39: =SUM(J20:J37) -> 2584483.9 | L39: =SUM(L20:L37) -> 0 | N39: =SUM(N20:N37) -> 175954.24 | O39: =SUM(O20:O37) -> 180738.08 | P39: =SUM(P20:P37) -> 208373.78 | Q39: =SUM(Q20:Q37) -> 226495.57 | R39: =SUM(R20:R37) -> 255006.51 | S39: =SUM(S20:S37) -> 260410.14 | T39: =SUM(T20:T37) -> 280072.07 | U39: =SUM(U20:U37) -> 217702.08 | ... Y39: =SUM(Y20:Y37) -> 107387.79 | AA39: =SUM(AA20:AA37) -> 0
C41: Other Fuel Tanks
C43: Other Fuel Tanks | D43: ULP Tank | E43: ULP | G43: =J43+L43 -> 0 | J43: =SUM(N43:Y43) -> 0 | K43: [select] | AC43: [select] | AE43: [select]
E44: [select] | G44: =J44+L44 -> 0 | J44: =SUM(N44:Y44) -> 0 | K44: [select] | AC44: [select] | AE44: [select]
E45: [select] | G45: =J45+L45 -> 0 | J45: =SUM(N45:Y45) -> 0 | K45: [select] | AC45: [select] | AE45: [select]
E46: [select] | G46: =J46+L46 -> 0 | J46: =SUM(N46:Y46) -> 0 | K46: [select] | AC46: [select] | AE46: [select]
C49: All fuel storage tanks that have a breather vent must be recorded
C50: Primary tanks have fuel delivered directly from the fuel supplier. A secondary tank only receives fuel from the primary tank. Total fuel use on site is aggregated from primary tanks only to avoid double counting
C52: Paste raw data below:
C53: Note from Carole: the Smartfill counters / systems failed around September / October 2023 and maintenance failed to get the systems fixed. What this means is that we don’t have a 100% accurate split of what fuel went to the specific pieces of equipment. Liquip are coming out to site on the 9th of this month to fix everything – this however doesn’t help us with an accurate distribution of fuel for the past 8 to 10 months.

Sheet CWF - Point Source Energy
C3: Ravenswood Operations | G3: Enter all power generators (>500kW) and other sources of point souce emissions
C4: 01/07/2023 - 30/06/2024 | G4: Point source emissions are directed into a vent or stack and emitted through a single point source into the atmosphere.
C6: Point Source Energy - Fuel Use and Electricity Production
G8: Data Source: | I8: Pronto - Stock Issues 103570 (772256) (talk to Murray to get an export of stock issues from Pronto), created pivot table to identify monthly Qty of LPG. Used allocation ratio to determine how much LPG each plant item uses. Origin Energy - bulk supplied (get invoices for this from Julie/Carole - we need the invoices for QAQC),
C9: Process Heating
I10: Fuel Used | V10: Allocation Ratio (%)
C11: Class | D11: Name | E11: Fuel Type (1) | F11: FY2023 Fuel | G11: FY2024 Fuel | H11: Unit | I11: Jul | J11: Aug | K11: Sep | L11: Oct | M11: Nov | N11: Dec | O11: Jan | P11: Feb | Q11: Mar | R11: Apr | S11: May | T11: Jun
C12: Boilers | D12: Glycol Boiler | E12: LPG | F12: 186204.4 | G12: =SUM(I12:T12) -> 337493 | H12: L | I12: 21014 | J12: 31361 | K12: 22777 | L12: 16468 | M12: 39135 | N12: 16406 | O12: 29568 | P12: 21210 | Q12: 42641 | R12: 29445 | S12: 26528 | T12: 40940 | V12: 50
C13: Furnaces | D13: Gold Room Furnace | E13: LPG | F13: 18620.44 | G13: =SUM(I13:T13) -> 33750 | H13: L | I13: 2101 | J13: 3136 | K13: 2278 | L13: 1647 | M13: 3914 | N13: 1641 | O13: 2957 | P13: 2121 | Q13: 4264 | R13: 2944 | S13: 2653 | T13: 4094 | V13: 5
C14: Furnaces | D14: Laboratory Muffle Furnace | E14: LPG | F14: 18620.44 | G14: =SUM(I14:T14) -> 33750 | H14: L | I14: 2101 | J14: 3136 | K14: 2278 | L14: 1647 | M14: 3914 | N14: 1641 | O14: 2957 | P14: 2121 | Q14: 4264 | R14: 2944 | S14: 2653 | T14: 4094 | V14: 5
C15: Kilns | D15: Kilns/Boilers (Gold Processing) | E15: LPG | F15: 148963.52 | G15: =SUM(I15:T15) -> 269996 | H15: L | I15: 16812 | J15: 25089 | K15: 18222 | L15: 13174 | M15: 31308 | N15: 13125 | O15: 23654 | P15: 16968 | Q15: 34113 | R15: 23556 | S15: 21223 | T15: 32752 | V15: 40
E16: [select] | H16: [select]
E17: [select] | H17: [select]
C19: Total LPG Usage | E19: LPG | F19: 372408.8 | G19: =SUM(I19:T19) -> 674986.9 | H19: L | I19: 42028.9 | J19: 62722.7 | K19: 45553.9 | L19: 32935.2 | M19: 78270.2 | N19: 32812.2 | O19: 59135.1 | P19: 42420.6 | Q19: 85282.6 | R19: 58889.8 | S19: 53056.5 | T19: 81879.2 | V19: =SUM(V12:V17) -> 100
C21: Pollution Control
C22: Class | D22: Name | E22: Engine Power Rating (kW) | F22: Pollution Control, please list | G22: Date Installed | H22: Total Operating Hours | I22: Unit Type/Size?
C23: Other Point Source | D23: Glycol Boiler | E23: 1500 | F23: None | I23: LPG (N/A)
D24: Gold Room Furnace | E24: 30 | F24: None | I24: LPG (N/A)
D25: Laboratory Muffle Furnace | E25: 30 | F25: None | I25: LPG (N/A)
D26: Kilns/Boilers (Gold Processing) | E26: 350 | F26: None | I26: LPG (N/A)
F27: [select] | I27: [select]
F28: [select] | I28: [select]
C30: Other Unit Size | D30: Other Point Source | E30: Engine
C31: [select] | D31: [select] | E31: [select]
C32: LPG (N/A) | D32: None | E32: None
C33: Nat Gas/Diesel Boiler - Large (>100 GJ/hr or >30MW) | D33: Cyclone | E33: Selective Catalyctic Reduction
C34: Nat Gas/Diesel Boiler - Small (<100 GJ/hr or <30MW) | D34: Cyclone (high efficiency) | E34: Water / Steam Injection
C35: Coal PC Drybottom | D35: Cyclone (high throughput) | E35: Air / Fuel Ratio: n/a
C36: Coal PC Wetbottom | D36: Electostatic precipitator | E36: Air / Fuel Ratio: + 3%
C37: Coal Cyclone | D37: ESP with carbon injection | E37: Air / Fuel Ratio: +/- 10%
C38: Coal FBC Circulating | D38: ESP with polishing wet scrubber | E38: Injection Rate Setting: n/a
C39: Coal FBC Bubbling | D39: Fabric filter | E39: Injection Rate Setting: + 0%
C40: Coal Spreader Stocker | D40: Fabric filter with carbon injection | E40: Injection Rate Setting: + 10%
C41: Coal Overfeed Stocker | D41: Fabric filter with polishing wet scrubber | E41: Injection Rate Setting: + 20%
C42: Coal Underfeed Stocker | D42: Fabric filter with spray absorbers (absorbent) | E42: Injection Rate Setting: + 30%
D43: Fabric filter with spray absorbers (limestone) | E43: Injection Timing Retard: Controlled
D44: Low excess air | E44: Injection Timing Retard: Uncontrolled
D45: Low NOX burner (air staged) | E45: Injection Timing Retard: 2C
D46: Low NOx burner (flue gas recirculation) | E46: Injection Timing Retard: + 4C
D47: Low NOX burner (fuel staged) | E47: Injection Timing Retard: + 8C
D48: Multicyclone
D49: Overfire air
D50: Scrubber (condensation)
D51: Scrubber (dry)
D52: Scrubber (impingement)
D53: Scrubber (orifice)
D54: Scrubber (semi-dry)
D55: Scrubber (venturi)
D56: Scrubber (wet)
D57: Scrubber (wet) with conditioning agent
D58: Selective catalytic reduction
D59: Selective non-catalytic reduction
D60: Selective non-catalytic reduction with low NOx burner
C62: If a station is dual fired, for example using gas and diesel, insert a new row and enter the station name twice. Enter one row as gas, the other as diesel
B63: (1) | C63: Brown coal has a gross calorific value less than 17,435kj/kj and greater than 31% volatile matter on a dry mineral free base
C65: Paste raw data below: Invoices from Carole saved in Sharepoint folder.
B66: Item Code | C66: Product Group | D66: UOM | E66: Trans Date | F66: Warehouse | G66: Trans Type | H66: Trans Account Code | I66: Reference 1 | J66: Reference 2 | K66: Reference 3 | L66: Batch Reference | M66: Quantity | N66: Cost | O66: Value
B67: 103570 - PROPANE LIQUID PROPANE GAS BULK DELIVERY | C67: PROP - PROPANE | D67: Litre | E67: 31/07/2023 | F67: NOL - Nolan Main Warehouse | G67: Component Used | I67: INT ISSUE | J67: 10401341190 | K67: A:314 | L67: 0060NT | M67: -42028.9 | N67: -40124.99 | O67: 0
B68: 103570 - PROPANE LIQUID PROPANE GAS BULK DELIVERY | C68: PROP - PROPANE | E68: 31/08/2023 | F68: NOL - Nolan Main Warehouse | G68: Component Used | I68: INT ISSUE | J68: 10401341190 | K68: A:314 | L68: 0064SH | M68: -483 | N68: -475.18 | O68: 0
B69: 103570 - PROPANE LIQUID PROPANE GAS BULK DELIVERY | C69: PROP - PROPANE | E69: 31/08/2023 | F69: NOL - Nolan Main Warehouse | G69: Component Used | I69: INT ISSUE | J69: 10401341190 | K69: A:314 | L69: 0064SD | M69: -62239.7 | N69: -61231.41 | O69: 0
B70: 103570 - PROPANE LIQUID PROPANE GAS BULK DELIVERY | C70: PROP - PROPANE | E70: 30/09/2023 | F70: NOL - Nolan Main Warehouse | G70: Component Used | I70: INT ISSUE | J70: 10401341190 | K70: A:470 | L70: 0068YF | M70: -45553.9 | N70: -47530.94 | O70: 0
B71: 103570 - PROPANE LIQUID PROPANE GAS BULK DELIVERY | C71: PROP - PROPANE | E71: 31/10/2023 | F71: NOL - Nolan Main Warehouse | G71: Component Used | I71: INT ISSUE | J71: 10401341190 | K71: A:314 | L71: 006F11 | M71: -32935.2 | N71: -35800.56 | O71: 0
B72: 103570 - PROPANE LIQUID PROPANE GAS BULK DELIVERY | C72: PROP - PROPANE | E72: 30/11/2023 | F72: NOL - Nolan Main Warehouse | G72: Component Used | I72: INT ISSUE | J72: 10401341190 | K72: A:314 | L72: 006KZQ | M72: -78270.2 | N72: -87592.18 | O72: 0
B73: 103570 - PROPANE LIQUID PROPANE GAS BULK DELIVERY | C73: PROP - PROPANE | E73: 31/12/2023 | F73: NOL - Nolan Main Warehouse | G73: Component Used | I73: INT ISSUE | J73: 10401341190 | K73: A:470 | L73: 006QKR | M73: -32812.2 | N73: -36667.63 | O73: 0
B74: 103570 - PROPANE LIQUID PROPANE GAS BULK DELIVERY | C74: PROP - PROPANE | E74: 31/01/2024 | F74: NOL - Nolan Main Warehouse | G74: Component Used | I74: INT ISSUE | J74: 10401341190 | K74: A:470 | L74: 006WB3 | M74: -59135.1 | N74: -66042.08 | O74: 0
B75: 103570 - PROPANE LIQUID PROPANE GAS BULK DELIVERY | C75: PROP - PROPANE | E75: 45414 | F75: NOL - Nolan Main Warehouse | G75: Component Used | I75: INT ISSUE | J75: 10401341190 | K75: A:470 | L75: 006WB0 | M75: -59135.1 | N75: -66042.08 | O75: 0
B76: 103570 - PROPANE LIQUID PROPANE GAS BULK DELIVERY | C76: PROP - PROPANE | E76: 45414 | F76: NOL - Nolan Main Warehouse | G76: Component Used | I76: INT ISSUE | J76: 10401341190 | K76: A:470 | L76: 006WB1 | M76: 59135.1 | N76: 66042.08 | O76: 0
B77: 103570 - PROPANE LIQUID PROPANE GAS BULK DELIVERY | C77: PROP - PROPANE | E77: 28/02/2024 | F77: NOL - Nolan Main Warehouse | G77: Component Used | I77: INT ISSUE | J77: 10401341190 | K77: A:314 | L77: 0070WM | M77: -42420.6 | N77: -48580.07 | O77: 0
B78: 103570 - PROPANE LIQUID PROPANE GAS BULK DELIVERY | C78: PROP - PROPANE | E78: 31/03/2024 | F78: NOL - Nolan Main Warehouse | G78: Component Used | I78: INT ISSUE | J78: 10401341190 | K78: A:314 | L78: 0075YN | M78: -85282.6 | N78: -99013.1 | O78: 0
B79: 103570 - PROPANE LIQUID PROPANE GAS BULK DELIVERY | C79: PROP - PROPANE | E79: 30/04/2024 | F79: NOL - Nolan Main Warehouse | G79: Component Used | I79: INT ISSUE | J79: 10401341190 | K79: A:470 | L79: 007B9F | M79: -58889.8 | N79: -68053.05 | O79: 0
B80: 103570 - PROPANE LIQUID PROPANE GAS BULK DELIVERY | C80: PROP - PROPANE | E80: 31/05/2024 | F80: NOL - Nolan Main Warehouse | G80: Component Used | I80: INT ISSUE | J80: 10401341190 | K80: A:470 | L80: 007HKK | M80: -53056.5 | N80: -61386.37 | O80: 0
B81: 103570 - PROPANE LIQUID PROPANE GAS BULK DELIVERY | C81: PROP - PROPANE | E81: 30/06/2024 | F81: NOL - Nolan Main Warehouse | G81: Component Used | I81: INT ISSUE | J81: 10401341190 | K81: A:470 | L81: 007MPY | M81: -81879.2 | N81: -94292.09 | O81: 0
B82: 103570 - PROPANE LIQUID PROPANE GAS BULK DELIVERY - Total | M82: -674986.9 | N82: -746789.65 | O82: 0
B83: Overall - Total | M83: -674986.9 | N83: -746789.65 | O83: 0
B84: Monday, 12-Aug-202412:16:29 PMUser: murray.lonerganPO | G84: 1 | L84: Pronto Xi Business Intelligence with IBM Cognos

Sheet CWF-Plant and Equipment-Diesel
C3: Ravenswood Operations | H3: This tab captures fuel use and dust emissions from vehicles and unmetered engines
C4: 01/07/2023 - 30/06/2024 | H4: Once you have the fuel database data from Carole, group similar equipment using the identifiers in column E (GB Classification), then create a pivot table to determine the fuel use for each group. Update the values in red.
C6: Diesel Usage and Operational Data by Engine Class
H8: Data Sources: | K8: Fuel Database - Email Carole for data dump.
C9: Engines
C10: (1) Smooth roads are typically sealed and well-formed unsealed roads, while rough roads are any poorly-formed unsealed roads and steep/poorly graded tracks.
K11: Monthly Diesel Fuel Combustion | X11: % Use on Site | Y11: Number of Vehicles
C12: Class of Vehicle (1) | D12: Owned / Contractor Name | E12: GB Classification | G12: FY2023 Fuel | H12: FY2024 Fuel | I12: Unit | K12: Jul | L12: Aug | M12: Sep | N12: Oct | O12: Nov | P12: Dec | Q12: Jan | R12: Feb | S12: Mar | T12: Apr | U12: May | V12: Jun | X12: % Use on Site
C13: Bobcat | E13: RAV Vehicles (Bobcat) | G13: 0 | H13: =SUM(K13:V13) -> 0 | I13: L | X13: 100 | Y13: FILL OUT
C14: Bus | E14: RAV Vehicles (Bus) | G14: 17155.8 | H14: =SUM(K14:V14) -> 16712.62 | I14: L | K14: 967.58 | L14: 1636.63 | M14: 1529.01 | N14: 831.15 | O14: 1671.68 | P14: 1127.18 | Q14: 1304.29 | R14: 1897.36 | S14: 1897.36 | T14: 2140.7 | U14: 1709.68 | X14: 100 | Y14: FILL OUT
C15: Bogger | E15: RAV Vehicles (Bogger) | G15: 0 | H15: =SUM(K15:V15) -> 0 | I15: L | X15: 100 | Y15: FILL OUT
C16: Compressor (<450kW) | E16: RAV Vehicles (Compressor) | G16: 3348.1687 | H16: =SUM(K16:V16) -> 2191.3 | I16: L | K16: 410 | L16: 120 | M16: 227.1 | N16: 298.4 | O16: 164.1 | P16: 263.8 | Q16: 335.1 | R16: 46.6 | S16: 46.6 | T16: 154.2 | U16: 125.4 | X16: 100 | Y16: FILL OUT
C17: Concrete/Shotcrete Truck | E17: RAV Vehicles (Concrete Truck) | G17: 0 | H17: =SUM(K17:V17) -> 0 | I17: L | X17: 100 | Y17: FILL OUT
C18: Crane | E18: RAV Vehicles (Crane) | G18: 13362.2 | H18: =SUM(K18:V18) -> 2900.09 | I18: L | L18: 212.33 | O18: 220.47 | P18: 306.06 | Q18: 398.6 | R18: 372.5 | S18: 372.5 | T18: 590.75 | U18: 426.88 | X18: 79 | Y18: FILL OUT
C19: Dozer (Track Type) | E19: RAV Vehicles (Dozer - Tracked) | G19: 1854472.5 | H19: =SUM(K19:V19) -> 1831486 | I19: L | K19: 165650.8 | L19: 134663.87 | M19: 148848.1 | N19: 168020.58 | O19: 164213.5 | P19: 153484.4 | Q19: 144452.6 | R19: 108971.2 | S19: 108971.2 | T19: 166448.9 | U19: 167775.27 | V19: 199985.58 | X19: 100 | Y19: FILL OUT
C20: Drill (Surface) (<450kW) | E20: RAV Vehicles (Drill - Surface) | G20: 369693.68 | H20: =SUM(K20:V20) -> 1346935.9 | I20: L | K20: 110288.88 | L20: 108646.96 | M20: 130131.5 | N20: 163429.95 | O20: 185127.87 | P20: 136631.71 | Q20: 144961.78 | R20: 153111.94 | S20: 153111.94 | T20: 45353.84 | U20: 13136.64 | V20: 3002.84 | X20: 100 | Y20: FILL OUT
C21: EWP | E21: RAV Vehicles (EWP) | G21: 430 | H21: =SUM(K21:V21) -> 35 | I21: L | Q21: 35 | X21: 100 | Y21: FILL OUT
C22: Excavator (<450kW) | E22: RAV Vehicles (Excavator <450kW) | G22: 5123188 | H22: =SUM(K22:V22) -> 4371536.5 | I22: L | K22: 358694.2 | L22: 348509.6 | M22: 436572.82 | N22: 385985.09 | O22: 426102.76 | P22: 405860.5 | Q22: 374098.48 | R22: 234758.72 | S22: 234758.72 | T22: 389546.15 | U22: 357497.7 | V22: 419151.8 | X22: 100 | Y22: FILL OUT
C23: Excavator (>450kW) | E23: RAV Vehicles (Excavator >450kW) | G23: 0 | H23: =SUM(K23:V23) -> 0 | I23: L | X23: 100 | Y23: FILL OUT
C24: Forklift | E24: RAV Vehicles (Forklift) | G24: 13785.338 | H24: =SUM(K24:V24) -> 20453.9 | I24: L | K24: 4094.07 | L24: 1101.64 | M24: 3564.6 | N24: 6964.22 | O24: 725.43 | P24: 531.4 | Q24: 551.44 | R24: 863.77 | S24: 863.77 | T24: 356.17 | U24: 595.39 | V24: 242 | X24: 100 | Y24: FILL OUT
C25: Field Generator (<450kW) | E25: RAV Vehicles (Generator <500kW <100,000 kWhrs) | G25: 1746424.7 | H25: =SUM(K25:V25) -> 123839.89 | I25: L | K25: 10997.7 | L25: 9976.3 | M25: 6076.9 | N25: 11992.095 | O25: 8355.1 | P25: 5399 | Q25: 15542.8 | R25: 3721.9 | S25: 3721.9 | T25: 21801.2 | U25: 21245.1 | V25: 5009.9 | X25: 100 | Y25: FILL OUT
C26: Field Generator (>500kW) | E26: RAV vehicle (Power Plant Generator) | G26: 12697371 | H26: =SUM(K26:V26) -> 25288078 | I26: L | K26: 1937868 | L26: 1520480 | M26: 1971468 | N26: 2463846 | O26: 2192819 | P26: 2308483 | Q26: 1996950 | R26: 2036285 | S26: 2036285 | T26: 2420764 | U26: 2054270 | V26: 2348560 | X26: 100 | Y26: FILL OUT
C27: Grader | E27: RAV Vehicles (Grader) | G27: 197596.11 | H27: =SUM(K27:V27) -> 252404.48 | I27: L | K27: 20211.08 | L27: 17050.9 | M27: 19690.91 | N27: 22161.46 | O27: 24337.44 | P27: 24008.91 | Q27: 21649.7 | R27: 14714.1 | S27: 14714.1 | T27: 22296.38 | U27: 25653.7 | V27: 25915.8 | X27: 100 | Y27: FILL OUT
C28: Haul/Dump Truck | E28: RAV Vehicles (Haul Truck) | G28: 11874044 | H28: =SUM(K28:V28) -> 13008539 | I28: L | K28: 1025675 | L28: 931880.82 | M28: 923727.52 | N28: 958782.68 | O28: 989826.61 | P28: 1099107.4 | Q28: 946960.48 | R28: 1292265.2 | S28: 1292265.2 | T28: 1196069.4 | U28: 1170660.2 | V28: 1181318.3 | X28: 100 | Y28: FILL OUT
C29: IT Loader | E29: RAV Vehicles (IT Loader) | G29: 22383.53 | H29: =SUM(K29:V29) -> 6984.26 | I29: L | K29: 175.43 | L29: 611.35 | M29: 503.42 | N29: 770.14 | O29: 730.31 | P29: 699.15 | Q29: 767.44 | R29: 867.31 | S29: 867.31 | T29: 340.39 | U29: 612.01 | V29: 40 | X29: 100 | Y29: FILL OUT
C30: Light Truck | E30: RAV Vehicles (Light Truck) | G30: 156358.59 | H30: =SUM(K30:V30) -> 78855.75 | I30: L | K30: 3526.26 | L30: 6886 | M30: 4485.7 | N30: 10148.7 | O30: 11903.14 | P30: 7511.59 | Q30: 9100.46 | R30: 8561.09 | S30: 8561.09 | T30: 3875.2 | U30: 3928.73 | V30: 367.79 | X30: 84 | Y30: FILL OUT
C31: Light Vehicle | E31: RAV Vehicles (Light Vehicle Post-2004) | G31: 605301.85 | H31: =SUM(K31:V31) -> 399646.61 | I31: L | K31: 32090.63 | L31: 33693.13 | M31: 25097.36 | N31: 26147.15 | O31: 38377.12 | P31: 32615.78 | Q31: 32033.51 | R31: 30893.66 | S31: 30893.66 | T31: 35159.77 | U31: 73818.92 | V31: 8825.92 | X31: 77 | Y31: FILL OUT
C32: Lighting Plant (<450kW) | E32: RAV Vehicles (Lighting Plant) | G32: 42579.37 | H32: =SUM(K32:V32) -> 79940.35 | I32: L | K32: 4768.43 | L32: 5029.3 | M32: 7687.16 | N32: 6023.17 | O32: 4119.06 | P32: 9623.1 | Q32: 4356.8 | R32: 11309.46 | S32: 11309.46 | T32: 5123.01 | U32: 5712.1 | V32: 4879.3 | X32: 100 | Y32: FILL OUT
C33: Loader (Wheeled) | E33: RAV Vehicles (Loader - Wheeled) | G33: 2691730.3 | H33: =SUM(K33:V33) -> 2076974.7 | I33: L | K33: 191998.35 | L33: 154583.36 | M33: 153321.23 | N33: 163542.29 | O33: 153620.26 | P33: 200962.94 | Q33: 187186.68 | R33: 120877.69 | S33: 120877.69 | T33: 203894.95 | U33: 214987.36 | V33: 211121.88 | X33: 100 | Y33: FILL OUT
C34: Mobile Screen (<450kW) | E34: RAV Vehicles (Mobile Screen) | G34: 97.5 | H34: =SUM(K34:V34) -> 0 | I34: L | X34: 100 | Y34: FILL OUT
C35: Mobile Stacker (<450kW) | E35: RAV Vehicles (Mobile Stacker) | G35: 273.33 | H35: =SUM(K35:V35) -> 0 | I35: L | X35: 100 | Y35: FILL OUT
C36: Mobile Crusher (<450kW) | E36: RAV Vehicles (Mobiler Crusher) | G36: 133063.65 | H36: =SUM(K36:V36) -> 0 | I36: L | X36: 100 | Y36: FILL OUT
C37: Pump (<450kW) | E37: RAV Vehicles (Pump <450kW) | G37: 101409.93 | H37: =SUM(K37:V37) -> 195822.3 | I37: L | K37: 6277.7 | L37: 11327 | M37: 5469.3 | N37: 21500.7 | O37: 30517.7 | P37: 34809.6 | Q37: 10695.3 | T37: 7930 | U37: 49263 | V37: 18032 | X37: 100 | Y37: FILL OUT
C38: Road Train | E38: RAV Vehicles (Road Train) | G38: 0 | H38: =SUM(K38:V38) -> 0 | I38: L | X38: 100 | Y38: FILL OUT
C39: Roller | E39: RAV Vehicles (Roller) | G39: 62659.702 | H39: =SUM(K39:V39) -> 100202.86 | I39: L | K39: 3350.92 | L39: 3150.73 | M39: 4169.98 | N39: 19032.954 | O39: 11283.21 | P39: 7653.38 | Q39: 8104.15 | R39: 9207.76 | S39: 9207.76 | T39: 14718.32 | U39: 6885.7 | V39: 3438 | X39: 100 | Y39: FILL OUT
C40: Scraper | E40: RAV Vehicles (Scraper) | G40: 213383.48 | H40: =SUM(K40:V40) -> 433620.13 | I40: L | K40: 36724 | L40: 21975.374 | M40: 52025 | N40: 53908.868 | O40: 49942.82 | P40: 25871.87 | Q40: 22854.15 | R40: 43493.82 | S40: 43493.82 | T40: 63331.72 | U40: 18289.69 | V40: 1709 | X40: 100 | Y40: FILL OUT
C41: Service Truck | E41: RAV Vehicles (Service Truck) | G41: 218885.97 | H41: =SUM(K41:V41) -> 0 | I41: L | X41: 100 | Y41: FILL OUT
C42: Tractor | E42: RAV Vehicles (Tractor) | G42: 1393.84 | H42: =SUM(K42:V42) -> 1801.06 | I42: L | M42: 46.96 | N42: 245.63 | O42: 128.07 | P42: 134.66 | Q42: 252.43 | R42: 209.28 | S42: 209.28 | T42: 256.08 | U42: 318.67 | X42: 100 | Y42: FILL OUT
C43: Unspecified | E43: RAV Vehicles (Unspecified) | G43: 85269.87 | H43: =SUM(K43:V43) -> 544093.36 | I43: L | K43: 619.32 | L43: 116026.99 | M43: 155175.47 | N43: 189.5 | O43: 874.4 | P43: 132841.58 | Q43: 15490.72 | R43: 45275.33 | S43: 45275.33 | T43: 8869.26 | U43: 13816.03 | V43: 9639.43 | X43: 100 | Y43: FILL OUT
C44: Water Cart | E44: RAV Vehicles (Water Cart) | G44: 0 | H44: =SUM(K44:V44) -> 180150.49 | I44: L | K44: 10058.85 | L44: 8766.48 | M44: 16423.27 | N44: 14487.1 | O44: 20618.49 | P44: 16461.31 | Q44: 17697.98 | R44: 15725.8 | S44: 15725.8 | T44: 20732.56 | U44: 17315.75 | V44: 6137.1 | X44: 100 | Y44: FILL OUT
C45: Welder (<450kW) | E45: RAV Vehicles (Welder) | G45: 1524.825 | H45: =SUM(K45:V45) -> 5449.8 | I45: L | K45: 100 | L45: 180 | M45: 50 | N45: 174.7 | O45: 201.7 | P45: 2995 | Q45: 781.4 | R45: 359.7 | S45: 359.7 | T45: 247.6 | X45: 100 | Y45: FILL OUT
C46: [select] | H46: =SUM(K46:V46) -> 0 | I46: [select] | X46: 100 | Y46: FILL OUT
C47: [select] | H47: =SUM(K47:V47) -> 0 | I47: [select] | X47: 100 | Y47: FILL OUT
D49: Total Fuel | G49: 38247188 | H49: =SUM(H13:H47) -> 50368654 | K49: =SUM(K13:K47) -> 3924547.2 | L49: =SUM(L13:L47) -> 3436508.8 | M49: =SUM(M13:M47) -> 4066291.3 | N49: =SUM(N13:N47) -> 4498482.5 | O49: =SUM(O13:O47) -> 4315880.2 | P49: =SUM(P13:P47) -> 4607383.3 | Q49: =SUM(Q13:Q47) -> 3956561.3 | R49: =SUM(R13:R47) -> 4133789.1 | ... V49: =SUM(V13:V47) -> 4447376.6
C51: Operating Hours | D51: Greenbase will estimate the operating hours if this information is unable to be provided
K52: Work Area | L52: STEP 1 % In Pit | M52: Fuel Burn Rate
C53: Class of Vehicle | D53: Owner | E53: GB Classification | G53: FY2023 Hours | H53: FY2024 Hours
G54: hr | H54: hr | K54: Option | L54: % | M54: L/hr
C55: Dozer (Track Type) | E55: RAV Vehicles (Dozer - Tracked) | G55: 30401.188 | K55: Buck Reef Waste Dump | L55: 50 | M55: 61
C57: Kilometres Travelled | D57: Greenbase will estimate the kilometres travelled if this information is unable to be provided
C58: The values for distance (column H) are calculated using the fuel burn rate (column P) and the amount of fuel used (from table above, column H "2024 FY Fuel"). Distances are not calculated for stationary equipment (lighting towers, generators, welders etc)
K59: Work Area | L59: STEP 1 % In Pit | M59: STEP 2 % Underground | N59: STEP 3 % Sealed | O59: Mean Vehicle Weight | P59: Fuel Burn Rate | Q59: Average Vehicle Speed | R59: Average Haul Distance
C60: Class of Vehicle | D60: Owner | E60: GB Classification | G60: FY2023 Distance | H60: FY2024 Distance
G61: km | H61: km | K61: Option | L61: % | M61: % | N61: % | O61: Tonne | P61: km/L | Q61: km/hr | R61: km
C62: Ancillary (Other) | E62: RAV Vehicles (Ancillary) | G62: - | K62: Open Area (Haul Roads and Access Tracks)
C63: Bobcat | E63: RAV Vehicles (Bobcat) | G63: - | K63: Open Area (Plant Site - Watering)
C64: Bus | E64: RAV Vehicles (Bus) | G64: 257337 | H64: =H14*P64 -> 250689.3 | K64: Haul Roads and Access Tracks | L64: 0 | M64: 0 | N64: 100 | O64: 16 | P64: 15 | Q64: NA | R64: NA
C65: Ancillary (Other) | E65: RAV Vehicles (Compressor) | G65: - | K65: Open Area (Plant Site - Watering)
C66: Crane | E66: RAV Vehicles (Crane) | G66: 3207 | H66: =H18*P66 -> 0 | K66: Open Area (Plant Site - Watering)
C67: Dozer (Track Type) | E67: RAV Vehicles (Dozer - Tracked) | G67: 327117 | H67: =H19*P67 -> 0 | K67: Open Area (General Open Area)
C68: Drill Rig | E68: RAV Vehicles (Drill - Surface) | G68: 15081 | H68: =H20*P68 -> 0 | K68: Open Area (General Open Area)
C69: EWP | E69: RAV Vehicles (EWP) | G69: 477 | H69: =H21*P69 -> 0 | K69: Open Area (Plant Site - Watering)
C70: Excavator | E70: RAV Vehicles (Excavator) | G70: 539473 | H70: =H22*P70 -> 0 | K70: Open Area (General Open Area)
C71: Ancillary (Other) | E71: RAV Vehicles (Generator <500kW <100,000 kWhrs) | G71: - | K71: Open Area (Plant Site - Watering)
C72: Forklift | E72: RAV Vehicles (Forklift) | G72: 68927 | H72: =H24*P72 -> 0 | K72: Open Area (Plant Site - Watering)
C73: Grader | E73: RAV Vehicles (Grader) | G73: 49399.028 | H73: =H27*P73 -> 0 | K73: Haul Roads and Access Tracks | L73: 30 | M73: 0 | N73: 70 | O73: NA | P73: 0 | Q73: 5 | R73: NA
C74: Haul/Dump Truck | E74: RAV Vehicles (Haul Truck) | G74: 3087251.5 | H74: =H28*P74 -> 0 | K74: Haul Roads and Access Tracks | L74: 50 | M74: 0 | N74: 50 | O74: 80 | P74: 0 | Q74: NA | R74: 30
C75: IT Loader | E75: RAV Vehicles (IT Loader) | G75: 64017 | H75: =H29*P75 -> 0 | K75: Open Area (Plant Site - Watering)
C76: Light Truck | E76: RAV Vehicles (Light Truck) | G76: 469075.77 | H76: =H30*P76 -> 236567.25 | K76: Haul Roads and Access Tracks | L76: 50 | M76: 0 | N76: 50 | O76: 10 | P76: 3 | Q76: NA | R76: NA
C77: Light Vehicle | E77: RAV Vehicles (Light Vehicle Post 2004) | G77: 3026509.3 | H77: =H31*P77 -> 1998233.1 | K77: Haul Roads and Access Tracks | L77: 30 | M77: 0 | N77: 70 | O77: NA | P77: 5 | Q77: 50 | R77: NA
C78: Ancillary (Other) | E78: RAV Vehicles (Lighting Plant) | G78: - | K78: Open Area (General Open Area)
C79: Loader | E79: RAV Vehicles (Loader - Wheeled) | G79: 1803167 | H79: =H33*P79 -> 0 | K79: Open Area (Haul Roads and Access Tracks)
C80: Ancillary (Other) | E80: RAV Vehicles (Mobiler Crusher) | G80: - | K80: Open Area (Plant Site - Watering)
C81: Ancillary (Other) | E81: RAV Vehicles (Mobile Screen) | G81: - | K81: Open Area (Plant Site - Watering)
C82: Ancillary (Other) | E82: RAV Vehicles (Mobile Stacker) | G82: - | K82: Open Area (Plant Site - Watering)
C83: Ancillary (Other) | E83: RAV Vehicles (Pump <450kW) | G83: - | K83: Open Area (Plant Site - Watering)
C84: Roller | E84: RAV Vehicles (Roller) | G84: 6893 | H84: =H39*P84 -> 0 | K84: Open Area (General Open Area)
C85: Road Train | E85: RAV Vehicles (Road Train) | G85: 0 | K85: Haul Roads and Access Tracks | L85: 0 | M85: 0 | N85: 100 | O85: 48 | P85: 1 | Q85: NA | R85: NA
C86: Scraper (when not scraping) | E86: RAV Vehicles (Scraper) | G86: 119494.75 | H86: =H40*P86 -> 433620.13 | K86: General Open Area | L86: 0 | M86: 0 | N86: 100 | O86: 39 | P86: 1 | Q86: NA | R86: NA
C87: Service Truck | E87: RAV Vehicles (Service Truck) | G87: 656657.92 | H87: =H41*P87 -> 0 | K87: Haul Roads and Access Tracks | L87: 30 | M87: 0 | N87: 70 | O87: 20 | P87: 3 | Q87: NA | R87: NA
C88: Tractor | E88: RAV Vehicles (Tractor) | G88: 1854 | H88: =H42*P88 -> 0 | K88: Open Area (General Open Area)
C89: Welder (<450kW) | E89: RAV Vehicles (Welder) | G89: - | K89: Open Area (Plant Site - Watering)
C90: Unspecified | E90: RAV Vehicles (Unspecified) | G90: - | K90: Open Area (Haul Roads and Access Tracks)
C93: Vehicle Class | D93: Dust Sources | E93: Required Variables | K93: Parameter | M93: Description
C94: [select]
C95: Aircraft
C96: Ancillary (Other) | D96: Movement, if applicable | E96: Work Area, Distance Travelled, % in Locations, Weights | K96: Owner: | M96: Owner of the fleet, i.e. your company or contractor name
C97: Backhoe | D97: No | K97: Model: | M97: Vehicle model name, i.e. Cat 657
C98: Barge (<450kW) | D98: No
C99: Barge (>450kW) | D99: No
C100: Bobcat | D100: No | K100: No Of: | M100: Number of type and model belonging to owner
C101: Bogger | D101: No | K101: Tare Weight: | M101: Unloaded or dry weight of vehicle
C102: Bus | D102: Movement | E102: Work Area, Distance Travelled, % in Locations, Weights | K102: Gross Weight: | M102: Fully loaded weight of vehicle
C103: Cars
C104: Commercial
C105: Commercial (Rough Roads) | D105: Movement | E105: Work Area, Distance Travelled, % in Locations, Weights | K105: Op Hrs: | M105: Total operating hours for period
C106: Commercial MGV (Smooth Roads)
C107: Commercial HGV (Smooth Roads)
C108: Compressor (<450kW) | D108: No
C109: Concrete/Shotcrete
...

Sheet CWF - Plant and Equipment-Other
C3: Ravenswood Operations | G3: This tab captures fuel use and dust emissions from vehicles and unmetered engines using fuel other than diesel
C4: 01/07/2023 - 30/06/2024 | G4: Greenbase will estimate the kilometres travelled if this information is unable to be provided
C6: Other Fuel Usage and Operational Data by Engine Class | G6: Request from Carole. If you cannot find the monthly invoices, go to the Post Office and ask to take photos of their log book. This will show monthly fuel issues for RG.
J8: Data Sources: | L8: Monthly invoices from Ravenswood Post Office (Julie/Carole)
C9: Other Fuels
L10: Monthly Other Fuel Consumption | Y10: % Use on Site
C11: Class of Vehicle (1) | D11: Owner | E11: Model | F11: Fuel Type | G11: Unit | I11: FY2023 Fuel | J11: FY2024 Fuel | L11: Jul | M11: Aug | N11: Sep | O11: Oct | P11: Nov | Q11: Dec | R11: Jan | S11: Feb | T11: Mar | U11: Apr | V11: May | W11: Jun | Y11: % Use on Site
C12: Light Vehicle | D12: NOL | E12: Light Vehicles | F12: ULP | G12: L | I12: 5599.1 | J12: =SUM(L12:W12) -> 4964.8 | L12: 391.3 | M12: 430.9 | N12: 501.4 | O12: 630.5 | P12: 457.3 | Q12: 389.2 | R12: 518.9 | S12: 364.5 | T12: 346.3 | U12: 420.2 | V12: 175.6 | W12: 338.7 | Y12: 80
C13: Compressor | D13: Enviro | E13: Honda | F13: ULP | G13: L | I13: 8.7 | J13: =SUM(L13:W13) -> 167.3 | Q13: 39.2 | S13: 73.3 | T13: 54.8 | Y13: 20
C14: Ancillary (Other) | D14: NOL | E14: Mowers, LV workshop (compressor) | F14: ULP | G14: L | I14: 1921.3 | J14: =SUM(L14:W14) -> 0 | Y14: 100
C15: Bus | D15: NOL | F15: [select] | G15: [select] | J15: =SUM(L15:W15) -> 937.5 | L15: 74 | M15: 53 | N15: 39 | O15: 117.5 | P15: 76.8 | Q15: 129.7 | R15: 93.5 | S15: 50 | T15: 96.1 | U15: 111.9 | V15: 49.9 | W15: 46.1 | Y15: 100
C16: [select] | F16: [select] | G16: [select] | J16: =SUM(L16:W16) -> 0 | Y16: 100
C18: Kilometres Travelled | D18: Greenbase will estimate the kilometres travelled if this information is unable to be provided
L19: Work Area | M19: STEP 1 % In Pit | N19: STEP 2 % Underground | O19: STEP 3 % Sealed | P19: % Surface and Unpaved | Q19: Mean Vehicle Weight | R19: Fuel Burn Rate | S19: Average Vehicle Speed
C20: Class of Vehicle | D20: Owner | E20: Model | I20: FY2023 Distance | J20: FY2024 Distance
I21: km | J21: km | L21: Option | M21: % | N21: % | O21: % | P21: % | Q21: Tonne | R21: km/L | S21: km/hr
C22: Light Vehicle | D22: NOL | E22: Light Vehicles | I22: 27995.5 | J22: =J12*R22 -> 24824 | L22: Roads and Access Tracks | M22: 0 | N22: 0 | O22: 60 | P22: =100-M22-N22-O22 -> 40 | Q22: =IF($C22="[select]","Select Vehicle Class",IF($C22="light vehicle","NA",IF($C22="grader","NA","Please enter"))) -> NA | R22: 5 | S22: 50
C23: Bus | L23: [select] | M23: 0 | N23: 0 | O23: 0 | P23: =100-M23-N23-O23 -> 100 | Q23: =IF($C23="[select]","Select Vehicle Class",IF($C23="light vehicle","NA",IF($C23="grader","NA","Please enter"))) -> Please enter | S23: =IF($C23="[select]","Select Vehicle Class",IF($C23="light vehicle","Please enter",IF($C23="grader","Please enter","NA"))) -> NA
C24: [select] | L24: [select] | M24: 0 | N24: 0 | O24: 0 | P24: =100-M24-N24-O24 -> 100 | Q24: =IF($C24="[select]","Select Vehicle Class",IF($C24="light vehicle","NA",IF($C24="grader","NA","Please enter"))) -> Select Vehicle Class | S24: =IF($C24="[select]","Select Vehicle Class",IF($C24="light vehicle","Please enter",IF($C24="grader","Please enter","NA"))) -> Select Vehicle Class
C26: Vehicle Class | D26: Dust Sources | E26: Required Variables | L26: Parameter | N26: Description
C27: [select]
C28: Aircraft | D28: No
C29: Ancillary (Other) | D29: Movement, if applicable | E29: Work Area, Distance Travelled, % in Locations, Weights | L29: Owner: | N29: Owner of the fleet, i.e. your company or contractor name
C30: Backhoe | D30: No | L30: Model: | N30: Vehicle model name, i.e. Cat 657
C31: Bobcat | D31: No | L31: No Of: | N31: Number of type and model belonging to owner
C32: Bus | D32: Movement | E32: Work Area, Distance Travelled, % in Locations, Weights | L32: Gross Weight: | N32: Fully loaded weight of vehicle
C33: Cars
C34: Commercial (Rough Roads) | D34: Movement | E34: Work Area, Distance Travelled, % in Locations, Weights | L34: Op Hrs: | N34: Total operating hours for period
C35: Commercial MGV (Smooth Roads)
C36: Commercial HGV (Smooth Roads)
C37: Crane | D37: No | L37: Kilometres Travelled: | N37: Total distance travelled for period
C38: EWP | D38: No | L38: % Sealed, In Pit, UG and Surface | N38: This info is required because vehicles used in the pit, underground or sealed have a reduced dust emission factor
C39: Forklift | D39: No
C40: Grader | D40: Movement | E40: Distance Travelled, % in Locations
C41: Heaters and BBQs | D41: No
C42: IT Loader | D42: No
C43: Jumbo | D43: No
C44: Light Vehicle (Rough Roads) | D44: Movement | E44: Work Area, Distance Travelled, % in Locations, Weights
C45: Light Vehicle (Smooth Roads)
C46: Tractor | D46: No
C47: Traxcavator | D47: No
C49: (1) Smooth road vehicles are typically sealed and well-formed unsealed roads, while rough roads vehicles are any poorly-formed unsealed roads and steep/poorly graded tracks.
C51: Paste raw data below:
C53: Monthly invoices saved in the Sharepoint folder

Sheet ES - Drilling and Explosives
C3: Ravenswood Operations | G3: If area blasted is unavailable, an appropriate approximation is BCM divided by average bench height
C4: 01/07/2023 - 30/06/2024 | G4: If count is selected for units option, please specify unit size.
C6: Drilling and Blasting | G6: Data for Drill and Blast is saved in the pink tab (Yearly Pollution and greenhouse) in G:\Environment\16. SHE Monitoring, Measuring and Reporting\Monitoring\Blast monitoring\2024\Drill database V13-Shortcut . You will need to get Grade Control data from AJ Koen and Exploration data from Steve Harper.
C8: Blasting
C10: Explosives | K10: Data Sources: | M10: Sourced from Mining Department (Drill and Blast Engineers), Mining Geology (Grade Control), Exploration
C12: Mine Name | D12: Product Name | F12: Supplier | G12: Fuel % If Applicable | H12: Explosive batched onsite? | I12: Hole Dia (> or < 152mm) | J12: FY2023 Amount | K12: FY2024 Amount | L12: Unit | M12: Monthly Amount
D13: Explosive Type | E13: Commercial Name | M13: Jul | N13: Aug | O13: Sep | P13: Oct | Q13: Nov | R13: Dec | S13: Jan | T13: Feb | U13: Mar | V13: Apr | W13: May | X13: Jun
C14: Buck Reef West and Sarsfield | D14: Emulsion/ANFO blend | E14: Fortis Eclipse 1.1 | F14: Orica | G14: 1 | H14: Yes | I14: <152mm | J14: 7098.576 | K14: =SUM(M14:X14) -> 6595.446 | L14: tonnes | M14: 609.472 | N14: 547.351 | O14: 566.13 | P14: 645.774 | Q14: 837.437 | R14: 524.644 | S14: 434.849 | T14: 386.9 | U14: 475.38 | V14: 561.485 | W14: 446.089 | X14: 559.935
C16: Mine Name | D16: Product Name | F16: Supplier | G16: Fuel % If Applicable | H16: Explosive batched onsite? | I16: Hole Dia (> or < 152mm) | J16: FY2023 Amount | K16: FY2024 Amount | L16: Unit | M16: Monthly Amount
D17: Explosive Type | E17: Commercial Name | M17: Jul | N17: Aug | O17: Sep | P17: Oct | Q17: Nov | R17: Dec | S17: Jan | T17: Feb | U17: Mar | V17: Apr | W17: May | X17: Jun
H18: [select] | I18: [select] | J18: - | K18: =SUM(M18:X18) -> 0 | L18: [select]
H19: [select] | I19: [select] | K19: =SUM(M19:X19) -> 0 | L19: [select]
H20: [select] | I20: [select] | K20: =SUM(M20:X20) -> 0 | L20: [select]
H22: Total ANFO Doped Emulsion | K22: =SUM(M22:X22) -> 0 | L22: [select] | M22: =SUM(M18:M20) -> 0 | N22: =SUM(N18:N20) -> 0 | O22: =SUM(O18:O20) -> 0 | P22: =SUM(P18:P20) -> 0 | Q22: =SUM(Q18:Q20) -> 0 | R22: =SUM(R18:R20) -> 0 | S22: =SUM(S18:S20) -> 0 | T22: =SUM(T18:T20) -> 0 | ... X22: =SUM(X18:X20) -> 0
C24: Drill and Blast
C26: Open Cut Name | E26: Parameter | I26: Material Assay | J26: FY2023 Amount | K26: FY2024 Amount | L26: Unit | M26: Monthly Amount
M27: Jul | N27: Aug | O27: Sep | P27: Oct | Q27: Nov | R27: Dec | S27: Jan | T27: Feb | U27: Mar | V27: Apr | W27: May | X27: Jun
C28: Buck Reef West and Sarsfield | E28: Total surface area blasted | I28: BRW Ore Assay | J28: 877569 | K28: =SUM(M28:X28) -> 829659.5 | L28: m2 | M28: 81858.576 | N28: 74693.064 | O28: 73856.589 | P28: 91433.683 | Q28: 107105.78 | R28: 72448.44 | S28: 43610.75 | T28: 49290.152 | U28: 63955.435 | V28: 54800.584 | W28: 57765.376 | X28: 58841.071
E29: Number of blast events | J29: 179 | K29: =SUM(M29:X29) -> 199 | L29: count | M29: 16 | N29: 15 | O29: 18 | P29: 18 | Q29: 16 | R29: 21 | S29: 17 | T29: 13 | U29: 17 | V29: 17 | W29: 18 | X29: 13
E30: Number of holes drilled | J30: 103451 | K30: =SUM(M30:X30) -> 98273 | L30: count | M30: 10213 | N30: 8508 | O30: 7663 | P30: 10367 | Q30: 10913 | R30: 7947 | S30: 5954 | T30: 6022 | U30: 7051 | V30: 7383 | W30: 8265 | X30: 7987
E31: Drilling in pit | J31: 100 | L31: %
E32: Water Sprays used for drilling | J32: No | K32: [select] | L32: option
E33: Dust Collector used for drilling (Fabric Filter) | J33: Yes | K33: [select] | L33: option
E34: Moisture Content of Pit | J34: 2 | L34: %
C37: Drilling for On-Site Grade Control and Resource Definition
C39: Area Name | E39: Parameter | I39: Material Assay | J39: FY2023 Value | K39: FY2024 Value | L39: Unit | M39: Monthly Amount
M40: Jul | N40: Aug | O40: Sep | P40: Oct | Q40: Nov | R40: Dec | S40: Jan | T40: Feb | U40: Mar | V40: Apr | W40: May | X40: Jun
C41: BRW (Grade Control) | E41: Number of holes drilled | I41: BRW Ore Assay | J41: 5094 | K41: =SUM(M41:X41) -> 3654 | L41: count | M41: 281 | N41: 329 | O41: 464 | P41: 454 | Q41: 427 | R41: 312 | S41: 193 | T41: 343 | U41: 258 | V41: 130 | W41: 323 | X41: 140
E42: Drilling on site | J42: 100 | L42: %
E43: Drilling in pit | J43: 0 | L43: %
E44: Dust collection hopper (cyclone) used | J44: Yes | K44: [select] | L44: option
E45: Water Sprays used for drilling | J45: Yes | K45: [select] | L45: option
E46: Dust Collector used for drilling (Fabric Filter) | J46: Yes | K46: [select] | L46: option
C48: Area Name | E48: Parameter | I48: Material Assay | J48: FY2023 Value | K48: FY2024 Value | L48: Unit | M48: Monthly Amount
M49: Jul | N49: Aug | O49: Sep | P49: Oct | Q49: Nov | R49: Dec | S49: Jan | T49: Feb | U49: Mar | V49: Apr | W49: May | X49: Jun
C50: Sarsfield (Grade Control) | E50: Number of holes drilled | I50: Sarsfield Combined Ore Assay | J50: 5094 | K50: =SUM(M50:X50) -> 625 | L50: count | M50: 0 | N50: 0 | O50: 45 | P50: 32 | Q50: 6 | R50: 28 | S50: 76 | T50: 19 | U50: 102 | V50: 173 | W50: 32 | X50: 112
E51: Drilling on site | J51: 100 | L51: %
E52: Drilling in pit | J52: 0 | L52: %
E53: Dust collection hopper (cyclone) used | J53: Yes | K53: [select] | L53: option
E54: Water Sprays used for drilling | J54: Yes | K54: [select] | L54: option
E55: Dust Collector used for drilling (Fabric Filter) | J55: Yes | K55: [select] | L55: option
C57: Buck Reef West and Sarsfield (Exploration) Total | E57: Number of holes drilled | I57: Average Ore Assay | J57: 62 | K57: =SUM(M57:X57) -> 22 | L57: count | M57: 0 | N57: 0 | O57: 0 | P57: 0 | Q57: 0 | R57: 0 | S57: 0 | T57: 1 | U57: 6 | V57: 5 | W57: 5 | X57: 5
E58: Drilling on site | J58: 100 | L58: %
E59: Drilling in pit | J59: 0 | L59: %
E60: Water Sprays used for drilling | J60: Yes | K60: [select] | L60: option
E61: Dust Collector used for drilling (Fabric Filter) | J61: No | K61: [select] | L61: option
C63: Paste raw data below:

Sheet Geology
C3: Ravenswood Operations | G3: Rock and soil assays
C4: 01/07/2023 - 30/06/2024 | G4: If a substance is not detected please enter the detection limit
G5: If no value supplied, Greenbase are obliged to use Table 9 from the Mining Manual to fill in any gaps (see screenshot below).
C7: Geology | E7: Data Source: | F7: Total Metal Analysis - data from DataSight
C9: Type | D9: Name | E9: Assay Date | F9: Substance and Units
F10: As | G10: B | H10: Be | I10: Cd | J10: Co | K10: Cr | L10: Cr (III) | M10: Cu | N10: F | O10: Hg | P10: Mn | Q10: Ni | R10: Pb | S10: Sb | T10: Se | U10: Zn
F11: mg/kg | G11: mg/kg | H11: mg/kg | I11: mg/kg | J11: mg/kg | K11: mg/kg | L11: mg/kg | M11: mg/kg | N11: mg/kg | O11: mg/kg | P11: mg/kg | Q11: mg/kg | R11: mg/kg | S11: mg/kg | T11: mg/kg | U11: mg/kg
C12: Road Assay | D12: Combined Road | E12: Average | F12: 67.476 | G12: 10 | H12: 0.3 | I12: 0.902 | J12: 2.6 | K12: 4.571 | L12: 4.571 | M12: 234.238 | N12: 200 | O12: 0.025 | P12: 950 | Q12: 6.667 | R12: 5.452 | S12: 0.2 | T12: 1.5 | U12: 70
C13: Topsoil Assay | D13: Average Topsoil Assay | E13: Average | F13: 4.8333 | G13: 20 | H13: 0.4333 | I13: 0.45 | J13: 9 | K13: 26.3333 | L13: 26.3333 | M13: 35.6667 | N13: 190 | O13: 0.0533 | P13: 638.6667 | Q13: 19.6667 | R13: 13.3333 | S13: 1.7333 | T13: 1.6833 | U13: 46.3333
C14: Ore Assay | D14: Average Ore Assay | E14: Average | F14: 81.0625 | G14: 19.375 | H14: 0.6875 | I14: 1.6375 | J14: 21.8125 | K14: 7.75 | L14: 7.75 | M14: 463.75 | N14: 571.25 | O14: 0.05 | P14: 1225.625 | Q14: 9.125 | R14: 25.8188 | S14: 2.5188 | T14: 2.2188 | U14: 240.25
C15: Tailings Assay | D15: Average Tailings Assay | E15: Average | F15: 64.8835 | G15: 17.5 | H15: 1.55 | I15: 1.558 | J15: 17.5 | K15: 11.6975 | L15: 11.6975 | M15: 363.1045 | N15: 605 | O15: 0.05 | P15: 1015 | Q15: 8.0235 | R15: 29.7095 | S15: 1.35 | T15: 2 | U15: 93
C16: Average Waste Assay | D16: Average Waste Assay | E16: Average | F16: 11.9667 | G16: 15 | H16: 0.6 | I16: 1.1 | J16: 12.5333 | K16: 6.4333 | L16: 6.4333 | M16: 128.3333 | N16: 470 | O16: 0.05 | P16: 1022.3333 | Q16: 23 | R16: 5.9333 | S16: 1 | T16: 1.1833 | U16: 302
C17: Average Scats Assay | D17: Average Scats Assay | E17: Average | F17: 2.659 | G17: 17.5 | H17: 0.75 | I17: 0.3455 | J17: 21 | K17: 9.0455 | L17: 9.0455 | M17: 232.6045 | N17: 325 | O17: 0.0375 | P17: 945.5 | Q17: 7.0235 | R17: 27.4595 | S17: 1.35 | T17: 2 | U17: 61.5
C18: Ore Assays | D18: BRW Ore Assay | E18: 43666 | F18: 155 | G18: <50 | H18: <1 | I18: 4 | J18: 16 | K18: 2 | M18: 141 | N18: 350 | O18: <0.1 | P18: 2770 | Q18: 7 | R18: 9 | S18: <5 | T18: <5 | U18: 946
C19: Ore Assays | D19: Sarsfield Combined Ore Assay | E19: 39790 | F19: 107.5 | G19: 10 | H19: 1 | I19: 2.2 | J19: 32.5 | K19: 12 | L19: 12 | M19: 850 | N19: 950 | O19: 0.05 | P19: 1375 | Q19: 13 | R19: 7.35 | S19: 2.55 | T19: 1.75 | U19: 140
C21: Geology | E21: Data Sources: | G21: Total Metal Analysis - data from DataSight
X22: As | Y22: B | Z22: Be | AA22: Cd | AB22: Co | AC22: Cr | AD22: Cr (III) | AE22: Cu | AF22: F | AG22: Hg | AH22: Mn | AI22: Ni | AJ22: Pb | AK22: Sb | AL22: Se | AM22: Zn
C23: Topsoil Assay | D23: LALA Topsoil | E23: 43668 | F23: 6 | G23: <50 | H23: <1 | I23: <1 | J23: 9 | K23: 5 | M23: 48 | N23: 170 | O23: <0.1 | P23: 542 | Q23: 5 | R23: <5 | S23: <5 | T23: <5 | U23: 51 | X23: =IF(LEFT(F23,1)="<",(RIGHT(F23,LEN(F23)-1))/2,F23) -> 6 | Y23: =IF(LEFT(G23,1)="<",(RIGHT(G23,LEN(G23)-1))/2,G23) -> 25 | Z23: =IF(LEFT(H23,1)="<",(RIGHT(H23,LEN(H23)-1))/2,H23) -> 0.5 | AA23: =IF(LEFT(I23,1)="<",(RIGHT(I23,LEN(I23)-1))/2,I23) -> 0.5 | AB23: =IF(LEFT(J23,1)="<",(RIGHT(J23,LEN(J23)-1))/2,J23) -> 9 | AC23: =IF(LEFT(K23,1)="<",(RIGHT(K23,LEN(K23)-1))/2,K23) -> 5 | AD23: =IF(LEFT(L23,1)="<",(RIGHT(L23,LEN(L23)-1))/2,L23) -> 0 | AE23: =IF(LEFT(M23,1)="<",(RIGHT(M23,LEN(M23)-1))/2,M23) -> 48 | ... AM23: =IF(LEFT(U23,1)="<",(RIGHT(U23,LEN(U23)-1))/2,U23) -> 51
C24: Topsoil Assay | D24: SAR Topsoil | E24: 43668 | F24: <5 | G24: <50 | H24: <1 | I24: <1 | J24: 10 | K24: 4 | M24: 29 | N24: 200 | O24: <0.1 | P24: 424 | Q24: 4 | R24: <5 | S24: <5 | T24: <5 | U24: 18 | X24: =IF(LEFT(F24,1)="<",(RIGHT(F24,LEN(F24)-1))/2,F24) -> 2.5 | Y24: =IF(LEFT(G24,1)="<",(RIGHT(G24,LEN(G24)-1))/2,G24) -> 25 | Z24: =IF(LEFT(H24,1)="<",(RIGHT(H24,LEN(H24)-1))/2,H24) -> 0.5 | AA24: =IF(LEFT(I24,1)="<",(RIGHT(I24,LEN(I24)-1))/2,I24) -> 0.5 | AB24: =IF(LEFT(J24,1)="<",(RIGHT(J24,LEN(J24)-1))/2,J24) -> 10 | AC24: =IF(LEFT(K24,1)="<",(RIGHT(K24,LEN(K24)-1))/2,K24) -> 4 | AD24: =IF(LEFT(L24,1)="<",(RIGHT(L24,LEN(L24)-1))/2,L24) -> 0 | AE24: =IF(LEFT(M24,1)="<",(RIGHT(M24,LEN(M24)-1))/2,M24) -> 29 | ... AM24: =IF(LEFT(U24,1)="<",(RIGHT(U24,LEN(U24)-1))/2,U24) -> 18
C25: Topsoil Assay | D25: Wastes Topsoil | E25: 39790 | F25: 6 | G25: 10 | H25: 0.3 | I25: 0.35 | J25: 8 | K25: 70 | M25: 30 | N25: 200 | O25: 0.06 | P25: 950 | Q25: 50 | R25: 35 | S25: 0.2 | T25: 0.05 | U25: 70 | X25: =IF(LEFT(F25,1)="<",(RIGHT(F25,LEN(F25)-1))/2,F25) -> 6 | Y25: =IF(LEFT(G25,1)="<",(RIGHT(G25,LEN(G25)-1))/2,G25) -> 10 | Z25: =IF(LEFT(H25,1)="<",(RIGHT(H25,LEN(H25)-1))/2,H25) -> 0.3 | AA25: =IF(LEFT(I25,1)="<",(RIGHT(I25,LEN(I25)-1))/2,I25) -> 0.35 | AB25: =IF(LEFT(J25,1)="<",(RIGHT(J25,LEN(J25)-1))/2,J25) -> 8 | AC25: =IF(LEFT(K25,1)="<",(RIGHT(K25,LEN(K25)-1))/2,K25) -> 70 | AD25: =IF(LEFT(L25,1)="<",(RIGHT(L25,LEN(L25)-1))/2,L25) -> 0 | AE25: =IF(LEFT(M25,1)="<",(RIGHT(M25,LEN(M25)-1))/2,M25) -> 30 | ... AM25: =IF(LEFT(U25,1)="<",(RIGHT(U25,LEN(U25)-1))/2,U25) -> 70
C26: Average Topsoil Assay | D26: Average Topsoil Assay | F26: =AVERAGE(X23:X25) -> 4.8333333 | G26: =AVERAGE(Y23:Y25) -> 20 | H26: =AVERAGE(Z23:Z25) -> 0.43333333 | I26: =AVERAGE(AA23:AA25) -> 0.45 | J26: =AVERAGE(AB23:AB25) -> 9 | K26: =AVERAGE(AC23:AC25) -> 26.333333 | L26: =K26 -> 26.333333 | M26: =AVERAGE(AE23:AE25) -> 35.666667 | N26: =AVERAGE(AF23:AF25) -> 190 | O26: =AVERAGE(AG23:AG25) -> 0.053333333 | P26: =AVERAGE(AH23:AH25) -> 638.66667 | Q26: =AVERAGE(AI23:AI25) -> 19.666667 | R26: =AVERAGE(AJ23:AJ25) -> 13.333333 | S26: =AVERAGE(AK23:AK25) -> 1.7333333 | T26: =AVERAGE(AL23:AL25) -> 1.6833333 | U26: =AVERAGE(AM23:AM25) -> 46.333333
C28: Road Assay | D28: Combined Road | E28: 39790 | F28: 67.476 | G28: 10 | H28: 0.3 | I28: 0.902 | J28: 2.6 | K28: 4.571 | M28: 234.238 | N28: 200 | O28: 0.025 | P28: 950 | Q28: 6.667 | R28: 5.452 | S28: 0.2 | T28: 1.5 | U28: 70 | X28: =IF(LEFT(F28,1)="<",(RIGHT(F28,LEN(F28)-1))/2,F28) -> 67.476 | Y28: =IF(LEFT(G28,1)="<",(RIGHT(G28,LEN(G28)-1))/2,G28) -> 10 | Z28: =IF(LEFT(H28,1)="<",(RIGHT(H28,LEN(H28)-1))/2,H28) -> 0.3 | AA28: =IF(LEFT(I28,1)="<",(RIGHT(I28,LEN(I28)-1))/2,I28) -> 0.902 | AB28: =IF(LEFT(J28,1)="<",(RIGHT(J28,LEN(J28)-1))/2,J28) -> 2.6 | AC28: =IF(LEFT(K28,1)="<",(RIGHT(K28,LEN(K28)-1))/2,K28) -> 4.571 | AD28: =IF(LEFT(L28,1)="<",(RIGHT(L28,LEN(L28)-1))/2,L28) -> 0 | AE28: =IF(LEFT(M28,1)="<",(RIGHT(M28,LEN(M28)-1))/2,M28) -> 234.238 | ... AM28: =IF(LEFT(U28,1)="<",(RIGHT(U28,LEN(U28)-1))/2,U28) -> 70
C29: Combined Road | D29: Combined Road | F29: =AVERAGE(X28) -> 67.476 | G29: =AVERAGE(Y28) -> 10 | H29: =AVERAGE(Z28) -> 0.3 | I29: =AVERAGE(AA28) -> 0.902 | J29: =AVERAGE(AB28) -> 2.6 | K29: =AVERAGE(AC28) -> 4.571 | L29: =K29 -> 4.571 | M29: =AVERAGE(AE28) -> 234.238 | N29: =AVERAGE(AF28) -> 200 | O29: =AVERAGE(AG28) -> 0.025 | P29: =AVERAGE(AH28) -> 950 | Q29: =AVERAGE(AI28) -> 6.667 | R29: =AVERAGE(AJ28) -> 5.452 | S29: =AVERAGE(AK28) -> 0.2 | T29: =AVERAGE(AL28) -> 1.5 | U29: =AVERAGE(AM28) -> 70
C31: Waste Assay | D31: Combined Waste | E31: 39790 | F31: 6.9 | G31: 10 | H31: 0.3 | I31: 0.1 | J31: 2.6 | K31: 2.3 | M31: 30 | N31: 200 | O31: 0.05 | P31: 950 | Q31: 50 | R31: 9.4 | S31: 0.2 | T31: 0.05 | U31: 70 | X31: =IF(LEFT(F31,1)="<",(RIGHT(F31,LEN(F31)-1))/2,F31) -> 6.9 | Y31: =IF(LEFT(G31,1)="<",(RIGHT(G31,LEN(G31)-1))/2,G31) -> 10 | Z31: =IF(LEFT(H31,1)="<",(RIGHT(H31,LEN(H31)-1))/2,H31) -> 0.3 | AA31: =IF(LEFT(I31,1)="<",(RIGHT(I31,LEN(I31)-1))/2,I31) -> 0.1 | AB31: =IF(LEFT(J31,1)="<",(RIGHT(J31,LEN(J31)-1))/2,J31) -> 2.6 | AC31: =IF(LEFT(K31,1)="<",(RIGHT(K31,LEN(K31)-1))/2,K31) -> 2.3 | AD31: =IF(LEFT(L31,1)="<",(RIGHT(L31,LEN(L31)-1))/2,L31) -> 0 | AE31: =IF(LEFT(M31,1)="<",(RIGHT(M31,LEN(M31)-1))/2,M31) -> 30 | ... AM31: =IF(LEFT(U31,1)="<",(RIGHT(U31,LEN(U31)-1))/2,U31) -> 70
C32: Waste Assay | D32: NOL E Waste | E32: 43668 | F32: 12 | G32: <50 | H32: <1 | I32: 3 | J32: 13 | K32: 4 | M32: 150 | N32: 260 | O32: <0.1 | P32: 797 | Q32: 6 | R32: 5 | S32: <5 | T32: <5 | U32: 766 | X32: =IF(LEFT(F32,1)="<",(RIGHT(F32,LEN(F32)-1))/2,F32) -> 12 | Y32: =IF(LEFT(G32,1)="<",(RIGHT(G32,LEN(G32)-1))/2,G32) -> 25 | Z32: =IF(LEFT(H32,1)="<",(RIGHT(H32,LEN(H32)-1))/2,H32) -> 0.5 | AA32: =IF(LEFT(I32,1)="<",(RIGHT(I32,LEN(I32)-1))/2,I32) -> 3 | AB32: =IF(LEFT(J32,1)="<",(RIGHT(J32,LEN(J32)-1))/2,J32) -> 13 | AC32: =IF(LEFT(K32,1)="<",(RIGHT(K32,LEN(K32)-1))/2,K32) -> 4 | AD32: =IF(LEFT(L32,1)="<",(RIGHT(L32,LEN(L32)-1))/2,L32) -> 0 | AE32: =IF(LEFT(M32,1)="<",(RIGHT(M32,LEN(M32)-1))/2,M32) -> 150 | ... AM32: =IF(LEFT(U32,1)="<",(RIGHT(U32,LEN(U32)-1))/2,U32) -> 766
C33: Waste Assay | D33: SAR Waste | E33: 39790 | F33: 17 | G33: 10 | H33: 1 | I33: 0.2 | J33: 22 | K33: 13 | M33: 205 | N33: 950 | O33: 0.05 | P33: 1320 | Q33: 13 | R33: 3.4 | S33: 0.3 | T33: 1 | U33: 70 | X33: =IF(LEFT(F33,1)="<",(RIGHT(F33,LEN(F33)-1))/2,F33) -> 17 | Y33: =IF(LEFT(G33,1)="<",(RIGHT(G33,LEN(G33)-1))/2,G33) -> 10 | Z33: =IF(LEFT(H33,1)="<",(RIGHT(H33,LEN(H33)-1))/2,H33) -> 1 | AA33: =IF(LEFT(I33,1)="<",(RIGHT(I33,LEN(I33)-1))/2,I33) -> 0.2 | AB33: =IF(LEFT(J33,1)="<",(RIGHT(J33,LEN(J33)-1))/2,J33) -> 22 | AC33: =IF(LEFT(K33,1)="<",(RIGHT(K33,LEN(K33)-1))/2,K33) -> 13 | AD33: =IF(LEFT(L33,1)="<",(RIGHT(L33,LEN(L33)-1))/2,L33) -> 0 | AE33: =IF(LEFT(M33,1)="<",(RIGHT(M33,LEN(M33)-1))/2,M33) -> 205 | ... AM33: =IF(LEFT(U33,1)="<",(RIGHT(U33,LEN(U33)-1))/2,U33) -> 70
C34: Average Waste Assay | D34: Average Waste Assay | F34: =AVERAGE(X31:X33) -> 11.966667 | G34: =AVERAGE(Y31:Y33) -> 15 | H34: =AVERAGE(Z31:Z33) -> 0.6 | I34: =AVERAGE(AA31:AA33) -> 1.1 | J34: =AVERAGE(AB31:AB33) -> 12.533333 | K34: =AVERAGE(AC31:AC33) -> 6.4333333 | L34: =K34 -> 6.4333333 | M34: =AVERAGE(AE31:AE33) -> 128.33333 | N34: =AVERAGE(AF31:AF33) -> 470 | O34: =AVERAGE(AG31:AG33) -> 0.05 | P34: =AVERAGE(AH31:AH33) -> 1022.3333 | Q34: =AVERAGE(AI31:AI33) -> 23 | R34: =AVERAGE(AJ31:AJ33) -> 5.9333333 | S34: =AVERAGE(AK31:AK33) -> 1 | T34: =AVERAGE(AL31:AL33) -> 1.1833333 | U34: =AVERAGE(AM31:AM33) -> 302
C36: Tailings Assay | D36: Tailings Assay | E36: 43431 | F36: 54 | G36: <50 | H36: <1 | I36: 1 | J36: 15 | K36: 11 | L36: 11 | M36: 309 | N36: 260 | O36: <0.1 | P36: 1080 | Q36: 8 | R36: 7 | S36: <5 | T36: <5 | U36: 116 | X36: =IF(LEFT(F36,1)="<",(RIGHT(F36,LEN(F36)-1))/2,F36) -> 54 | Y36: =IF(LEFT(G36,1)="<",(RIGHT(G36,LEN(G36)-1))/2,G36) -> 25 | Z36: =IF(LEFT(H36,1)="<",(RIGHT(H36,LEN(H36)-1))/2,H36) -> 0.5 | AA36: =IF(LEFT(I36,1)="<",(RIGHT(I36,LEN(I36)-1))/2,I36) -> 1 | AB36: =IF(LEFT(J36,1)="<",(RIGHT(J36,LEN(J36)-1))/2,J36) -> 15 | AC36: =IF(LEFT(K36,1)="<",(RIGHT(K36,LEN(K36)-1))/2,K36) -> 11 | AD36: =IF(LEFT(L36,1)="<",(RIGHT(L36,LEN(L36)-1))/2,L36) -> 11 | AE36: =IF(LEFT(M36,1)="<",(RIGHT(M36,LEN(M36)-1))/2,M36) -> 309 | ... AM36: =IF(LEFT(U36,1)="<",(RIGHT(U36,LEN(U36)-1))/2,U36) -> 116
C37: Tailings Assay | D37: Tailings Assay | E37: 39790 | F37: 75.767 | G37: 10 | H37: 2.6 | I37: 2.116 | J37: 20 | K37: 12.395 | L37: 12.395 | M37: 417.209 | N37: 950 | O37: 0.05 | P37: 950 | Q37: 8.047 | R37: 52.419 | S37: 0.2 | T37: 1.5 | U37: 70 | X37: =IF(LEFT(F37,1)="<",(RIGHT(F37,LEN(F37)-1))/2,F37) -> 75.767 | Y37: =IF(LEFT(G37,1)="<",(RIGHT(G37,LEN(G37)-1))/2,G37) -> 10 | Z37: =IF(LEFT(H37,1)="<",(RIGHT(H37,LEN(H37)-1))/2,H37) -> 2.6 | AA37: =IF(LEFT(I37,1)="<",(RIGHT(I37,LEN(I37)-1))/2,I37) -> 2.116 | AB37: =IF(LEFT(J37,1)="<",(RIGHT(J37,LEN(J37)-1))/2,J37) -> 20 | AC37: =IF(LEFT(K37,1)="<",(RIGHT(K37,LEN(K37)-1))/2,K37) -> 12.395 | AD37: =IF(LEFT(L37,1)="<",(RIGHT(L37,LEN(L37)-1))/2,L37) -> 12.395 | AE37: =IF(LEFT(M37,1)="<",(RIGHT(M37,LEN(M37)-1))/2,M37) -> 417.209 | ... AM37: =IF(LEFT(U37,1)="<",(RIGHT(U37,LEN(U37)-1))/2,U37) -> 70
C38: Average Tailings Assay | D38: Average Tailings Assay | F38: =AVERAGE(X36:X37) -> 64.8835 | G38: =AVERAGE(Y36:Y37) -> 17.5 | H38: =AVERAGE(Z36:Z37) -> 1.55 | I38: =AVERAGE(AA36:AA37) -> 1.558 | J38: =AVERAGE(AB36:AB37) -> 17.5 | K38: =AVERAGE(AC36:AC37) -> 11.6975 | L38: =K38 -> 11.6975 | M38: =AVERAGE(AE36:AE37) -> 363.1045 | N38: =AVERAGE(AF36:AF37) -> 605 | O38: =AVERAGE(AG36:AG37) -> 0.05 | P38: =AVERAGE(AH36:AH37) -> 1015 | Q38: =AVERAGE(AI36:AI37) -> 8.0235 | R38: =AVERAGE(AJ36:AJ37) -> 29.7095 | S38: =AVERAGE(AK36:AK37) -> 1.35 | T38: =AVERAGE(AL36:AL37) -> 2 | U38: =AVERAGE(AM36:AM37) -> 93
C40: Scats Assay | D40: Scats Assay | E40: 43431 | F40: <5 | G40: <50 | H40: <1 | I40: <1 | J40: 13 | K40: 9 | L40: 9 | M40: 48 | N40: 240 | O40: <0.1 | P40: 941 | Q40: 6 | R40: <5 | S40: <5 | T40: <5 | U40: 53 | X40: =IF(LEFT(F40,1)="<",(RIGHT(F40,LEN(F40)-1))/2,F40) -> 2.5 | Y40: =IF(LEFT(G40,1)="<",(RIGHT(G40,LEN(G40)-1))/2,G40) -> 25 | Z40: =IF(LEFT(H40,1)="<",(RIGHT(H40,LEN(H40)-1))/2,H40) -> 0.5 | AA40: =IF(LEFT(I40,1)="<",(RIGHT(I40,LEN(I40)-1))/2,I40) -> 0.5 | AB40: =IF(LEFT(J40,1)="<",(RIGHT(J40,LEN(J40)-1))/2,J40) -> 13 | AC40: =IF(LEFT(K40,1)="<",(RIGHT(K40,LEN(K40)-1))/2,K40) -> 9 | AD40: =IF(LEFT(L40,1)="<",(RIGHT(L40,LEN(L40)-1))/2,L40) -> 9 | AE40: =IF(LEFT(M40,1)="<",(RIGHT(M40,LEN(M40)-1))/2,M40) -> 48 | ... AM40: =IF(LEFT(U40,1)="<",(RIGHT(U40,LEN(U40)-1))/2,U40) -> 53
C41: Scats Assay | D41: Scats Assay | E41: 39790 | F41: 2.818 | G41: 10 | H41: =H33 -> 1 | I41: 0.191 | J41: 29 | K41: 9.091 | M41: 417.209 | N41: 410 | O41: 0.025 | P41: 950 | Q41: 8.047 | R41: 52.419 | S41: 0.2 | T41: 1.5 | U41: 70 | X41: =IF(LEFT(F41,1)="<",(RIGHT(F41,LEN(F41)-1))/2,F41) -> 2.818 | Y41: =IF(LEFT(G41,1)="<",(RIGHT(G41,LEN(G41)-1))/2,G41) -> 10 | Z41: =IF(LEFT(H41,1)="<",(RIGHT(H41,LEN(H41)-1))/2,H41) -> 1 | AA41: =IF(LEFT(I41,1)="<",(RIGHT(I41,LEN(I41)-1))/2,I41) -> 0.191 | AB41: =IF(LEFT(J41,1)="<",(RIGHT(J41,LEN(J41)-1))/2,J41) -> 29 | AC41: =IF(LEFT(K41,1)="<",(RIGHT(K41,LEN(K41)-1))/2,K41) -> 9.091 | AD41: =IF(LEFT(L41,1)="<",(RIGHT(L41,LEN(L41)-1))/2,L41) -> 0 | AE41: =IF(LEFT(M41,1)="<",(RIGHT(M41,LEN(M41)-1))/2,M41) -> 417.209 | ... AM41: =IF(LEFT(U41,1)="<",(RIGHT(U41,LEN(U41)-1))/2,U41) -> 70
C42: Average Scats Assay | D42: Average Scats Assay | F42: =AVERAGE(X40:X41) -> 2.659 | G42: =AVERAGE(Y40:Y41) -> 17.5 | H42: =AVERAGE(Z40:Z41) -> 0.75 | I42: =AVERAGE(AA40:AA41) -> 0.3455 | J42: =AVERAGE(AB40:AB41) -> 21 | K42: =AVERAGE(AC40:AC41) -> 9.0455 | L42: =K42 -> 9.0455 | M42: =AVERAGE(AE40:AE41) -> 232.6045 | N42: =AVERAGE(AF40:AF41) -> 325 | O42: =AVERAGE(AG40:AG41) -> 0.0375 | P42: =AVERAGE(AH40:AH41) -> 945.5 | Q42: =AVERAGE(AI40:AI41) -> 7.0235 | R42: =AVERAGE(AJ40:AJ41) -> 27.4595 | S42: =AVERAGE(AK40:AK41) -> 1.35 | T42: =AVERAGE(AL40:AL41) -> 2 | U42: =AVERAGE(AM40:AM41) -> 61.5
C44: Ore Assay | D44: NOL E Ore | E44: 43666 | F44: 85 | G44: <50 | H44: <1 | I44: 1 | J44: 21 | K44: 10 | M44: 291 | N44: 320 | O44: <0.1 | P44: 707 | Q44: 8 | R44: 68 | S44: <5 | T44: <5 | U44: 342 | X44: =IF(LEFT(F44,1)="<",(RIGHT(F44,LEN(F44)-1))/2,F44) -> 85 | Y44: =IF(LEFT(G44,1)="<",(RIGHT(G44,LEN(G44)-1))/2,G44) -> 25 | Z44: =IF(LEFT(H44,1)="<",(RIGHT(H44,LEN(H44)-1))/2,H44) -> 0.5 | AA44: =IF(LEFT(I44,1)="<",(RIGHT(I44,LEN(I44)-1))/2,I44) -> 1 | AB44: =IF(LEFT(J44,1)="<",(RIGHT(J44,LEN(J44)-1))/2,J44) -> 21 | AC44: =IF(LEFT(K44,1)="<",(RIGHT(K44,LEN(K44)-1))/2,K44) -> 10 | AD44: =IF(LEFT(L44,1)="<",(RIGHT(L44,LEN(L44)-1))/2,L44) -> 0 | AE44: =IF(LEFT(M44,1)="<",(RIGHT(M44,LEN(M44)-1))/2,M44) -> 291 | ... AM44: =IF(LEFT(U44,1)="<",(RIGHT(U44,LEN(U44)-1))/2,U44) -> 342
C45: Ore Assay | D45: Sarsfield HG Ore Assay | E45: 39790 | F45: 120 | G45: 10 | H45: 1 | I45: 4 | J45: 30 | K45: 12 | L45: 12 | M45: 1000 | N45: 950 | O45: 0.05 | P45: 1350 | Q45: 13 | R45: 9 | S45: 4.3 | T45: 1.6 | U45: 160 | X45: =IF(LEFT(F45,1)="<",(RIGHT(F45,LEN(F45)-1))/2,F45) -> 120 | Y45: =IF(LEFT(G45,1)="<",(RIGHT(G45,LEN(G45)-1))/2,G45) -> 10 | Z45: =IF(LEFT(H45,1)="<",(RIGHT(H45,LEN(H45)-1))/2,H45) -> 1 | AA45: =IF(LEFT(I45,1)="<",(RIGHT(I45,LEN(I45)-1))/2,I45) -> 4 | AB45: =IF(LEFT(J45,1)="<",(RIGHT(J45,LEN(J45)-1))/2,J45) -> 30 | AC45: =IF(LEFT(K45,1)="<",(RIGHT(K45,LEN(K45)-1))/2,K45) -> 12 | AD45: =IF(LEFT(L45,1)="<",(RIGHT(L45,LEN(L45)-1))/2,L45) -> 12 | AE45: =IF(LEFT(M45,1)="<",(RIGHT(M45,LEN(M45)-1))/2,M45) -> 1000 | ... AM45: =IF(LEFT(U45,1)="<",(RIGHT(U45,LEN(U45)-1))/2,U45) -> 160
C46: Ore Assay | D46: Sarsfield Combined Ore Assay | E46: 39790 | F46: 107.5 | G46: 10 | H46: 1 | I46: 2.2 | J46: 32.5 | K46: 12 | L46: 12 | M46: 850 | N46: 950 | O46: 0.05 | P46: 1375 | Q46: 13 | R46: 7.35 | S46: 2.55 | T46: 1.75 | U46: 140 | X46: =IF(LEFT(F46,1)="<",(RIGHT(F46,LEN(F46)-1))/2,F46) -> 107.5 | Y46: =IF(LEFT(G46,1)="<",(RIGHT(G46,LEN(G46)-1))/2,G46) -> 10 | Z46: =IF(LEFT(H46,1)="<",(RIGHT(H46,LEN(H46)-1))/2,H46) -> 1 | AA46: =IF(LEFT(I46,1)="<",(RIGHT(I46,LEN(I46)-1))/2,I46) -> 2.2 | AB46: =IF(LEFT(J46,1)="<",(RIGHT(J46,LEN(J46)-1))/2,J46) -> 32.5 | AC46: =IF(LEFT(K46,1)="<",(RIGHT(K46,LEN(K46)-1))/2,K46) -> 12 | AD46: =IF(LEFT(L46,1)="<",(RIGHT(L46,LEN(L46)-1))/2,L46) -> 12 | AE46: =IF(LEFT(M46,1)="<",(RIGHT(M46,LEN(M46)-1))/2,M46) -> 850 | ... AM46: =IF(LEFT(U46,1)="<",(RIGHT(U46,LEN(U46)-1))/2,U46) -> 140
C47: Ore Assay | D47: Sarsfield LG Ore | E47: 39790 | F47: 95 | G47: 10 | H47: 1 | I47: 0.4 | J47: 35 | K47: 12 | M47: 700 | N47: 950 | O47: 0.05 | P47: 1400 | Q47: 13 | R47: 5.7 | S47: 0.8 | T47: 1.9 | U47: 120 | X47: =IF(LEFT(F47,1)="<",(RIGHT(F47,LEN(F47)-1))/2,F47) -> 95 | Y47: =IF(LEFT(G47,1)="<",(RIGHT(G47,LEN(G47)-1))/2,G47) -> 10 | Z47: =IF(LEFT(H47,1)="<",(RIGHT(H47,LEN(H47)-1))/2,H47) -> 1 | AA47: =IF(LEFT(I47,1)="<",(RIGHT(I47,LEN(I47)-1))/2,I47) -> 0.4 | AB47: =IF(LEFT(J47,1)="<",(RIGHT(J47,LEN(J47)-1))/2,J47) -> 35 | AC47: =IF(LEFT(K47,1)="<",(RIGHT(K47,LEN(K47)-1))/2,K47) -> 12 | AD47: =IF(LEFT(L47,1)="<",(RIGHT(L47,LEN(L47)-1))/2,L47) -> 0 | AE47: =IF(LEFT(M47,1)="<",(RIGHT(M47,LEN(M47)-1))/2,M47) -> 700 | ... AM47: =IF(LEFT(U47,1)="<",(RIGHT(U47,LEN(U47)-1))/2,U47) -> 120
C48: Ore Assay | D48: BRW Ore Assay | E48: 43666 | F48: 155 | G48: <50 | H48: <1 | I48: 4 | J48: 16 | K48: 2 | M48: 141 | N48: 350 | O48: <0.1 | P48: 2770 | Q48: 7 | R48: 9 | S48: <5 | T48: <5 | U48: 946 | X48: =IF(LEFT(F48,1)="<",(RIGHT(F48,LEN(F48)-1))/2,F48) -> 155 | Y48: =IF(LEFT(G48,1)="<",(RIGHT(G48,LEN(G48)-1))/2,G48) -> 25 | Z48: =IF(LEFT(H48,1)="<",(RIGHT(H48,LEN(H48)-1))/2,H48) -> 0.5 | AA48: =IF(LEFT(I48,1)="<",(RIGHT(I48,LEN(I48)-1))/2,I48) -> 4 | AB48: =IF(LEFT(J48,1)="<",(RIGHT(J48,LEN(J48)-1))/2,J48) -> 16 | AC48: =IF(LEFT(K48,1)="<",(RIGHT(K48,LEN(K48)-1))/2,K48) -> 2 | AD48: =IF(LEFT(L48,1)="<",(RIGHT(L48,LEN(L48)-1))/2,L48) -> 0 | AE48: =IF(LEFT(M48,1)="<",(RIGHT(M48,LEN(M48)-1))/2,M48) -> 141 | ... AM48: =IF(LEFT(U48,1)="<",(RIGHT(U48,LEN(U48)-1))/2,U48) -> 946
C49: Ore Assay | D49: SRS Ore | E49: 43666 | F49: 41 | G49: <50 | H49: <1 | I49: <1 | J49: 14 | K49: 7 | M49: 314 | N49: 350 | O49: <0.1 | P49: 627 | Q49: 7 | R49: 20 | S49: <5 | T49: <5 | U49: 89 | X49: =IF(LEFT(F49,1)="<",(RIGHT(F49,LEN(F49)-1))/2,F49) -> 41 | Y49: =IF(LEFT(G49,1)="<",(RIGHT(G49,LEN(G49)-1))/2,G49) -> 25 | Z49: =IF(LEFT(H49,1)="<",(RIGHT(H49,LEN(H49)-1))/2,H49) -> 0.5 | AA49: =IF(LEFT(I49,1)="<",(RIGHT(I49,LEN(I49)-1))/2,I49) -> 0.5 | AB49: =IF(LEFT(J49,1)="<",(RIGHT(J49,LEN(J49)-1))/2,J49) -> 14 | AC49: =IF(LEFT(K49,1)="<",(RIGHT(K49,LEN(K49)-1))/2,K49) -> 7 | AD49: =IF(LEFT(L49,1)="<",(RIGHT(L49,LEN(L49)-1))/2,L49) -> 0 | AE49: =IF(LEFT(M49,1)="<",(RIGHT(M49,LEN(M49)-1))/2,M49) -> 314 | ... AM49: =IF(LEFT(U49,1)="<",(RIGHT(U49,LEN(U49)-1))/2,U49) -> 89
C50: Ore Assay | D50: S9 Ore Raw | E50: 43666 | F50: 9 | G50: <50 | H50: <1 | I50: <1 | J50: 9 | K50: 3 | M50: 185 | N50: 290 | O50: <0.1 | P50: 825 | Q50: 6 | R50: <5 | S50: <5 | T50: <5 | U50: 49 | X50: =IF(LEFT(F50,1)="<",(RIGHT(F50,LEN(F50)-1))/2,F50) -> 9 | Y50: =IF(LEFT(G50,1)="<",(RIGHT(G50,LEN(G50)-1))/2,G50) -> 25 | Z50: =IF(LEFT(H50,1)="<",(RIGHT(H50,LEN(H50)-1))/2,H50) -> 0.5 | AA50: =IF(LEFT(I50,1)="<",(RIGHT(I50,LEN(I50)-1))/2,I50) -> 0.5 | AB50: =IF(LEFT(J50,1)="<",(RIGHT(J50,LEN(J50)-1))/2,J50) -> 9 | AC50: =IF(LEFT(K50,1)="<",(RIGHT(K50,LEN(K50)-1))/2,K50) -> 3 | AD50: =IF(LEFT(L50,1)="<",(RIGHT(L50,LEN(L50)-1))/2,L50) -> 0 | AE50: =IF(LEFT(M50,1)="<",(RIGHT(M50,LEN(M50)-1))/2,M50) -> 185 | ... AM50: =IF(LEFT(U50,1)="<",(RIGHT(U50,LEN(U50)-1))/2,U50) -> 49
C51: Ore Assay | D51: S9 Ore Prod (rapid crusher) | E51: 43666 | F51: 36 | G51: <50 | H51: <1 | I51: <1 | J51: 17 | K51: 4 | M51: 229 | N51: 410 | O51: <0.1 | P51: 751 | Q51: 6 | R51: 85 | S51: <5 | T51: <5 | U51: 76 | X51: =IF(LEFT(F51,1)="<",(RIGHT(F51,LEN(F51)-1))/2,F51) -> 36 | Y51: =IF(LEFT(G51,1)="<",(RIGHT(G51,LEN(G51)-1))/2,G51) -> 25 | Z51: =IF(LEFT(H51,1)="<",(RIGHT(H51,LEN(H51)-1))/2,H51) -> 0.5 | AA51: =IF(LEFT(I51,1)="<",(RIGHT(I51,LEN(I51)-1))/2,I51) -> 0.5 | AB51: =IF(LEFT(J51,1)="<",(RIGHT(J51,LEN(J51)-1))/2,J51) -> 17 | AC51: =IF(LEFT(K51,1)="<",(RIGHT(K51,LEN(K51)-1))/2,K51) -> 4 | AD51: =IF(LEFT(L51,1)="<",(RIGHT(L51,LEN(L51)-1))/2,L51) -> 0 | AE51: =IF(LEFT(M51,1)="<",(RIGHT(M51,LEN(M51)-1))/2,M51) -> 229 | ... AM51: =IF(LEFT(U51,1)="<",(RIGHT(U51,LEN(U51)-1))/2,U51) -> 76
C52: Average Ore Assay | D52: Average Ore Assay | F52: =AVERAGE(X44:X51) -> 81.0625 | G52: =AVERAGE(Y44:Y51) -> 19.375 | H52: =AVERAGE(Z44:Z51) -> 0.6875 | I52: =AVERAGE(AA44:AA51) -> 1.6375 | J52: =AVERAGE(AB44:AB51) -> 21.8125 | K52: =AVERAGE(AC44:AC51) -> 7.75 | L52: =K52 -> 7.75 | M52: =AVERAGE(AE44:AE51) -> 463.75 | N52: =AVERAGE(AF44:AF51) -> 571.25 | O52: =AVERAGE(AG44:AG51) -> 0.05 | P52: =AVERAGE(AH44:AH51) -> 1225.625 | Q52: =AVERAGE(AI44:AI51) -> 9.125 | R52: =AVERAGE(AJ44:AJ51) -> 25.81875 | S52: =AVERAGE(AK44:AK51) -> 2.51875 | T52: =AVERAGE(AL44:AL51) -> 2.21875 | U52: =AVERAGE(AM44:AM51) -> 240.25
C54: Ore Assay | D54: Sarsfield LG Ore | E54: 39790 | F54: 95 | G54: 10 | H54: 1 | I54: 0.4 | J54: 35 | K54: 12 | M54: 700 | N54: 950 | O54: 0.05 | P54: 1400 | Q54: 13 | R54: 5.7 | S54: 0.8 | T54: 1.9 | U54: 120 | X54: =IF(LEFT(F54,1)="<",(RIGHT(F54,LEN(F54)-1))/2,F54) -> 95 | Y54: =IF(LEFT(G54,1)="<",(RIGHT(G54,LEN(G54)-1))/2,G54) -> 10 | Z54: =IF(LEFT(H54,1)="<",(RIGHT(H54,LEN(H54)-1))/2,H54) -> 1 | AA54: =IF(LEFT(I54,1)="<",(RIGHT(I54,LEN(I54)-1))/2,I54) -> 0.4 | AB54: =IF(LEFT(J54,1)="<",(RIGHT(J54,LEN(J54)-1))/2,J54) -> 35 | AC54: =IF(LEFT(K54,1)="<",(RIGHT(K54,LEN(K54)-1))/2,K54) -> 12 | AD54: =IF(LEFT(L54,1)="<",(RIGHT(L54,LEN(L54)-1))/2,L54) -> 0 | AE54: =IF(LEFT(M54,1)="<",(RIGHT(M54,LEN(M54)-1))/2,M54) -> 700 | ... AM54: =IF(LEFT(U54,1)="<",(RIGHT(U54,LEN(U54)-1))/2,U54) -> 120
C55: Ore Assay | D55: Sarsfield HG Ore Assay | E55: 39790 | F55: 120 | G55: 10 | H55: 1 | I55: 4 | J55: 30 | K55: 12 | L55: 12 | M55: 1000 | N55: 950 | O55: 0.05 | P55: 1350 | Q55: 13 | R55: 9 | S55: 4.3 | T55: 1.6 | U55: 160 | X55: =IF(LEFT(F55,1)="<",(RIGHT(F55,LEN(F55)-1))/2,F55) -> 120 | Y55: =IF(LEFT(G55,1)="<",(RIGHT(G55,LEN(G55)-1))/2,G55) -> 10 | Z55: =IF(LEFT(H55,1)="<",(RIGHT(H55,LEN(H55)-1))/2,H55) -> 1 | AA55: =IF(LEFT(I55,1)="<",(RIGHT(I55,LEN(I55)-1))/2,I55) -> 4 | AB55: =IF(LEFT(J55,1)="<",(RIGHT(J55,LEN(J55)-1))/2,J55) -> 30 | AC55: =IF(LEFT(K55,1)="<",(RIGHT(K55,LEN(K55)-1))/2,K55) -> 12 | AD55: =IF(LEFT(L55,1)="<",(RIGHT(L55,LEN(L55)-1))/2,L55) -> 12 | AE55: =IF(LEFT(M55,1)="<",(RIGHT(M55,LEN(M55)-1))/2,M55) -> 1000 | ... AM55: =IF(LEFT(U55,1)="<",(RIGHT(U55,LEN(U55)-1))/2,U55) -> 160
C56: Ore Assay | D56: Sarsfield Combined Ore Assay | E56: 39790 | F56: 107.5 | G56: 10 | H56: 1 | I56: 2.2 | J56: 32.5 | K56: 12 | L56: 12 | M56: 850 | N56: 950 | O56: 0.05 | P56: 1375 | Q56: 13 | R56: 7.35 | S56: 2.55 | T56: 1.75 | U56: 140 | X56: =IF(LEFT(F56,1)="<",(RIGHT(F56,LEN(F56)-1))/2,F56) -> 107.5 | Y56: =IF(LEFT(G56,1)="<",(RIGHT(G56,LEN(G56)-1))/2,G56) -> 10 | Z56: =IF(LEFT(H56,1)="<",(RIGHT(H56,LEN(H56)-1))/2,H56) -> 1 | AA56: =IF(LEFT(I56,1)="<",(RIGHT(I56,LEN(I56)-1))/2,I56) -> 2.2 | AB56: =IF(LEFT(J56,1)="<",(RIGHT(J56,LEN(J56)-1))/2,J56) -> 32.5 | AC56: =IF(LEFT(K56,1)="<",(RIGHT(K56,LEN(K56)-1))/2,K56) -> 12 | AD56: =IF(LEFT(L56,1)="<",(RIGHT(L56,LEN(L56)-1))/2,L56) -> 12 | AE56: =IF(LEFT(M56,1)="<",(RIGHT(M56,LEN(M56)-1))/2,M56) -> 850 | ... AM56: =IF(LEFT(U56,1)="<",(RIGHT(U56,LEN(U56)-1))/2,U56) -> 140
C57: Average Sarsfield Ore Assay | D57: Average Sarsfield Ore Assay | F57: =AVERAGE(F54:F56) -> 107.5 | G57: =AVERAGE(G54:G56) -> 10 | H57: =AVERAGE(H54:H56) -> 1 | I57: =AVERAGE(I54:I56) -> 2.2 | J57: =AVERAGE(J54:J56) -> 32.5 | K57: =AVERAGE(K54:K56) -> 12 | L57: =K57 -> 12 | M57: =AVERAGE(M54:M56) -> 850 | N57: =AVERAGE(N54:N56) -> 950 | O57: =AVERAGE(O54:O56) -> 0.05 | P57: =AVERAGE(P54:P56) -> 1375 | Q57: =AVERAGE(Q54:Q56) -> 13 | R57: =AVERAGE(R54:R56) -> 7.35 | S57: =AVERAGE(S54:S56) -> 2.55 | T57: =AVERAGE(T54:T56) -> 1.75 | U57: =AVERAGE(U54:U56) -> 140
C60: Assays are not required to be sampled every year if they are still representative - sampling is recommended usually every 5 years or if there is a significant change to the operations
C61: Enter “less than” (<) if tested but not detected. “Less than” values will be recorded in the final report as half the recorded “less than” value entered
C62: Road Assays are used in estimating wheel generated dust and wind blown dust
C63: Ore Assays are used for estimating metals in dust from loading and the processing circuit
C64: Waste Assays are used for estimating metals in dust from waste dump activities such as bulldozing and waste unloading
C65: Topsoil Assay is used to estimate metals in wind blown dust from topsoil stockpiles and scraper operations
C67: Paste raw data below:
C69: Table 9 from the NPI Mining Manual

Sheet MA - Open Areas
C3: Ravenswood Operations | G3: The Open Areas tab is used with assays on the Geology tab to estimate wind blown dust | Q3: Moisture Content (%) | R3: 2
C4: 01/07/2022 - 30/06/2023 | G4: Open areas can be aligned with other government reporting programs, e.g. the MRF (in WA) or annual environmental reports | Q4: Silt Content (%) | R4: 10
G5: Open the 2023 workspace, add in the new satellite image and amend the polygons to cover any new disturbance for FY23-24. Then, update the values in red below using the areas of the updated polygons.
C6: Open Areas
E7: Data Sources: | G7: Map Info NPI Disturbance 2023.WOR
C8: Other Open Areas & Inactive Stockpiles
G9: Breakdown of Total Disturbance (ha) | Q9: Assay 1
C10: Area Category | D10: Name/Lease/Tenement | E10: Total Disturbance (ha) | G10: Exposed Area (no erosion reduction) | H10: Primary rehabilitation | I10: Secondary rehabilitation | J10: Revegetation | K10: Fully rehabilitated (release) vegetation | L10: Area visibly not producing dust | N10: Dust Suppression | Q10: Assay Name | R10: Per cent contribution to Open Area
E11: Dust Reduction Percentage (1): | G11: 0 | H11: 0.3 | I11: 0.6 | J11: 0.9 | K11: 1 | L11: 100% (not including rehab)
C12: Other Open Areas and Inactive Stockpiles
C13: Waste Rock Dump | D13: Mt Wright Waste Dump & ROM | E13: =SUM(G13:L13) -> 5.07 | G13: 5.07 | H13: 0 | I13: 0 | J13: 0 | K13: 0 | L13: 0 | N13: Nil | Q13: Average Ore Assay | R13: 1
C14: Waste Rock Dump | D14: Mt Wright Glory Hole | E14: =SUM(G14:L14) -> 3.3 | G14: 0 | H14: 0 | I14: 0 | J14: 3.3 | K14: 0 | N14: Nil | Q14: Combined Waste Assay | R14: 1
C15: Waste Rock Dump | D15: SYC OCA Waste Dump | E15: =SUM(G15:L15) -> 11.2 | H15: 0 | I15: 0 | J15: 11.2 | K15: 0 | L15: 0 | N15: Nil | Q15: SAR Waste Assay | R15: 1
C16: Waste Rock Dump | D16: Nolans Waste Dump | E16: =SUM(G16:L16) -> 31.6 | G16: 28.3 | H16: 0 | I16: 0 | J16: 3.3 | K16: 0 | N16: Nil | Q16: NOL E Waste | R16: 1
C17: Waste Rock Dump | D17: Sarsfield Waste Dump | E17: =SUM(G17:L17) -> 140.53 | G17: 122 | H17: 0 | I17: 0 | J17: =16.43+2.1 -> 18.53 | K17: 0 | N17: Nil | Q17: SAR Waste Assay | R17: 1
C18: Waste Rock Dump | D18: Buck Reef Waste Dump | E18: =SUM(G18:L18) -> 25.05 | G18: 25.05 | H18: 0 | I18: 0 | J18: 0 | K18: 0 | N18: Nil | Q18: Combined Waste Assay | R18: 1
C19: Open Area (Waste Rock Dump) | E19: =SUM(G19:L19) -> 216.75 | G19: =SUM(G13:G18) -> 180.42 | H19: =SUM(H13:H18) -> 0 | I19: =SUM(I13:I18) -> 0 | J19: =SUM(J13:J18) -> 36.33 | K19: =SUM(K13:K18) -> 0 | L19: =SUM(L13:L18) -> 0 | N19: Nil | Q19: Average Waste Assay | R19: 1
C21: Roads and Access Track | D21: Roads and Access Tracks | E21: =SUM(G21:L21) -> 34.1 | G21: 34.1 | H21: 0 | I21: 0 | J21: 0 | K21: 0 | L21: 0 | N21: Watering (≤2 l/m2/hr) | Q21: Combined Road Assay | R21: 1
C22: Roads and Access Track | D22: Bitumen Road | E22: =SUM(G22:L22) -> 1.29 | G22: 0 | H22: 0 | I22: 0 | J22: 0 | K22: 0 | L22: 1.29 | N22: NR | Q22: NR | R22: 0
C23: Haul Road | D23: All Haul Roads | E23: =SUM(G23:L23) -> 31.15 | G23: 31.15 | H23: 0 | I23: 0 | J23: 0 | K23: 0 | L23: 0 | N23: Watering (≤2 l/m2/hr) | Q23: Combined Road Assay | R23: 1
C24: Open Area (Haul Roads and Access Tracks) | E24: =SUM(G24:L24) -> 66.54 | G24: =SUM(G21:G23) -> 65.25 | H24: =SUM(H21:H23) -> 0 | I24: =SUM(I21:I23) -> 0 | J24: =SUM(J21:J23) -> 0 | K24: =SUM(K21:K23) -> 0 | L24: =SUM(L21:L23) -> 1.29 | N24: Watering (≤2 l/m2/hr) | Q24: Combined Road Assay | R24: 1
C26: Accommodation Village | D26: SPQ & Company Housing | E26: =SUM(G26:L26) -> 9.15 | G26: 9.15 | H26: 0 | I26: 0 | J26: 0 | K26: 0 | L26: 0 | N26: Nil | Q26: Combined Road Assay | R26: 1
C27: Plant Site | D27: Sandy Creek site | E27: =SUM(G27:L27) -> 28.7 | G27: 16.7 | H27: 0 | I27: 0 | J27: 12 | K27: 0 | N27: Nil | Q27: Combined Road Assay | R27: 1
C28: Heap Leach Pad | D28: SC (Sandy Creek) Heapleach Pad 1 | E28: =SUM(G28:L28) -> 6.7 | G28: 6.7 | H28: 0 | I28: 0 | J28: 0 | K28: 0 | L28: 0 | N28: Nil | Q28: Average Topsoil Assay | R28: 1
C29: Plant Site | D29: Mount Wright site | E29: =SUM(G29:L29) -> 8.28 | G29: 8.28 | H29: 0 | I29: 0 | K29: 0 | L29: 0 | N29: Nil | Q29: Combined Road Assay | R29: 1
C30: Open Area (Plant Site - No Watering) | E30: =SUM(G30:L30) -> 52.83 | G30: =SUM(G26:G29) -> 40.83 | H30: =SUM(H26:H29) -> 0 | I30: =SUM(I26:I29) -> 0 | J30: =SUM(J26:J29) -> 12 | K30: =SUM(K26:K29) -> 0 | L30: =SUM(L26:L29) -> 0 | N30: Nil | Q30: Combined Road Assay | R30: 1
C32: Plant Site | D32: Nolans & BRW Process Areas | E32: =SUM(G32:L32) -> 35.11 | G32: 35.11 | H32: 0 | I32: 0 | J32: 0 | K32: 0 | N32: Watering (≤2 l/m2/hr) | Q32: Combined Road Assay | R32: 1
C33: ROM Pad | D33: Feeder 5 ROM | E33: =SUM(G33:L33) -> 0.89 | G33: 0.89 | H33: 0 | I33: 0 | J33: 0 | K33: 0 | L33: 0 | N33: Watering (≤2 l/m2/hr) | Q33: BRW Ore | R33: 1
C34: ROM Pad | D34: BRW ROM Pad | E34: =SUM(G34:L34) -> 15.84 | G34: 15.84 | H34: 0 | I34: 0 | J34: 0 | K34: 0 | L34: 0 | N34: Watering (≤2 l/m2/hr) | Q34: BRW Ore | R34: 1
C35: ROM Pad | D35: Nolans ROM Pad | E35: =SUM(G35:L35) -> 14.95 | G35: 14.95 | H35: 0 | I35: 0 | J35: 0 | K35: 0 | L35: 0 | N35: Watering (≤2 l/m2/hr) | Q35: BRW Ore | R35: 1
C36: Open Area (Plant Site - Watering) | E36: =SUM(G36:L36) -> 66.79 | G36: =SUM(G32:G35) -> 66.79 | H36: =SUM(H32:H35) -> 0 | I36: =SUM(I32:I35) -> 0 | J36: =SUM(J32:J35) -> 0 | K36: =SUM(K32:K35) -> 0 | L36: =SUM(L32:L35) -> 0 | N36: Watering (≤2 l/m2/hr) | Q36: Combined Road Assay | R36: 1
C38: Retired Tailings Storage Facility | D38: NTSF (Rehabilitated) | E38: =SUM(G38:L38) -> 72.0199 | G38: 0 | H38: 0 | I38: 0 | J38: 72.0199 | K38: 0 | L38: 0 | N38: Nil | Q38: Average Topsoil Assay | R38: 1
C39: Retired Tailings Storage Facility | D39: Sandy Creek TSF (Rehabilitated) | J39: 14.2 | N39: Nil
C40: Open Area (TSF - Not Active) | E40: =SUM(G40:L40) -> 72.0199 | G40: =SUM(G38) -> 0 | H40: =SUM(H38) -> 0 | I40: =SUM(I38) -> 0 | J40: =SUM(J38) -> 72.0199 | K40: =SUM(K38) -> 0 | L40: =SUM(L38) -> 0 | N40: Nil | Q40: Average Topsoil Assay | R40: 1
C42: General Open Area | D42: Sarsfield Acoustic Bund & Redback | E42: =SUM(G42:L42) -> 6.79 | G42: 6.79 | H42: 0 | I42: 0 | K42: 0 | L42: 0 | N42: Nil | Q42: SAR Topsoil | R42: 1
C43: General Open Area | D43: BRW Noise Bund | E43: =SUM(G43:L43) -> 11.798 | G43: 11.798 | H43: 0 | I43: 0 | J43: 0 | K43: 0 | L43: 0 | N43: Nil | Q43: Average Topsoil Assay | R43: 1
C44: General Open Area | D44: Golf Course | E44: =SUM(G44:L44) -> 8 | G44: 0 | H44: 0 | I44: 0 | J44: 8 | K44: 0 | L44: 0 | N44: Nil | Q44: Average Topsoil Assay | R44: 1
C45: General Open Area | D45: Water Management | E45: =SUM(G45:L45) -> 7.15 | G45: 0 | H45: 0 | I45: 0 | J45: 0 | K45: 0 | L45: 7.15 | N45: Nil | Q45: Average Topsoil Assay | R45: 1
C46: Open Area (General Open Area - No Watering) | E46: =SUM(G46:L46) -> 33.738 | G46: =SUM(G42:G45) -> 18.588 | H46: =SUM(H42:H45) -> 0 | I46: =SUM(I42:I45) -> 0 | J46: =SUM(J42:J45) -> 8 | K46: =SUM(K42:K45) -> 0 | L46: =SUM(L42:L45) -> 7.15 | N46: Nil | Q46: Average Topsoil Assay | R46: 1
C48: General Open Area | D48: TSF Expansion Area | E48: =SUM(G48:L48) -> 112 | G48: 112 | H48: 0 | I48: 0 | J48: 0 | K48: 0 | L48: 0 | N48: Watering (≤2 l/m2/hr) | Q48: Average Topsoil Assay | R48: 1
C49: Open Area (General Open Area - Watering) | E49: =SUM(G49:L49) -> 112 | G49: =SUM(G48) -> 112 | H49: =SUM(H48) -> 0 | I49: =SUM(I48) -> 0 | J49: =SUM(J48) -> 0 | K49: =SUM(K48) -> 0 | L49: =SUM(L48) -> 0 | N49: Watering (≤2 l/m2/hr) | Q49: Average Topsoil Assay | R49: 1
C51: Topsoil Stockpile | D51: SWRD Main | E51: =SUM(G51:L51) -> 1.8 | G51: 1.8 | H51: 0 | I51: 0 | J51: 0 | K51: 0 | L51: 0 | N51: Nil | Q51: SAR Topsoil | R51: 1
C52: Topsoil Stockpile | D52: NTSFE Dumps | G52: 15.4 | N52: Nil | Q52: Average Topsoil Assay
C53: Topsoil Stockpile | D53: Topsoil dump 3 | E53: =SUM(G53:L53) -> 3.52 | G53: 3.52 | H53: 0 | I53: 0 | J53: 0 | K53: 0 | L53: 0 | N53: Nil | Q53: Average Topsoil Assay | R53: 1
C54: Topsoil Stockpile | D54: Deco Dump - Sarsfield | E54: =SUM(G54:L54) -> 4.74 | G54: 4.74 | H54: 0 | I54: 0 | J54: 0 | K54: 0 | L54: 0 | N54: Watering (≤2 l/m2/hr) | Q54: SAR Topsoil | R54: 1
C55: Open Area (Topsoil Stockpile) | E55: =SUM(G55:L55) -> 25.46 | G55: =SUM(G51:G54) -> 25.46 | H55: =SUM(H51:H54) -> 0 | I55: =SUM(I51:I54) -> 0 | J55: =SUM(J51:J54) -> 0 | K55: =SUM(K51:K54) -> 0 | L55: =SUM(L51:L54) -> 0 | N55: Nil | Q55: Average Topsoil Assay | R55: 1
C57: Borrow Pit | D57: Borrow Pit | E57: =SUM(G57:L57) -> 0.3 | G57: 0.3 | H57: 0 | I57: 0 | J57: 0 | K57: 0 | L57: 0 | N57: Nil | Q57: Average Topsoil Assay | R57: 1
C58: Laydown Area | D58: Laydown areas & park-ups | E58: =SUM(G58:L58) -> 86.25 | G58: 86.25 | H58: 0 | I58: 0 | J58: 0 | K58: 0 | L58: 0 | N58: Watering (≤2 l/m2/hr) | Q58: Combined Road Assay | R58: 1
C59: Other Infrastructure | D59: Sewage Treatment Plant | E59: =SUM(G59:L59) -> 0.7 | G59: 0.7 | H59: 0 | I59: 0 | J59: 0 | K59: 0 | L59: 0 | N59: Nil | Q59: Average Topsoil Assay | R59: 1
C60: Other Infrastructure | D60: Magazine | E60: =SUM(G60:L60) -> 0.3 | G60: 0.3 | H60: 0 | I60: 0 | J60: 0 | K60: 0 | L60: 0 | N60: Nil | Q60: Average Topsoil Assay | R60: 1
C61: Landfill | D61: Landfill | E61: =SUM(G61:L61) -> 2.6 | G61: 2.6 | H61: 0 | I61: 0 | J61: 0 | K61: 0 | L61: 0 | N61: Nil | Q61: Average Topsoil Assay | R61: 1
C62: Other | E62: =SUM(G62:L62) -> 90.15 | G62: =SUM(G57:G61) -> 90.15 | H62: =SUM(H57:H61) -> 0 | I62: =SUM(I57:I61) -> 0 | J62: =SUM(J57:J61) -> 0 | K62: =SUM(K57:K61) -> 0 | L62: =SUM(L57:L61) -> 0 | N62: Nil | Q62: Average Topsoil Assay | R62: 1
C64: [select] | E64: =SUM(G64:L64) -> 0 | N64: [select] | Q64: [select]
C65: [select] | E65: =SUM(G65:L65) -> 0 | N65: [select] | Q65: [select]
C66: [select] | E66: =SUM(G66:L66) -> 0 | N66: [select] | Q66: [select]
C68: Not Reportable - No Dust
C69: Pit | D69: BRW Pit | E69: =SUM(G69:L69) -> 46.3 | G69: 46.3 | H69: 0 | I69: 0 | J69: 0 | K69: 0 | L69: 0 | N69: Nil | Q69: Combined Waste Assay | R69: 1
C70: Pit | D70: Sarsfield/Nolans E Pit | E70: =SUM(G70:L70) -> 91.7 | G70: 91.7 | H70: 0 | I70: 0 | J70: 0 | K70: 0 | N70: Nil | Q70: SAR Waste | R70: 1
C71: Tailings Storage Facility | D71: NTSFE (Active) | E71: =SUM(G71:L71) -> 69 | G71: 69 | H71: 0 | I71: 0 | J71: 0 | K71: 0 | L71: 0 | N71: Nil | Q71: Tailings Assay | R71: 1
C73: Active Stockpiles
G74: Breakdown of Total Disturbance (ha) | Q74: Assay 1
C75: Area Category | D75: Name/Lease/Tenement | E75: Total Disturbance (ha) | G75: Exposed Area (no erosion reduction) | H75: Primary earthworks (reshaping/profiling, drainage structures installed) | J75: Rock armour and/or topsoil applied | L75: Area visibly not producing dust | N75: Enclosure | O75: Dust Suppression | Q75: Assay Name | R75: Per cent contribution to Open Area
E76: Dust Reduction Percentage (1): | G76: 0 | H76: 0.3 | J76: 0.3 | L76: 1
C77: Active Stockpiles
C78: Ore Stockpile | D78: Nolans Cone | E78: =SUM(G78:L78) -> 0.67 | G78: 0.67 | H78: 0 | J78: 0 | L78: 0 | N78: None | O78: Watering | Q78: BRW Ore | R78: 1
C79: Low Grade Stockpile | D79: Modular crusher product stockpile | E79: =SUM(G79:L79) -> 0.05 | G79: 0.05 | H79: 0 | J79: 0 | L79: 0 | N79: None | O79: Nil | Q79: BRW Ore | R79: 1
C80: Ore Stockpile | D80: Crusher 1 Cone | E80: =SUM(G80:L80) -> 0.2 | G80: 0.2 | H80: 0 | J80: 0 | L80: 0 | N80: None | O80: Nil | Q80: BRW Ore | R80: 1
C81: Open Area (Ore Stockpile) | E81: =SUM(G81:L81) -> 0.92 | G81: =SUM(G78:G80) -> 0.92 | H81: =SUM(H78:H80) -> 0 | I81: =SUM(I78:I80) -> 0 | J81: =SUM(J78:J80) -> 0 | K81: =SUM(K78:K80) -> 0 | L81: =SUM(L78:L80) -> 0 | N81: None | O81: Nil | Q81: Average Ore Assay | R81: 1
C83: [select] | E83: =SUM(G83:L83) -> 0 | N83: [select] | O83: [select] | Q83: [select]
C84: [select] | E84: =SUM(G84:L84) -> 0 | N84: [select] | O84: [select] | Q84: [select]
C85: [select] | E85: =SUM(G85:L85) -> 0 | N85: [select] | O85: [select] | Q85: [select]
C87: OPEN AREA CATEGORIES
C88: [select]
C89: General Open Area
C90: Roads and Access Track
C91: Haul Road
C92: Open Pit
C93: ROM Pad
C94: Topsoil Stockpile
C95: Subsoil Stockpile
C96: Low Grade Stockpile
C97: Other Stockpile
C98: Waste Rock Dump
... C121: Haul Roads are defined as the road between the Mine and ROM. Access Roads are all other roads
B122: (1) | C122: Dust can be reduced based on the natural dustiness of the area or the extent of rehabilitation. Split each area into the categories based on the level of dust reduction (e.g. 30%, 60%, etc.)
C124: Paste raw data below:

Sheet GC - Material Transfers
C3: Ravenswood Operations | G3: Identify dust reduction facilities. These only apply to the actual transfer (drop) point, and not the rest of the conveyor
C4: 01/07/2022 - 30/06/2023 | G4: (1) If a precise moisture content is unavailable, please estimate if it is less than or greater than 4%
G5: Include rehandled material
C7: Material Moved | I7: Data Sources:
F9: Material Assay | G9: FY2023 Material Moved | H9: FY2024 Material Moved | I9: Unit | K9: Monthly Material moved (Tonnes) | X9: Water Sprays Unloading Only | Y9: Loading/ Unloading in Pit | Z9: Moisture Content (%)
C10: Class of Vehicle | D10: Description | E10: DataSources | K10: Jul | L10: Aug | M10: Sep | N10: Oct | O10: Nov | P10: Dec | Q10: Jan | R10: Feb | S10: Mar | T10: Apr | U10: May | V10: Jun
C11: Loader | D11: Total Loader (Ore) loaded in BRW Pit | F11: BRW Ore Assay | G11: 6658499.5 | H11: =SUM(H41, H49, H64, H80, H100, H103) -> 111092.8 | I11: Tonne | K11: =SUM(K41, K49, K64, K80, K100, K103) -> 19917 | L11: =SUM(L41, L49, L64, L80, L100, L103) -> 13794.3 | M11: =SUM(M41, M49, M64, M80, M100, M103) -> 11210.2 | N11: =SUM(N41, N49, N64, N80, N100, N103) -> 3369.2 | O11: =SUM(O41, O49, O64, O80, O100, O103) -> 10535.6 | P11: =SUM(P41, P49, P64, P80, P100, P103) -> 4514.9 | Q11: =SUM(Q41, Q49, Q64, Q80, Q100, Q103) -> 7784.5 | R11: =SUM(R41, R49, R64, R80, R100, R103) -> 2325.1 | ... V11: =SUM(V41, V49, V64, V80, V100, V103) -> 6720.6 | X11: No/NA | Y11: Yes - 100%
C12: Loader | D12: Total Loader (Ore) | F12: Average Ore Assay | G12: - | H12: =SUM(H45, H56, H59, H69, H76, H83, H90, H94, H96, H115) -> 8521453.9 | I12: Tonne | K12: =SUM(K45, K56, K59, K69, K76, K83, K90, K94, K96, K115) -> 701278.8 | L12: =SUM(L45, L56, L59, L69, L76, L83, L90, L94, L96, L115) -> 609260.3 | M12: =SUM(M45, M56, M59, M69, M76, M83, M90, M94, M96, M115) -> 640502.1 | N12: =SUM(N45, N56, N59, N69, N76, N83, N90, N94, N96, N115) -> 687579.4 | O12: =SUM(O45, O56, O59, O69, O76, O83, O90, O94, O96, O115) -> 635735.1 | P12: =SUM(P45, P56, P59, P69, P76, P83, P90, P94, P96, P115) -> 820024.1 | Q12: =SUM(Q45, Q56, Q59, Q69, Q76, Q83, Q90, Q94, Q96, Q115) -> 675113.4 | R12: =SUM(R45, R56, R59, R69, R76, R83, R90, R94, R96, R115) -> 576903.4 | ... V12: =SUM(V45, V56, V59, V69, V76, V83, V90, V94, V96, V115) -> 802671.8 | X12: No/NA | Y12: NA/No - 0%
C13: Loader | D13: Total Loader (Ore) loaded in SAR Pit | F13: Sarsfield Combined Ore Assay | G13: - | H13: =SUM(H86, H105) -> 5998.1 | I13: Tonne | K13: =SUM(K86, K105) -> 0 | L13: =SUM(L86, L105) -> 0 | M13: =SUM(M86, M105) -> 0 | N13: =SUM(N86, N105) -> 0 | O13: =SUM(O86, O105) -> 0 | P13: =SUM(P86, P105) -> 0 | Q13: =SUM(Q86, Q105) -> 0 | R13: =SUM(R86, R105) -> 353.5 | ... V13: =SUM(V86, V105) -> 0 | X13: No/NA | Y13: Yes - 100%
C14: Loader | D14: Total Loader (Ore) loaded in SAR Pit | F14: Sarsfield LG Ore | G14: - | H14: =SUM(H108) -> 16524.9 | I14: Tonne | K14: =SUM(K108) -> 0 | L14: =SUM(L108) -> 0 | M14: =SUM(M108) -> 0 | N14: =SUM(N108) -> 0 | O14: =SUM(O108) -> 0 | P14: =SUM(P108) -> 0 | Q14: =SUM(Q108) -> 0 | R14: =SUM(R108) -> 0 | ... V14: =SUM(V108) -> 0 | X14: No/NA | Y14: Yes - 100%
C15: Excavator | D15: Total Excavator (Ore) loaded in BRW Pit | F15: BRW Ore Assay | G15: 11995567 | H15: =SUM(H40, H50, H65, H79, H99, H102) -> 10440269 | I15: Tonne | K15: =SUM(K40, K50, K65, K79, K99, K102) -> 844695.4 | L15: =SUM(L40, L50, L65, L79, L99, L102) -> 1154883.2 | M15: =SUM(M40, M50, M65, M79, M99, M102) -> 1241005.5 | N15: =SUM(N40, N50, N65, N79, N99, N102) -> 758863.2 | O15: =SUM(O40, O50, O65, O79, O99, O102) -> 910794.4 | P15: =SUM(P40, P50, P65, P79, P99, P102) -> 709248.9 | Q15: =SUM(Q40, Q50, Q65, Q79, Q99, Q102) -> 629769.3 | R15: =SUM(R40, R50, R65, R79, R99, R102) -> 700669.9 | ... V15: =SUM(V40, V50, V65, V79, V99, V102) -> 519919.1 | X15: No/NA | Y15: Yes - 100%
C16: Excavator | D16: Total Excavator (Ore) | F16: Average Ore Assay | G16: - | H16: =SUM(H43, H60, H82, H93, H112) -> 221879.1 | I16: Tonne | K16: =SUM(K43, K60, K82, K93, K112) -> 18822 | L16: =SUM(L43, L60, L82, L93, L112) -> 38926 | M16: =SUM(M43, M60, M82, M93, M112) -> 2334.5 | N16: =SUM(N43, N60, N82, N93, N112) -> 52195.5 | O16: =SUM(O43, O60, O82, O93, O112) -> 27594.3 | P16: =SUM(P43, P60, P82, P93, P112) -> 82006.8 | Q16: =SUM(Q43, Q60, Q82, Q93, Q112) -> 0 | R16: =SUM(R43, R60, R82, R93, R112) -> 0 | ... V16: =SUM(V43, V60, V82, V93, V112) -> 0 | X16: No/NA | Y16: NA/No - 0%
C17: Excavator | D17: Total Excavator (Ore) loaded in SAR Pit | F17: Sarsfield HG Ore Assay | G17: - | H17: =SUM(H52) -> 112645 | I17: Tonne | K17: =SUM(K52) -> 0 | L17: =SUM(L52) -> 0 | M17: =SUM(M52) -> 0 | N17: =SUM(N52) -> 0 | O17: =SUM(O52) -> 0 | P17: =SUM(P52) -> 0 | Q17: =SUM(Q52) -> 81903.4 | R17: =SUM(R52) -> 30562 | ... V17: =SUM(V52) -> 0 | X17: No/NA | Y17: Yes - 100%
C18: Excavator | D18: Total Excavator (Ore) loaded in SAR Pit | F18: Sarsfield Combined Ore Assay | G18: - | H18: =SUM(H67, H85) -> 83197 | I18: Tonne | K18: =SUM(K67, K85) -> 0 | L18: =SUM(L67, L85) -> 0 | M18: =SUM(M67, M85) -> 0 | N18: =SUM(N67, N85) -> 0 | O18: =SUM(O67, O85) -> 0 | P18: =SUM(P67, P85) -> 0 | Q18: =SUM(Q67, Q85) -> 178 | R18: =SUM(R67, R85) -> 26977 | ... V18: =SUM(V67, V85) -> 195.2 | X18: No/NA | Y18: Yes - 100%
C19: Excavator | D19: Total Excavator (Ore) loaded in SAR Pit | F19: Sarsfield LG Ore | G19: 179887 | H19: =SUM(H107) -> 249954.3 | I19: Tonne | K19: =SUM(K107) -> 0 | L19: =SUM(L107) -> 0 | M19: =SUM(M107) -> 0 | N19: =SUM(N107) -> 0 | O19: =SUM(O107) -> 0 | P19: =SUM(P107) -> 0 | Q19: =SUM(Q107) -> 46227.7 | R19: =SUM(R107) -> 551.2 | ... V19: =SUM(V107) -> 76557.3 | X19: No/NA | Y19: Yes - 100%
C20: Haul/Dump Truck | D20: Total Haul/Dump Truck (Ore) loaded in BRW Pit | F20: BRW Ore Assay | G20: 13731906 | H20: =SUM(H42, H51, H66, H81, H101, H104) -> 10551362 | I20: Tonne | K20: =SUM(K42, K51, K66, K81, K101, K104) -> 864612.4 | L20: =SUM(L42, L51, L66, L81, L101, L104) -> 1168677.5 | M20: =SUM(M42, M51, M66, M81, M101, M104) -> 1252215.7 | N20: =SUM(N42, N51, N66, N81, N101, N104) -> 762232.4 | O20: =SUM(O42, O51, O66, O81, O101, O104) -> 921330 | P20: =SUM(P42, P51, P66, P81, P101, P104) -> 713763.8 | Q20: =SUM(Q42, Q51, Q66, Q81, Q101, Q104) -> 637553.8 | R20: =SUM(R42, R51, R66, R81, R101, R104) -> 702995 | ... V20: =SUM(V42, V51, V66, V81, V101, V104) -> 526639.7 | X20: No/NA | Y20: NA/No - 0%
C21: Haul/Dump Truck | D21: Total Haul/Dump Truck (Ore) | F21: Average Ore Assay | G21: - | H21: =SUM(H44, H61, H70, H84, H95, H116) -> 1144210 | I21: Tonne | K21: =SUM(K44, K61, K70, K84, K95, K116) -> 33659.8 | L21: =SUM(L44, L61, L70, L84, L95, L116) -> 72973.3 | M21: =SUM(M44, M61, M70, M84, M95, M116) -> 81404.6 | N21: =SUM(N44, N61, N70, N84, N95, N116) -> 132505.9 | O21: =SUM(O44, O61, O70, O84, O95, O116) -> 138900.4 | P21: =SUM(P44, P61, P70, P84, P95, P116) -> 104063.9 | Q21: =SUM(Q44, Q61, Q70, Q84, Q95, Q116) -> 18643.4 | R21: =SUM(R44, R61, R70, R84, R95, R116) -> 32618.4 | ... V21: =SUM(V44, V61, V70, V84, V95, V116) -> 85289.8 | X21: No/NA | Y21: NA/No - 0%
C22: Haul/Dump Truck | D22: Total Haul/Dump Truck (Ore) loaded in SAR Pit | F22: Sarsfield HG Ore Assay | G22: - | H22: =SUM(H53) -> 112645 | I22: Tonne | K22: =SUM(K53) -> 0 | L22: =SUM(L53) -> 0 | M22: =SUM(M53) -> 0 | N22: =SUM(N53) -> 0 | O22: =SUM(O53) -> 0 | P22: =SUM(P53) -> 0 | Q22: =SUM(Q53) -> 81903.4 | R22: =SUM(R53) -> 30562 | ... V22: =SUM(V53) -> 0 | X22: No/NA | Y22: NA/No - 0%
C23: Haul/Dump Truck | D23: Total Haul/Dump Truck (Ore) loaded in SAR Pit | F23: Sarsfield Combined Ore Assay | G23: - | H23: =SUM(H68, H87, H106) -> 89195.1 | I23: Tonne | K23: =SUM(K68, K87, K106) -> 0 | L23: =SUM(L68, L87, L106) -> 0 | M23: =SUM(M68, M87, M106) -> 0 | N23: =SUM(N68, N87, N106) -> 0 | O23: =SUM(O68, O87, O106) -> 0 | P23: =SUM(P68, P87, P106) -> 0 | Q23: =SUM(Q68, Q87, Q106) -> 178 | R23: =SUM(R68, R87, R106) -> 27330.5 | ... V23: =SUM(V68, V87, V106) -> 195.2 | X23: No/NA | Y23: NA/No - 0%
C24: Haul/Dump Truck | D24: Total Haul/Dump Truck (Ore) loaded in SAR Pit | F24: Sarsfield LG Ore | G24: 179887 | H24: =SUM(H109) -> 266479.2 | I24: Tonne | K24: =SUM(K109) -> 0 | L24: =SUM(L109) -> 0 | M24: =SUM(M109) -> 0 | N24: =SUM(N109) -> 0 | O24: =SUM(O109) -> 0 | P24: =SUM(P109) -> 0 | Q24: =SUM(Q109) -> 46227.7 | R24: =SUM(R109) -> 551.2 | ... V24: =SUM(V109) -> 76557.3 | X24: No/NA | Y24: NA/No - 0%
C25: Loader | D25: Total Loader (Waste) loaded in BRW Pit | F25: Average Waste Assay | G25: 1640150.4 | H25: =SUM(H45, H54, H74, H88, H120, H129, H131, H138, H140, H152, H154) -> 1890366.9 | I25: Tonne | K25: =SUM(K45, K54, K74, K88, K120, K129, K131, K138, K140, K152, K154) -> 145263.5 | L25: =SUM(L45, L54, L74, L88, L120, L129, L131, L138, L140, L152, L154) -> 59574.5 | M25: =SUM(M45, M54, M74, M88, M120, M129, M131, M138, M140, M152, M154) -> 73073.5 | N25: =SUM(N45, N54, N74, N88, N120, N129, N131, N138, N140, N152, N154) -> 168548.6 | O25: =SUM(O45, O54, O74, O88, O120, O129, O131, O138, O140, O152, O154) -> 111272.4 | P25: =SUM(P45, P54, P74, P88, P120, P129, P131, P138, P140, P152, P154) -> 265532.5 | Q25: =SUM(Q45, Q54, Q74, Q88, Q120, Q129, Q131, Q138, Q140, Q152, Q154) -> 103272.8 | R25: =SUM(R45, R54, R74, R88, R120, R129, R131, R138, R140, R152, R154) -> 144666.3 | ... V25: =SUM(V45, V54, V74, V88, V120, V129, V131, V138, V140, V152, V154) -> 305717.8 | X25: No/NA | Y25: NA/No - 0%
C26: Loader | D26: Total Loader (Waste) loaded in SAR Pit | F26: Average Tailings Assay | G26: - | H26: =SUM(H71, H113, H142) -> 21855 | I26: Tonne | K26: =SUM(K71, K113, K142) -> 1919 | L26: =SUM(L71, L113, L142) -> 0 | M26: =SUM(M71, M113, M142) -> 0 | N26: =SUM(N71, N113, N142) -> 0 | O26: =SUM(O71, O113, O142) -> 1564 | P26: =SUM(P71, P113, P142) -> 1169 | Q26: =SUM(Q71, Q113, Q142) -> 1138 | R26: =SUM(R71, R113, R142) -> 1795 | ... V26: =SUM(V71, V113, V142) -> 2665 | X26: No/NA | Y26: NA/No - 0%
C27: Loader | D27: Total Loader (Waste) loaded in SAR Pit | F27: SAR Waste | G27: - | H27: =SUM(H125) -> 168910 | I27: Tonne | K27: =SUM(K125) -> 23547.6 | L27: =SUM(L125) -> 1263.5 | M27: =SUM(M125) -> 1593.1 | N27: =SUM(N125) -> 27843.7 | O27: =SUM(O125) -> 19318.2 | P27: =SUM(P125) -> 206.5 | Q27: =SUM(Q125) -> 16982.9 | R27: =SUM(R125) -> 34305.2 | ... V27: =SUM(V125) -> 2261 | X27: No/NA | Y27: Yes - 100%
C28: Excavator | D28: Total Excavator (Waste) loaded in BRW Pit | F28: Average Waste Assay | G28: 17651720 | H28: =SUM(H119, H137, H151) -> 9440063 | I28: Tonne | K28: =SUM(K119, K137, K151) -> 1229724.3 | L28: =SUM(L119, L137, L151) -> 1066103.4 | M28: =SUM(M119, M137, M151) -> 1029382.8 | N28: =SUM(N119, N137, N151) -> 797821.6 | O28: =SUM(O119, O137, O151) -> 696893.3 | P28: =SUM(P119, P137, P151) -> 950481.6 | Q28: =SUM(Q119, Q137, Q151) -> 501888.7 | R28: =SUM(R119, R137, R151) -> 521664.5 | ... V28: =SUM(V119, V137, V151) -> 1194982.5 | X28: No/NA | Y28: NA/No - 0%
C29: Excavator | D29: Total Excavator (Waste) | F29: Average Tailings Assay | G29: - | H29: =SUM(H72) -> 3706 | I29: Tonne | K29: =SUM(K72) -> 0 | L29: =SUM(L72) -> 2144 | M29: =SUM(M72) -> 381 | N29: =SUM(N72) -> 0 | O29: =SUM(O72) -> 0 | P29: =SUM(P72) -> 0 | Q29: =SUM(Q72) -> 0 | R29: =SUM(R72) -> 0 | ... V29: =SUM(V72) -> 145 | X29: No/NA | Y29: NA/No - 0%
C30: Excavator | D30: Total Excavator (Waste) loaded in SAR Pit | F30: SAR Waste | G30: - | H30: =SUM(H124) -> 9003987.1 | I30: Tonne | K30: =SUM(K124) -> 187739.4 | L30: =SUM(L124) -> 215367.7 | M30: =SUM(M124) -> 237678.4 | N30: =SUM(N124) -> 1171221.5 | O30: =SUM(O124) -> 1117760.8 | P30: =SUM(P124) -> 952994 | Q30: =SUM(Q124) -> 1064336.4 | R30: =SUM(R124) -> 929152.4 | ... V30: =SUM(V124) -> 650590.5 | X30: No/NA | Y30: Yes - 100%
C31: Haul/Dump Truck | D31: Total Haul Truck (Waste) | F31: Average Waste Assay | G31: 19316384 | H31: =SUM(H46, H55, H75, H89, H121, H130, H132, H139, H141, H153, H155) -> 11352309 | I31: Tonne | K31: =SUM(K46, K55, K75, K89, K121, K130, K132, K139, K141, K153, K155) -> 1374987.8 | L31: =SUM(L46, L55, L75, L89, L121, L130, L132, L139, L141, L153, L155) -> 1125677.9 | M31: =SUM(M46, M55, M75, M89, M121, M130, M132, M139, M141, M153, M155) -> 1102456.3 | N31: =SUM(N46, N55, N75, N89, N121, N130, N132, N139, N141, N153, N155) -> 986313.2 | O31: =SUM(O46, O55, O75, O89, O121, O130, O132, O139, O141, O153, O155) -> 808165.7 | P31: =SUM(P46, P55, P75, P89, P121, P130, P132, P139, P141, P153, P155) -> 1216014.1 | Q31: =SUM(Q46, Q55, Q75, Q89, Q121, Q130, Q132, Q139, Q141, Q153, Q155) -> 605161.5 | R31: =SUM(R46, R55, R75, R89, R121, R130, R132, R139, R141, R153, R155) -> 666330.8 | ... V31: =SUM(V46, V55, V75, V89, V121, V130, V132, V139, V141, V153, V155) -> 1502636.3 | X31: No/NA | Y31: NA/No - 0%
C32: Haul/Dump Truck | D32: Total Haul Truck (Waste) | F32: Average Tailings Assay | G32: - | H32: =SUM(H73, H114, H143) -> 27326 | I32: Tonne | K32: =SUM(K73, K114, K143) -> 1919 | L32: =SUM(L73, L114, L143) -> 2336 | M32: =SUM(M73, M114, M143) -> 1954 | N32: =SUM(N73, N114, N143) -> 0 | O32: =SUM(O73, O114, O143) -> 1564 | P32: =SUM(P73, P114, P143) -> 1169 | Q32: =SUM(Q73, Q114, Q143) -> 1138 | R32: =SUM(R73, R114, R143) -> 1795 | ... V32: =SUM(V73, V114, V143) -> 2810 | X32: No/NA | Y32: NA/No - 0%
C33: Haul/Dump Truck | D33: Total Haul Truck (Waste) | F33: SAR Waste | G33: - | H33: =SUM(H126) -> 9172897.1 | I33: Tonne | K33: =SUM(K126) -> 211287 | L33: =SUM(L126) -> 216631.2 | M33: =SUM(M126) -> 239271.5 | N33: =SUM(N126) -> 1199065.2 | O33: =SUM(O126) -> 1137079 | P33: =SUM(P126) -> 953200.5 | Q33: =SUM(Q126) -> 1081319.3 | R33: =SUM(R126) -> 963457.6 | ... V33: =SUM(V126) -> 652851.5 | X33: No/NA | Y33: Yes - 100%
C34: Loader | D34: Total Loader (Topsoil) | F34: Average Scats Assay | G34: 429671.3 | H34: =SUM(H133) -> 322549 | I34: Tonne | K34: =SUM(K133) -> 28777 | L34: =SUM(L133) -> 35132 | M34: =SUM(M133) -> 33831 | N34: =SUM(N133) -> 17887 | O34: =SUM(O133) -> 27776 | P34: =SUM(P133) -> 24585 | Q34: =SUM(Q133) -> 20090 | R34: =SUM(R133) -> 20722 | ... V34: =SUM(V133) -> 15503 | X34: No/NA | Y34: NA/No - 0%
C35: Haul/Dump Truck | D35: Total Haul Truck (Topsoil) | F35: Average Scats Assay | G35: 429671.3 | H35: =SUM(H134) -> 325440 | I35: Tonne | K35: =SUM(K134) -> 29861 | L35: =SUM(L134) -> 36055 | M35: =SUM(M134) -> 33831 | N35: =SUM(N134) -> 17887 | O35: =SUM(O134) -> 27776 | P35: =SUM(P134) -> 24585 | Q35: =SUM(Q134) -> 20090 | R35: =SUM(R134) -> 20722 | ... V35: =SUM(V134) -> 15503 | X35: No/NA | Y35: NA/No - 0%
C36: Loader | D36: Total Loader (Topsoil) | F36: Topsoil Assay | G36: 181496.59 | H36: =SUM(H158, H160) -> 4642.7 | I36: Tonne | K36: =SUM(K158, K160) -> 0 | L36: =SUM(L158, L160) -> 0 | M36: =SUM(M158, M160) -> 2910 | N36: =SUM(N158, N160) -> 0 | O36: =SUM(O158, O160) -> 0 | P36: =SUM(P158, P160) -> 0 | Q36: =SUM(Q158, Q160) -> 0 | R36: =SUM(R158, R160) -> 0 | ... V36: =SUM(V158, V160) -> 1732.7 | X36: No/NA | Y36: NA/No - 0%
C37: Haul/Dump Truck | D37: Total Haul Truck (Topsoil) | F37: Topsoil Assay | G37: 181496.59 | H37: =SUM(H159, H161) -> 4642.7 | I37: Tonne | K37: =SUM(K159, K161) -> 0 | L37: =SUM(L159, L161) -> 0 | M37: =SUM(M159, M161) -> 2910 | N37: =SUM(N159, N161) -> 0 | O37: =SUM(O159, O161) -> 0 | P37: =SUM(P159, P161) -> 0 | Q37: =SUM(Q159, Q161) -> 0 | R37: =SUM(R159, R161) -> 0 | ... V37: =SUM(V159, V161) -> 1732.7 | X37: No/NA | Y37: NA/No - 0%
C39: BRW Crusher - Haul trucks direct dump into crusher
C40: Excavator (Ore) | D40: Load truck with ore from BRW pit | E40: Hexagon Data, in AJ's spreadsheet "FY-Enviro-Dept-Jul23-Jun24.xlsx" | F40: BRW Ore Assay | H40: =SUM(K40:V40) -> 432563.5 | I40: Tonne | K40: 4330 | L40: 17663.3 | M40: 35510.2 | N40: 44640 | O40: 50587.4 | P40: 8138.1 | Q40: 1850.4 | R40: 8202.4 | S40: 14100.2 | T40: 109020.7 | U40: 91966.1 | V40: 46554.7 | X40: No/NA | Y40: Yes - 100%
C41: Loader (Ore) | D41: Load truck with ore from BRW pit | E41: Hexagon Data, in AJ's spreadsheet "FY-Enviro-Dept-Jul23-Jun24.xlsx" | F41: BRW Ore Assay | H41: =SUM(K41:V41) -> 165.2 | I41: Tonne | K41: 0 | L41: 0 | M41: 165.2 | N41: 0 | O41: 0 | P41: 0 | Q41: 0 | R41: 0 | S41: 0 | T41: 0 | U41: 0 | V41: 0 | X41: No/NA | Y41: Yes - 100%
C42: Haul/Dump Truck (Ore) | D42: Haul BRW pit ore to BRW crusher and direct dump into crusher | E42: Hexagon Data, in AJ's spreadsheet "FY-Enviro-Dept-Jul23-Jun24.xlsx" | F42: BRW Ore Assay | H42: =SUM(K42:V42) -> 432728.7 | I42: Tonne | K42: 4330 | L42: 17663.3 | M42: 35675.4 | N42: 44640 | O42: 50587.4 | P42: 8138.1 | Q42: 1850.4 | R42: 8202.4 | S42: 14100.2 | T42: 109020.7 | U42: 91966.1 | V42: 46554.7 | X42: No/NA | Y42: NA/No - 0%
C43: Excavator (Ore) | D43: Load truck with fines - SIMMCO | E43: Simmco Daily Sheet | F43: Average Ore Assay | H43: =SUM(K43:V43) -> 760 | I43: Tonne | K43: 0 | L43: 0 | M43: 760 | N43: 0 | O43: 0 | P43: 0 | Q43: 0 | R43: 0 | S43: 0 | T43: 0 | U43: 0 | V43: 0 | X43: No/NA | Y43: NA/No - 0%
C44: Haul/Dump Truck (Ore) | D44: Haul fines to BRW crusher and dircet dump into crusher - SIMMCO | E44: Simmco Daily Sheet | F44: Average Ore Assay | H44: =SUM(K44:V44) -> 760 | I44: Tonne | K44: 0 | L44: 0 | M44: 760 | N44: 0 | O44: 0 | P44: 0 | Q44: 0 | R44: 0 | S44: 0 | T44: 0 | U44: 0 | V44: 0 | X44: No/NA | Y44: NA/No - 0%
C45: Loader (Ore) | D45: Load truck with rejects - SIMMCO | E45: Simmco Daily Sheet | F45: Average Waste Assay | H45: =SUM(K45:V45) -> 11729 | I45: Tonne | K45: 0 | L45: 0 | M45: 11729 | N45: 0 | O45: 0 | P45: 0 | Q45: 0 | R45: 0 | S45: 0 | T45: 0 | U45: 0 | V45: 0 | X45: No/NA | Y45: NA/No - 0%
C46: Haul/Dump Truck (Ore) | D46: Haul rejects to BRW crusher and dircet dump into crusher - SIMMCO | E46: Simmco Daily Sheet | F46: Average Waste Assay | H46: =SUM(K46:V46) -> 11729 | I46: Tonne | K46: 0 | L46: 0 | M46: 11729 | N46: 0 | O46: 0 | P46: 0 | Q46: 0 | R46: 0 | S46: 0 | T46: 0 | U46: 0 | V46: 0 | X46: No/NA | Y46: NA/No - 0%
C48: BRW Crusher - Loader picks up ore from ROM stockpiles and loads crusher
C49: Loader (Ore) | D49: Load truck with ore from BRW pit | E49: Hexagon Data, in AJ's spreadsheet "FY-Enviro-Dept-Jul23-Jun24.xlsx" | F49: BRW Ore Assay | H49: =SUM(K49:V49) -> 19728.1 | I49: Tonne | K49: 6586.9 | L49: 5399.3 | M49: 165.6 | P49: 1666.8 | Q49: 2687.2 | R49: 1637.8 | S49: 1517.2 | T49: 0 | U49: 0 | V49: 67.3 | X49: No/NA | Y49: Yes - 100%
C50: Excavator (Ore) | D50: Load truck with ore from BRW pit | E50: Hexagon Data, in AJ's spreadsheet "FY-Enviro-Dept-Jul23-Jun24.xlsx" | F50: BRW Ore Assay | H50: =SUM(K50:V50) -> 4733033.1 | I50: Tonne | K50: 348227.3 | L50: 588590.4 | M50: 238428.1 | N50: 239352.6 | O50: 399937.3 | P50: 262965.7 | Q50: 405724.8 | R50: 435694.8 | S50: 335226.3 | T50: 727841.3 | U50: 446239.9 | V50: 304804.6 | X50: No/NA | Y50: Yes - 100%
C51: Haul/Dump Truck (Ore) | D51: Haul BRW pit ore to BRW ROM and dump | E51: Hexagon Data, in AJ's spreadsheet "FY-Enviro-Dept-Jul23-Jun24.xlsx" | F51: BRW Ore Assay | H51: =SUM(K51:V51) -> 4752761.2 | I51: Tonne | K51: 354814.2 | L51: 593989.7 | M51: 238593.7 | N51: 239352.6 | O51: 399937.3 | P51: 264632.5 | Q51: 408412 | R51: 437332.6 | S51: 336743.5 | T51: 727841.3 | U51: 446239.9 | V51: 304871.9 | X51: No/NA | Y51: NA/No - 0%
C52: Excavator (Ore) | D52: Load truck with ore from SAR pit | E52: Hexagon Data, in AJ's spreadsheet "FY-Enviro-Dept-Jul23-Jun24.xlsx" | F52: Sarsfield HG Ore Assay | H52: =SUM(K52:V52) -> 112645 | I52: Tonne | K52: 0 | L52: 0 | M52: 0 | N52: 0 | O52: 0 | P52: 0 | Q52: 81903.4 | R52: 30562 | S52: 0 | T52: 179.6 | U52: 0 | V52: 0 | X52: No/NA | Y52: Yes - 100%
C53: Haul/Dump Truck (Ore) | D53: Haul SAR pit ore to BRW ROM and dump | E53: Hexagon Data, in AJ's spreadsheet "FY-Enviro-Dept-Jul23-Jun24.xlsx" | F53: Sarsfield HG Ore Assay | H53: =SUM(K53:V53) -> 112645 | I53: Tonne | K53: 0 | L53: 0 | M53: 0 | N53: 0 | O53: 0 | P53: 0 | Q53: 81903.4 | R53: 30562 | S53: 0 | T53: 179.6 | U53: 0 | V53: 0 | X53: No/NA | Y53: NA/No - 0%
C54: Loader (Waste) | D54: Load truck with rejects | E54: Hexagon Data, in AJ's spreadsheet "FY-Enviro-Dept-Jul23-Jun24.xlsx" | F54: Average Waste Assay | H54: =SUM(K54:V54) -> 708.9 | I54: Tonne | K54: 0 | L54: 0 | M54: 0 | N54: 0 | O54: 0 | P54: 513.5 | Q54: 0 | R54: 0 | S54: 0 | T54: 0 | U54: 0 | V54: 195.4 | X54: No/NA | Y54: NA/No - 0%
C55: Haul/Dump Truck (Waste) | D55: Haul rejects to BRW ROM and dump | E55: Hexagon Data, in AJ's spreadsheet "FY-Enviro-Dept-Jul23-Jun24.xlsx" | F55: Average Waste Assay | H55: =SUM(K55:V55) -> 708.9 | I55: Tonne | K55: 0 | L55: 0 | M55: 0 | N55: 0 | O55: 0 | P55: 513.5 | Q55: 0 | R55: 0 | S55: 0 | T55: 0 | U55: 0 | V55: 195.4 | X55: No/NA | Y55: NA/No - 0%
C56: Loader (Ore) | D56: Loader picks up ore from BRW ROM and loads BRW crusher - SIMMCO | E56: Simmco Daily Sheet | F56: Average Ore Assay | H56: =SUM(K56:V56) -> 5129898 | I56: Tonne | K56: 501834 | L56: 296811 | M56: 308826 | N56: 419922 | O56: 330840 | P56: 624677 | Q56: 485277 | R56: 299027 | S56: 355648 | T56: 480680 | U56: 480546 | V56: 545810 | X56: No/NA | Y56: NA/No - 0%
C58: BRW ROM - Load trucks with ore from BRW ROM, direct dump into BRW Crusher
C59: Loader (Ore) | D59: Load truck with ore from BRW ROM | E59: Hexagon Data, in AJ's spreadsheet "FY-Enviro-Dept-Jul23-Jun24.xlsx" | F59: Average Ore Assay | H59: =SUM(K59:V59) -> 432563.5 | I59: Tonne | K59: 4330 | L59: 17663.3 | M59: 35510.2 | N59: 44640 | O59: 50587.4 | P59: 8138.1 | Q59: 1850.4 | R59: 8202.4 | S59: 14100.2 | T59: 109020.7 | U59: 91966.1 | V59: 46554.7 | X59: No/NA | Y59: NA/No - 0%
C60: Excavator (Ore) | D60: Load truck with ore from BRW ROM | E60: Hexagon Data, in AJ's spreadsheet "FY-Enviro-Dept-Jul23-Jun24.xlsx" | F60: Average Ore Assay | H60: =SUM(K60:V60) -> 165.2 | I60: Tonne | K60: 0 | L60: 0 | M60: 165.2 | N60: 0 | O60: 0 | P60: 0 | Q60: 0 | R60: 0 | S60: 0 | T60: 0 | U60: 0 | V60: 0 | X60: No/NA | Y60: NA/No - 0%
C61: Haul/Dump Truck (Ore) | D61: Haul ore to BRW crusher and direct dump into crusher | E61: Hexagon Data, in AJ's spreadsheet "FY-Enviro-Dept-Jul23-Jun24.xlsx" | F61: Average Ore Assay | H61: =SUM(K61:V61) -> 432728.7 | I61: Tonne | K61: 4330 | L61: 17663.3 | M61: 35675.4 | N61: 44640 | O61: 50587.4 | P61: 8138.1 | Q61: 1850.4 | R61: 8202.4 | S61: 14100.2 | T61: 109020.7 | U61: 91966.1 | V61: 46554.7 | X61: No/NA | Y61: NA/No - 0%
C63: NOL Crusher - Loader picks up ore from ROM stockpiles and loads crusher
C64: Loader (Ore) | D64: Load truck with ore from BRW pit | E64: Hexagon Data, in AJ's spreadsheet "FY-Enviro-Dept-Jul23-Jun24.xlsx" | F64: BRW Ore Assay | H64: =SUM(K64:V64) -> 2847.6 | I64: Tonne | K64: 473.7 | L64: 0 | M64: 311.4 | N64: 0 | O64: 0 | P64: 0 | Q64: 101.2 | R64: 0 | S64: 1961.3 | T64: 0 | U64: 0 | V64: 0 | X64: No/NA | Y64: Yes - 100%
C65: Excavator (Ore) | D65: Load truck with ore from BRW pit | E65: Hexagon Data, in AJ's spreadsheet "FY-Enviro-Dept-Jul23-Jun24.xlsx" | F65: BRW Ore Assay | H65: =SUM(K65:V65) -> 1320371.8 | I65: Tonne | K65: 147889.3 | L65: 138503.1 | M65: 461676.4 | N65: 64293.9 | O65: 24269.5 | P65: 39444.6 | Q65: 14844.4 | R65: 56709.8 | S65: 189067.7 | T65: 38711.2 | U65: 91071 | V65: 53890.9 | X65: No/NA | Y65: Yes - 100%
C66: Haul/Dump Truck (Ore) | D66: Haul BRW pit ore to NOL ROM and dump | E66: Hexagon Data, in AJ's spreadsheet "FY-Enviro-Dept-Jul23-Jun24.xlsx" | F66: BRW Ore Assay | H66: =SUM(K66:V66) -> 1323219.4 | I66: Tonne | K66: 148363 | L66: 138503.1 | M66: 461987.8 | N66: 64293.9 | O66: 24269.5 | P66: 39444.6 | Q66: 14945.6 | R66: 56709.8 | S66: 191029 | T66: 38711.2 | U66: 91071 | V66: 53890.9 | X66: No/NA | Y66: NA/No - 0%
C67: Excavator (Ore) | D67: Load truck with ore from SAR pit | E67: Hexagon Data, in AJ's spreadsheet "FY-Enviro-Dept-Jul23-Jun24.xlsx" | F67: Sarsfield Combined Ore Assay | H67: =SUM(K67:V67) -> 340.2 | I67: Tonne | K67: 0 | L67: 0 | M67: 0 | N67: 0 | O67: 0 | P67: 0 | Q67: 178 | R67: 0 | S67: 162.2 | T67: 0 | U67: 0 | V67: 0 | X67: No/NA | Y67: Yes - 100%
C68: Haul/Dump Truck (Ore) | D68: Haul SAR pit ore to NOL ROM and dump | E68: Hexagon Data, in AJ's spreadsheet "FY-Enviro-Dept-Jul23-Jun24.xlsx" | F68: Sarsfield Combined Ore Assay | H68: =SUM(K68:V68) -> 340.2 | I68: Tonne | K68: 0 | L68: 0 | M68: 0 | N68: 0 | O68: 0 | P68: 0 | Q68: 178 | R68: 0 | S68: 162.2 | T68: 0 | U68: 0 | V68: 0 | X68: No/NA | Y68: NA/No - 0%
C69: Loader (Ore) | D69: Load trucks with various ore | E69: Simmco Daily Sheet | F69: Average Ore Assay | H69: =SUM(K69:V69) -> 35421 | I69: Tonne | K69: 0 | L69: 3492 | M69: 6694 | N69: 5734 | O69: 829 | P69: 0 | Q69: 5721 | R69: 9017 | S69: 0 | T69: 3934 | U69: 0 | V69: 0 | X69: No/NA | Y69: NA/No - 0%
C70: Haul/Dump Truck (Ore) | D70: Haul various ore to NOL ROM | E70: Simmco Daily Sheet | F70: Average Ore Assay | H70: =SUM(K70:V70) -> 35421 | I70: Tonne | K70: 0 | L70: 3492 | M70: 6694 | N70: 5734 | O70: 829 | P70: 0 | Q70: 5721 | R70: 9017 | S70: 0 | T70: 3934 | U70: 0 | V70: 0 | X70: No/NA | Y70: NA/No - 0%
C71: Loader (Ore) | D71: Load trucks with mill spillage - SIMMCO | E71: Simmco Daily Sheet | F71: Average Tailings Assay | H71: =SUM(K71:V71) -> 14206 | I71: Tonne | K71: 1919 | L71: 0 | M71: 0 | N71: 0 | O71: 388 | P71: 1169 | Q71: 1138 | R71: 1795 | S71: 2547 | T71: 1368 | U71: 1341 | V71: 2541 | X71: No/NA | Y71: NA/No - 0%
C72: Excavator (Ore) | D72: Load trucks with mill spillage - SIMMCO | E72: Simmco Daily Sheet | F72: Average Tailings Assay | H72: =SUM(K72:V72) -> 3706 | I72: Tonne | K72: 0 | L72: 2144 | M72: 381 | N72: 0 | O72: 0 | P72: 0 | Q72: 0 | R72: 0 | S72: 0 | T72: 1036 | U72: 0 | V72: 145 | X72: No/NA | Y72: NA/No - 0%
C73: Haul/Dump Truck (Ore) | D73: Haul mill spillage to NOL ROM - SIMMCO | E73: Simmco Daily Sheet | F73: Average Tailings Assay | H73: =SUM(K73:V73) -> 19677 | I73: Tonne | K73: 1919 | L73: 2336 | M73: 1954 | N73: 0 | O73: 388 | P73: 1169 | Q73: 1138 | R73: 1795 | S73: 2547 | T73: 2404 | U73: 1341 | V73: 2686 | X73: No/NA | Y73: NA/No - 0%
C74: Loader (Ore) | D74: Load trucks with HG rejects - SIMMCO | E74: Simmco Daily Sheet | F74: Average Waste Assay | H74: =SUM(K74:V74) -> 24964 | I74: Tonne | K74: 0 | L74: 0 | M74: 0 | N74: 4790 | O74: 11355 | P74: 3931 | Q74: 0 | R74: 0 | S74: 0 | T74: 0 | U74: 0 | V74: 4888 | X74: No/NA | Y74: NA/No - 0%
C75: Haul/Dump Truck (Ore) | D75: Haul HG rejects to NOL ROM - SIMMCO | E75: Simmco Daily Sheet | F75: Average Waste Assay | H75: =SUM(K75:V75) -> 36259 | I75: Tonne | K75: 0 | L75: 0 | M75: 0 | N75: 16085 | O75: 11355 | P75: 3931 | Q75: 0 | R75: 0 | S75: 0 | T75: 0 | U75: 0 | V75: 4888 | X75: No/NA | Y75: NA/No - 0%
C76: Loader (Ore) | D76: Loader picks up ore from NOL ROM and loads NOL crusher - SIMMCO | E76: Simmco Daily Sheet | F76: Average Ore Assay | H76: =SUM(K76:V76) -> 1908306 | I76: Tonne | K76: 141918 | L76: 139313 | M76: 162163 | N76: 182056 | O76: 159368 | P76: 156272 | Q76: 156279 | R76: 202034 | S76: 180446 | T76: 133327 | U76: 166824 | V76: 128306 | X76: No/NA | Y76: NA/No - 0%
C78: S9 Crusher - Loader picks up ore from ROM stockpiles and loads crusher
C79: Excavator (Ore) | D79: Load truck with ore from BRW pit | E79: Hexagon Data, in AJ's spreadsheet "FY-Enviro-Dept-Jul23-Jun24.xlsx" | F79: BRW Ore Assay | H79: =SUM(K79:V79) -> 2059854.9 | I79: Tonne | K79: 159223.4 | L79: 57731.6 | M79: 444840.5 | N79: 392273 | O79: 423057 | P79: 300642.9 | Q79: 0 | R79: 4793.5 | S79: 78546.8 | T79: 21469.2 | U79: 117150.3 | V79: 60126.7 | X79: No/NA | Y79: Yes - 100%
C80: Loader (Ore) | D80: Load truck with ore from BRW pit | E80: Hexagon Data, in AJ's spreadsheet "FY-Enviro-Dept-Jul23-Jun24.xlsx" | F80: BRW Ore Assay | H80: =SUM(K80:V80) -> 15070.8 | I80: Tonne | K80: 3832.4 | L80: 0 | M80: 4977.1 | N80: 0 | O80: 5736.6 | P80: 524.7 | Q80: 0 | R80: 0 | S80: 0 | T80: 0 | U80: 0 | V80: 0 | X80: No/NA | Y80: Yes - 100%
C81: Haul/Dump Truck (Ore) | D81: Haul BRW pit ore to S9 ROM and dump | E81: Hexagon Data, in AJ's spreadsheet "FY-Enviro-Dept-Jul23-Jun24.xlsx" | F81: BRW Ore Assay | H81: =SUM(K81:V81) -> 2074925.7 | I81: Tonne | K81: 163055.8 | L81: 57731.6 | M81: 449817.6 | N81: 392273 | O81: 428793.6 | P81: 301167.6 | Q81: 0 | R81: 4793.5 | S81: 78546.8 | T81: 21469.2 | U81: 117150.3 | V81: 60126.7 | X81: No/NA | Y81: NA/No - 0%
C82: Excavator (Ore) | D82: Load truck with LG from various dumps | E82: Hexagon Data, in AJ's spreadsheet "FY-Enviro-Dept-Jul23-Jun24.xlsx" | F82: Average Ore Assay | H82: =SUM(K82:V82) -> 162860.9 | I82: Tonne | K82: 0 | L82: 497 | M82: 567.3 | N82: 52195.5 | O82: 27594.3 | P82: 82006.8 | Q82: 0 | R82: 0 | S82: 0 | T82: 0 | U82: 0 | V82: 0 | X82: No/NA | Y82: NA/No - 0%
C83: Loader (Ore) | D83: Load truck with LG from various dumps | E83: Hexagon Data, in AJ's spreadsheet "FY-Enviro-Dept-Jul23-Jun24.xlsx" | F83: Average Ore Assay | H83: =SUM(K83:V83) -> 14662.6 | I83: Tonne | K83: 0 | L83: 0 | M83: 0 | N83: 12731.5 | O83: 1564.7 | P83: 0 | Q83: 0 | R83: 0 | S83: 0 | T83: 366.4 | U83: 0 | V83: 0 | X83: No/NA | Y83: NA/No - 0%
C84: Haul/Dump Truck (Ore) | D84: Haul LG to S9 ROM and dump | E84: Hexagon Data, in AJ's spreadsheet "FY-Enviro-Dept-Jul23-Jun24.xlsx" | F84: Average Ore Assay | H84: =SUM(K84:V84) -> 177523.5 | I84: Tonne | K84: 0 | L84: 497 | M84: 567.3 | N84: 64927 | O84: 29159 | P84: 82006.8 | Q84: 0 | R84: 0 | S84: 0 | T84: 366.4 | U84: 0 | V84: 0 | X84: No/NA | Y84: NA/No - 0%
C85: Excavator (Ore) | D85: Load truck with ore from SAR pit | E85: Hexagon Data, in AJ's spreadsheet "FY-Enviro-Dept-Jul23-Jun24.xlsx" | F85: Sarsfield Combined Ore Assay | H85: =SUM(K85:V85) -> 82856.8 | I85: Tonne | K85: 0 | L85: 0 | M85: 0 | N85: 0 | O85: 0 | P85: 0 | Q85: 0 | R85: 26977 | S85: 31142 | T85: 24542.6 | U85: 0 | V85: 195.2 | X85: No/NA | Y85: Yes - 100%
C86: Loader (Ore) | D86: Load truck with ore from SAR pit | E86: Hexagon Data, in AJ's spreadsheet "FY-Enviro-Dept-Jul23-Jun24.xlsx" | F86: Sarsfield Combined Ore Assay | H86: =SUM(K86:V86) -> 5644.6 | I86: Tonne | K86: 0 | L86: 0 | M86: 0 | N86: 0 | O86: 0 | P86: 0 | Q86: 0 | R86: 0 | S86: 0 | T86: 5644.6 | U86: 0 | V86: 0 | X86: No/NA | Y86: Yes - 100%
C87: Haul/Dump Truck (Ore) | D87: Haul SAR pit ore to S9 ROM and dump | E87: Hexagon Data, in AJ's spreadsheet "FY-Enviro-Dept-Jul23-Jun24.xlsx" | F87: Sarsfield Combined Ore Assay | H87: =SUM(K87:V87) -> 88501.4 | I87: Tonne | K87: 0 | L87: 0 | M87: 0 | N87: 0 | O87: 0 | P87: 0 | Q87: 0 | R87: 26977 | S87: 31142 | T87: 30187.2 | U87: 0 | V87: 195.2 | X87: No/NA | Y87: NA/No - 0%
C88: Loader (Ore) | D88: Load truck with HG rejects - SIMMCO | E88: Simmco Daily Sheet | F88: Average Waste Assay | H88: =SUM(K88:V88) -> 32762 | I88: Tonne | K88: 0 | L88: 0 | M88: 4049 | N88: 0 | O88: 0 | P88: 0 | Q88: 0 | R88: 0 | S88: 0 | T88: 3775 | U88: 24938 | V88: 0 | X88: No/NA | Y88: NA/No - 0%
C89: Haul/Dump Truck (Ore) | D89: Haul HG rejects to S9 ROM and dump - SIMMCO | E89: Simmco Daily Sheet | F89: Average Waste Assay | H89: =SUM(K89:V89) -> 32762 | I89: Tonne | K89: 0 | L89: 0 | M89: 4049 | N89: 0 | O89: 0 | P89: 0 | Q89: 0 | R89: 0 | S89: 0 | T89: 3775 | U89: 24938 | V89: 0 | X89: No/NA | Y89: NA/No - 0%
C90: Loader (Ore) | D90: Loader picks up ore from S9 ROM and loads S9 crusher - SIMMCO | E90: Simmco Daily Sheet | F90: Average Ore Assay | H90: =SUM(K90:V90) -> 143508 | I90: Tonne | K90: 0 | L90: 0 | M90: 42358 | N90: 0 | O90: 0 | P90: 5951 | Q90: 0 | R90: 33106 | S90: 34561 | T90: 1822 | U90: 8234 | V90: 17476 | X90: No/NA | Y90: NA/No - 0%
C92: Feeder 5
C93: Excavator (Ore) | D93: Sidecast fines (FD5) - SIMMCO | E93: Simmco Daily Sheet | F93: Average Ore Assay | H93: =SUM(K93:V93) -> 52731 | I93: Tonne | K93: 18822 | L93: 33909 | M93: 0 | N93: 0 | O93: 0 | P93: 0 | Q93: 0 | R93: 0 | S93: 0 | T93: 0 | U93: 0 | V93: 0 | X93: No/NA | Y93: NA/No - 0%
C94: Loader (Ore) | D94: Load truck with fines for FD5 - SIMMCO | E94: Simmco Daily Sheet | F94: Average Ore Assay | H94: =SUM(K94:V94) -> 169670 | I94: Tonne | K94: 0 | L94: 33909 | M94: 14423 | N94: 5396 | O94: 6568 | P94: 1276 | Q94: 0 | R94: 12752 | S94: 30276 | T94: 14861 | U94: 29069 | V94: 21140 | X94: No/NA | Y94: NA/No - 0%
C95: Haul/Dump Truck (Ore) | D95: Haul fines to FD5 - SIMMCO | E95: Simmco Daily Sheet | F95: Average Ore Assay | H95: =SUM(K95:V95) -> 171567 | I95: Tonne | K95: 0 | L95: 33909 | M95: 14423 | N95: 7975 | O95: 6568 | P95: 1276 | Q95: 0 | R95: 12752 | S95: 30276 | T95: 14861 | U95: 29069 | V95: 20458 | X95: No/NA | Y95: NA/No - 0%
C96: Loader (Ore) | D96: Load fines to FD5 - SIMMCO | E96: Simmco Daily Sheet | F96: Average Ore Assay | H96: =SUM(K96:V96) -> 195594 | I96: Tonne | K96: 0 | L96: 65472 | M96: 17809 | N96: 710 | O96: 14166 | P96: 0 | Q96: 0 | R96: 7294 | S96: 34717 | T96: 19274 | U96: 11044 | V96: 25108 | X96: No/NA | Y96: NA/No - 0%
C98: Other Ore movements
C99: Excavator (Ore) | D99: Load truck with ore from BRW pit | E99: Hexagon Data, in AJ's spreadsheet "FY-Enviro-Dept-Jul23-Jun24.xlsx" | F99: BRW Ore Assay | H99: =SUM(K99:V99) -> 1249853.5 | I99: Tonne | K99: 9509.3 | L99: 23699.9 | M99: 22530.8 | N99: 16062.3 | O99: 9381.9 | P99: 7546.1 | Q99: 206962.2 | R99: 194853.5 | S99: 151258.3 | T99: 148522.3 | U99: 406237.4 | V99: 53289.5 | X99: No/NA | Y99: Yes - 100%
C100: Loader (Ore) | D100: Load truck with ore from BRW pit | E100: Hexagon Data, in AJ's spreadsheet "FY-Enviro-Dept-Jul23-Jun24.xlsx" | F100: BRW Ore Assay | H100: =SUM(K100:V100) -> 58078.2 | I100: Tonne | K100: 615.4 | L100: 4266.1 | M100: 2925.5 | N100: 3369.2 | O100: 4799 | P100: 2323.4 | Q100: 4996.1 | R100: 687.3 | S100: 6618.7 | T100: 4760.1 | U100: 16064.1 | V100: 6653.3 | X100: No/NA | Y100: Yes - 100%
C101: Haul/Dump Truck (Ore) | D101: Haul ore from BRW pit to various locations | E101: Hexagon Data, in AJ's spreadsheet "FY-Enviro-Dept-Jul23-Jun24.xlsx" | F101: BRW Ore Assay | H101: =SUM(K101:V101) -> 1307931.7 | I101: Tonne | K101: 10124.7 | L101: 27966 | M101: 25456.3 | N101: 19431.5 | O101: 14180.9 | P101: 9869.5 | Q101: 211958.3 | R101: 195540.8 | S101: 157877 | T101: 153282.4 | U101: 422301.5 | V101: 59942.8 | X101: No/NA | Y101: NA/No - 0%
C102: Excavator (Ore) | D102: Load truck with LG ore from BRW pit | E102: Hexagon Data, in AJ's spreadsheet "FY-Enviro-Dept-Jul23-Jun24.xlsx" | F102: BRW Ore Assay | H102: =SUM(K102:V102) -> 644592.4 | I102: Tonne | K102: 175516.1 | L102: 328694.9 | M102: 38019.5 | N102: 2241.4 | O102: 3561.3 | P102: 90511.5 | Q102: 387.5 | R102: 415.9 | S102: 610.3 | T102: 1885.1 | U102: 1496.2 | V102: 1252.7 | X102: No/NA | Y102: Yes - 100%
C103: Loader (Ore) | D103: Load truck with LG ore from BRW pit | E103: Hexagon Data, in AJ's spreadsheet "FY-Enviro-Dept-Jul23-Jun24.xlsx" | F103: BRW Ore Assay | H103: =SUM(K103:V103) -> 15202.9 | I103: Tonne | K103: 8408.6 | L103: 4128.9 | M103: 2665.4 | N103: 0 | O103: 0 | P103: 0 | Q103: 0 | R103: 0 | S103: 0 | T103: 0 | U103: 0 | V103: 0 | X103: No/NA | Y103: Yes - 100%
C104: Haul/Dump Truck (Ore) | D104: Haul LG ore from BRW pit to various locations | E104: Hexagon Data, in AJ's spreadsheet "FY-Enviro-Dept-Jul23-Jun24.xlsx" | F104: BRW Ore Assay | H104: =SUM(K104:V104) -> 659795.3 | I104: Tonne | K104: 183924.7 | L104: 332823.8 | M104: 40684.9 | N104: 2241.4 | O104: 3561.3 | P104: 90511.5 | Q104: 387.5 | R104: 415.9 | S104: 610.3 | T104: 1885.1 | U104: 1496.2 | V104: 1252.7 | X104: No/NA | Y104: NA/No - 0%
C105: Loader (Ore) | D105: Load truck with ore from SAR pit | E105: Hexagon Data, in AJ's spreadsheet "FY-Enviro-Dept-Jul23-Jun24.xlsx" | F105: Sarsfield Combined Ore Assay | H105: =SUM(K105:V105) -> 353.5 | I105: Tonne | K105: 0 | L105: 0 | M105: 0 | N105: 0 | O105: 0 | P105: 0 | Q105: 0 | R105: 353.5 | S105: 0 | T105: 0 | U105: 0 | V105: 0 | X105: No/NA | Y105: Yes - 100%
C106: Haul/Dump Truck (Ore) | D106: Haul ore from SAR pit to various locations | E106: Hexagon Data, in AJ's spreadsheet "FY-Enviro-Dept-Jul23-Jun24.xlsx" | F106: Sarsfield Combined Ore Assay | H106: =SUM(K106:V106) -> 353.5 | I106: Tonne | K106: 0 | L106: 0 | M106: 0 | N106: 0 | O106: 0 | P106: 0 | Q106: 0 | R106: 353.5 | S106: 0 | T106: 0 | U106: 0 | V106: 0 | X106: No/NA | Y106: NA/No - 0%
C107: Excavator (Ore) | D107: Load truck with LG ore from SAR pit | E107: Hexagon Data, in AJ's spreadsheet "FY-Enviro-Dept-Jul23-Jun24.xlsx" | F107: Sarsfield LG Ore | H107: =SUM(K107:V107) -> 249954.3 | I107: Tonne | K107: 0 | L107: 0 | M107: 0 | N107: 0 | O107: 0 | P107: 0 | Q107: 46227.7 | R107: 551.2 | S107: 31808.7 | T107: 4811.1 | U107: 89998.3 | V107: 76557.3 | X107: No/NA | Y107: Yes - 100%
C108: Loader (Ore) | D108: Load truck with LG ore from SAR pit | E108: Hexagon Data, in AJ's spreadsheet "FY-Enviro-Dept-Jul23-Jun24.xlsx" | F108: Sarsfield LG Ore | H108: =SUM(K108:V108) -> 16524.9 | I108: Tonne | K108: 0 | L108: 0 | M108: 0 | N108: 0 | O108: 0 | P108: 0 | Q108: 0 | R108: 0 | S108: 0 | T108: 0 | U108: 16524.9 | V108: 0 | X108: No/NA | Y108: Yes - 100%
C109: Haul/Dump Truck (Ore) | D109: Haul LG ore from SAR pit to various locations | E109: Hexagon Data, in AJ's spreadsheet "FY-Enviro-Dept-Jul23-Jun24.xlsx" | F109: Sarsfield LG Ore | H109: =SUM(K109:V109) -> 266479.2 | I109: Tonne | K109: 0 | L109: 0 | M109: 0 | N109: 0 | O109: 0 | P109: 0 | Q109: 46227.7 | R109: 551.2 | S109: 31808.7 | T109: 4811.1 | U109: 106523.2 | V109: 76557.3 | X109: No/NA | Y109: NA/No - 0%
C111: Rehandled Ore
C112: Excavator (Ore) | D112: Break rock on ROM pad - SIMMCO | E112: Simmco Daily Sheet | F112: Average Ore Assay | H112: =SUM(K112:V112) -> 5362 | I112: Tonne | K112: 0 | L112: 4520 | M112: 842 | N112: 0 | O112: 0 | P112: 0 | Q112: 0 | R112: 0 | S112: 0 | T112: 0 | U112: 0 | V112: 0 | X112: No/NA | Y112: NA/No - 0%
...

Sheet GG - TSF
C3: Ravenswood Operations | H3: Tailings facilities can be a significant contributor to ground water pollution from leaks and seepage, and to air from volatilisation
C4: 01/07/2023 - 30/06/2024 | H4: Update the values in red. If the metallurgists cannot provide Known Water in Slurry and Solids in Tailings, then you will need to calculate these values. You can use the method used for previous years - just need to update the red values in the data table at the bottom of the page under "raw data". You can also get the data which is needed for the calculations from the metallurgists. For the samples - use data from DataSight for seepage bores and columns located around the NTSFE.
C6: Tailings Storage Facility
C8: Slurry Details | G8: Data Sources: | I8: Environmental Database - DataSight V3 for parameter values. Tailings makeup from Senior Metallurgist (Tim Mitchell/Peter Msonga)
C10: Location | D10: Parameter | E10: Material Assay | F10: FY2023 Total | G10: FY2024 Total | H10: Unit | I10: Monthly Amount
H11: units | I11: Jul | J11: Aug | K11: Sep | L11: Oct | M11: Nov | N11: Dec | O11: Jan | P11: Feb | Q11: Mar | R11: Apr | S11: May | T11: Jun
C12: NTSFE | D12: Slurry pumped into facility (WM#83) (TOTAL) | E12: Average Tailings Assay | F12: 4541742 | G12: =SUM(I12:T12) -> 4661674 | H12: m3 | I12: 335350 | J12: 413628 | K12: 353488 | L12: 357000 | M12: 479714 | N12: 291600 | O12: 463520 | P12: 429846 | Q12: 255234 | R12: 385806 | S12: 508810 | T12: 387678
D13: Tailings Solids from Plant to NTSFE | E13: Average Tailings Assay | F13: 2650446.4 | G13: =SUM(I13:T13) -> 2635546.4 | H13: m3 | I13: 223662.5 | J13: 195394.3 | K13: 203127.6 | L13: 253819.6 | M13: 210094.2 | N13: 244766.7 | O13: 216605.6 | P13: 210167.9 | Q13: 201584.6 | R13: 248533.2 | S13: 218460.9 | T13: 209329.3
D14: Water in Slurry (WM#83) | E14: Average Tailings Assay | F14: 1891295.6 | G14: =SUM(I14:T14) -> 2026127.6 | H14: m3 | I14: 111687.5 | J14: 218233.7 | K14: 150360.4 | L14: 103180.4 | M14: 269619.8 | N14: 46833.3 | O14: 246914.4 | P14: 219678.1 | Q14: 53649.4 | R14: 137272.8 | S14: 290349.1 | T14: 178348.7
D15: Tailings Solids from Plant to NTSFE (SG = 2.54) | E15: Average Tailings Assay | F15: 6732133.7 | G15: =SUM(I15:T15) -> 6694287.9 | H15: Tonnes | I15: =I13*2.54 -> 568102.75 | J15: =J13*2.54 -> 496301.52 | K15: =K13*2.54 -> 515944.1 | L15: =L13*2.54 -> 644701.78 | M15: =M13*2.54 -> 533639.27 | N15: =N13*2.54 -> 621707.42 | O15: =O13*2.54 -> 550178.22 | P15: =P13*2.54 -> 533826.47 | ... T15: =T13*2.54 -> 531696.42
D16: Solids in Tailings (from SAR Pit) | E16: Average Tailings Assay | F16: 18022 | G16: =SUM(I16:T16) -> 832500 | H16: Tonnes | I16: 41731 | J16: 43003 | K16: 66300 | L16: 48284 | M16: 23425 | N16: 21985 | O16: 53139 | P16: 65680 | Q16: 120196 | R16: 259831 | S16: 68430 | T16: 20496
G17: =SUM(I17:T17) -> 0
D18: Seepage Recovered | F18: 5029584 | G18: 212795 | H18: m3 | I18: 22063 | J18: 22958 | K18: 16317 | L18: 11367 | M18: 11814 | N18: 16046 | O18: 14890 | P18: 17875 | Q18: 28988 | R18: 29058 | S18: 12059 | T18: 9360
I20: Monthly Amount
C21: Location | D21: Parameter | E21: Date Sampled | F21: FY2023 Average | G21: FY2024 Average | H21: Unit | I21: Jul | J21: Aug | K21: Sep | L21: Oct | M21: Nov | N21: Dec | O21: Jan | P21: Feb | Q21: Mar | R21: Apr | S21: May | T21: Jun
C22: Tailings Slurry Leaving the Plant | D22: Free CN | E22: 45212 | F22: 126.55 | G22: 154 | H22: mg/L | L22: 154
D23: pH | E23: 45212 | F23: 10.11 | G23: 10.1 | H23: Unit | L23: 10.1
C27: Samples of TSF measured from Monitoring Bores
G29: Substance and Units
C30: Location | D30: Date Sampled | G30: Total CN | H30: WAD CN (1) | I30: As | J30: B | K30: Be | L30: Cd | M30: Co | N30: Cr (III) | O30: Cu | P30: F | Q30: Hg | R30: Mn | S30: Ni | T30: Pb | U30: Sb | V30: Se | W30: Zn
G31: mg/L | H31: mg/L | I31: mg/L | J31: mg/L | K31: mg/L | L31: mg/L | M31: mg/L | N31: mg/L | O31: mg/L | P31: mg/L | Q31: mg/L | R31: mg/L | S31: mg/L | T31: mg/L | U31: mg/L | V31: mg/L | W31: mg/L
C32: NOL_OB138 | D32: 45172 | G32: 0.088 | H32: 0.015 | I32: 0.003 | J32: 0.16 | L32: <0.0001 | M32: 0.246 | N32: <0.001 | O32: <0.001 | R32: 0.078 | S32: 0.002 | T32: <0.001 | U32: <0.001 | V32: <0.01 | W32: 0.027
C33: NOL_OB138 | D33: 45254 | G33: 0.073 | H33: <0.004 | I33: 0.006 | J33: 0.16 | L33: <0.0001 | M33: 0.298 | N33: <0.001 | O33: <0.001 | R33: 0.072 | S33: <0.001 | T33: <0.001 | U33: <0.001 | V33: <0.01 | W33: <0.005
C34: NOL_OB138 | D34: 45328 | G34: 0.105 | H34: <0.004 | I34: 0.006 | J34: 0.16 | L34: <0.0001 | M34: 0.394 | N34: <0.001 | O34: 0.0006 | R34: 0.082 | S34: <0.001 | T34: <0.001 | U34: <0.001 | V34: <0.01 | W34: <0.005
C35: NOL_OB138 | D35: 45391 | G35: 0.116 | H35: <0.004 | I35: 0.004 | J35: 0.16 | L35: <0.0001 | M35: 0.327 | N35: <0.001 | O35: 0.0006 | R35: 0.091 | S35: <0.001 | T35: <0.001 | U35: <0.001 | V35: <0.01 | W35: 0.025
C36: NOL_OB139 | D36: 45172 | G36: 0.118 | H36: 0.004 | I36: 0.006 | J36: 0.08 | L36: <0.0001 | M36: 0.4 | N36: <0.001 | O36: <0.001 | R36: 1.72 | S36: 0.002 | T36: <0.001 | U36: <0.001 | V36: <0.01 | W36: 0.027
C37: NOL_OB139 | D37: 45254 | G37: 0.125 | H37: <0.004 | I37: 0.01 | J37: 0.11 | L37: <0.0001 | M37: 0.505 | N37: <0.001 | O37: <0.001 | R37: 1.44 | S37: 0.001 | T37: <0.001 | U37: <0.001 | V37: <0.01 | W37: <0.005
C38: NOL_OB139 | D38: 45328 | G38: 0.13 | H38: <0.004 | I38: 0.006 | J38: 0.12 | L38: <0.0001 | M38: 0.478 | N38: <0.001 | O38: <0.0005 | R38: 1.6 | S38: 0.001 | T38: <0.001 | U38: <0.001 | V38: <0.01 | W38: <0.005
C39: NOL_OB139 | D39: 45392 | G39: 0.138 | H39: <0.004 | I39: 0.005 | J39: 0.14 | L39: <0.0001 | M39: 0.375 | N39: <0.001 | O39: <0.0005 | R39: 1.85 | S39: 0.001 | T39: <0.001 | U39: <0.001 | V39: <0.01 | W39: 0.016
C40: NOL_OB140 | D40: 45172 | G40: 0.04 | H40: 0.007 | I40: 0.002 | J40: 0.12 | L40: <0.0001 | M40: 0.11 | N40: <0.001 | O40: <0.001 | R40: 0.24 | S40: 0.002 | T40: <0.001 | U40: <0.001 | V40: <0.01 | W40: 0.011
C41: NOL_OB140 | D41: 45254 | G41: 0.031 | H41: <0.004 | I41: 0.005 | J41: 0.12 | L41: <0.0001 | M41: 0.116 | N41: <0.001 | O41: <0.001 | R41: 0.17 | S41: <0.001 | T41: <0.001 | U41: <0.001 | V41: <0.01 | W41: 0.006
C42: NOL_OB140 | D42: 45254 | G42: 0.033 | H42: <0.004 | I42: 0.005 | J42: 0.12 | L42: <0.0001 | M42: 0.115 | N42: <0.001 | O42: <0.001 | R42: 0.158 | S42: <0.001 | T42: <0.001 | U42: <0.001 | V42: <0.01 | W42: 0.008
C43: NOL_OB140 | D43: 45332 | G43: 0.028 | H43: <0.004 | I43: 0.003 | J43: 0.13 | L43: <0.0001 | M43: 0.117 | N43: <0.001 | O43: <0.0005 | R43: 0.416 | S43: 0.001 | T43: <0.001 | U43: <0.001 | V43: <0.01 | W43: 0.007
C44: NOL_OB140 | D44: 45391 | G44: 0.044 | H44: <0.004 | I44: 0.002 | J44: 0.14 | L44: <0.0001 | M44: 0.11 | N44: <0.001 | O44: <0.0005 | R44: 0.27 | S44: <0.001 | T44: <0.001 | U44: <0.001 | V44: <0.01 | W44: 0.02
C45: NTSFE Monitoring Bores Average | G45: =AVERAGE(G32:G44) -> 0.082230769 | H45: =AVERAGE(H32:H44) -> 0.0086666667 | I45: =AVERAGE(I32:I44) -> 0.0048461538 | J45: =AVERAGE(J32:J44) -> 0.13230769 | K45: =AVERAGE(K32:K44) -> #DIV/0! | L45: =AVERAGE(L32:L44) -> #DIV/0! | M45: =AVERAGE(M32:M44) -> 0.27623077 | N45: =AVERAGE(N32:N44) -> #DIV/0! | ... W45: =AVERAGE(W32:W44) -> 0.016333333
B48: (1) | C48: Weak Acid Dissociable Cyanide, only required if Total CN is not available
C49: Provide as many appropriate monitoring bore samples as are available and representative of seepage
C50: All metals are filtered results. Cr measurement is unspeciated result
C51: Paste raw data below:
C52: Parameter | E52: Material Assay | F52: 2023 Annual Total | G52: 2024 Annual Total | H52: units | I52: Monthly Amount
H53: units | I53: Jul | J53: Aug | K53: Sep | L53: Oct | M53: Nov | N53: Dec | O53: Jan | P53: Feb | Q53: Mar | R53: Apr | S53: May | T53: Jun
C54: Volume of tailings pumped into facility (WM#83) | E54: Average Tailings Assay | F54: 4541742 | G54: =SUM(I54:T54) -> 4661674 | H54: m3 | I54: 335350 | J54: 413628 | K54: 353488 | L54: 357000 | M54: 479714 | N54: 291600 | O54: 463520 | P54: 429846 | Q54: 255234 | R54: 385806 | S54: 508810 | T54: 387678
C55: Volume of tailings pumped into facility (from SAR Pit) | E55: Average Tailings Assay | F55: 733800 | G55: =SUM(I55:T55) -> 733800 | H55: m3 | I55: 0 | J55: 75220 | K55: 225034 | L55: 86524 | M55: 0 | N55: 0 | O55: 0 | P55: 0 | Q55: 0 | R55: 0 | S55: 150959 | T55: 196063
C56: Known Water in Slurry (WM#83) | E56: N/A | F56: 1891295.6 | G56: =SUM(I56:T56) -> 2026127.6 | H56: m3 | I56: =I54-I60 -> 111687.5 | J56: =J54-J60 -> 218233.7 | K56: =K54-K60 -> 150360.4 | L56: =L54-L60 -> 103180.4 | M56: =M54-M60 -> 269619.8 | N56: =N54-N60 -> 46833.3 | O56: =O54-O60 -> 246914.4 | P56: =P54-P60 -> 219678.1 | ... T56: =T54-T60 -> 178348.7
C57: Slurry Density (WM#83) | E57: N/A | F57: - | G57: =SUM(I57:T57) -> 686.73 | H57: % Sol | I57: 76.21 | J57: 75.49 | K57: 76.21 | L57: 75.92 | M57: 65.01 | N57: 43.91 | O57: 44.28 | P57: 43.61 | Q57: 42.81 | R57: 47.81 | S57: 47.94 | T57: 47.53
C58: Solids in Tailings (Tailings SG = 2.54) (WM#83) | E58: N/A | F58: 6732133.7 | G58: =SUM(I58:T58) -> 6694287.9 | H58: Tonnes | I58: =(I54-I56)*2.54 -> 568102.75 | J58: =(J54-J56)*2.54 -> 496301.52 | K58: =(K54-K56)*2.54 -> 515944.1 | L58: =(L54-L56)*2.54 -> 644701.78 | M58: =(M54-M56)*2.54 -> 533639.27 | N58: =(N54-N56)*2.54 -> 621707.42 | O58: =(O54-O56)*2.54 -> 550178.22 | P58: =(P54-P56)*2.54 -> 533826.47 | ... T58: =(T54-T56)*2.54 -> 531696.42
C59: Solids in Tailings (from SAR Pit) | E59: N/A | F59: 42512 | G59: =SUM(I59:T59) -> 42512 | H59: Tonnes | I59: 0 | J59: 6256 | K59: 14019 | L59: 4215 | M59: 0 | N59: 0 | O59: 0 | P59: 0 | Q59: 0 | R59: 0 | S59: 2903 | T59: 15119
C60: Tailings Solids from Plant to NTSFE (m3) | G60: =SUM(I60:T60) -> 2635546.4 | H60: m3 | I60: 223662.5 | J60: 195394.3 | K60: 203127.6 | L60: 253819.6 | M60: 210094.2 | N60: 244766.7 | O60: 216605.6 | P60: 210167.9 | Q60: 201584.6 | R60: 248533.2 | S60: 218460.9 | T60: 209329.3
G61: =SUM(I61:T61) -> 6694287.9 | H61: Tonnes | I61: =I60*2.54 -> 568102.75 | J61: =J60*2.54 -> 496301.52 | K61: =K60*2.54 -> 515944.1 | L61: =L60*2.54 -> 644701.78 | M61: =M60*2.54 -> 533639.27 | N61: =N60*2.54 -> 621707.42 | O61: =O60*2.54 -> 550178.22 | P61: =P60*2.54 -> 533826.47 | ... T61: =T60*2.54 -> 531696.42
C63: Location | D63: Parameter | E63: Material Assay | F63: FY2023 Total | G63: FY2024 Total | H63: Unit | I63: Monthly Amount
H64: units | I64: Jul | J64: Aug | K64: Sep | L64: Oct | M64: Nov | N64: Dec | O64: Jan | P64: Feb | Q64: Mar | R64: Apr | S64: May | T64: Jun
C65: NTSFE | D65: Slurry volume to TSF | E65: N/A | F65: 1891296 | G65: 4705206 | H65: m3 | I65: 359726 | J65: 413628 | K65: 353488 | L65: 437218 | M65: 399496 | N65: 474580 | O65: 401400 | P65: 308986 | Q65: 456160 | R65: 377444 | S65: 395498 | T65: 327582
D66: Decant water pumped from TSF | E66: [select] | F66: 6774646 | G66: 4949485 | H66: m3 | I66: 225346 | J66: 386303 | K66: 450175 | L66: 359028 | M66: 339249 | N66: 452874 | O66: 455001 | P66: 441506 | Q66: 471181 | R66: 637932 | S66: 467228 | T66: 263662
D67: Seepage Recovered | F67: 5029584 | G67: 212795 | H67: m3 | I67: 22063 | J67: 22958 | K67: 16317 | L67: 11367 | M67: 11814 | N67: 16046 | O67: 14890 | P67: 17875 | Q67: 28988 | R67: 29058 | S67: 12059 | T67: 9360
F71: =F58/2.54 -> 2650446.4

Sheet GG Leach Tanks & Heap Leach
C3: Ravenswood Operations | H3: Leach Tanks / Heap Leach are used for estimating the cyanide volatilisation to air and transfer to tailings component
C4: 01/07/2023 - 30/06/2024 | H4: Heap leach = not applicable. Only need to complete the Leach Tanks (NaCN, pH, Operating Hours) section. Update values in red.
C6: Heap Leach
H7: Monthly Amount
E8: FY2023 Total | F8: FY2024 Total | G8: Unit | H8: Jul | I8: Aug | J8: Sep | K8: Oct | L8: Nov | M8: Dec | N8: Jan | O8: Feb | P8: Mar | Q8: Apr | R8: May | S8: Jun
C9: NaCN Usage | F9: =SUM(H9:S9) -> 0 | G9: [select]
C11: Leach Tanks
E12: Data Sources: | G12: - Free cyanide (CN ppm) and pH data from spreadsheet G:\Laboratory\Mets 2016 'Pulps' tab - Operating hours provided by Jeffery Brockhurst / Zack Pringle - retrieved from PlantVantage. Method to retrieve data from plant vantage: access Macroview, and click on each plant asset i.e Processing Tank 101, the plant ID will appear at the top of the screen, go to PlantVantage and add each pen in, you can then select the date range and retrieve the data
C14: NaCN
E15: FY2023 Average | F15: FY2024 Average | G15: Unit | H15: Monthly Amount | U15: Diameter | V15: Surface Area
C16: Tank | H16: Jul | I16: Aug | J16: Sep | K16: Oct | L16: Nov | M16: Dec | N16: Jan | O16: Feb | P16: Mar | Q16: Apr | R16: May | S16: Jun | U16: m | V16: m2
C17: Processing Tank 101 | E17: 254.5822 | F17: =AVERAGE(H17:S17) -> 238.66667 | G17: mg/L | H17: 265 | I17: 259 | J17: 260 | K17: 251 | L17: 230 | M17: 219 | N17: 232 | O17: 215 | P17: 236 | Q17: 242 | R17: 238 | S17: 217 | V17: =PI()*(U17/2)^2 -> 0
C18: Processing Tank 102 | E18: 0 | F18: =AVERAGE(H18:S18) -> 227.75 | G18: mg/L | H18: 239 | I18: 237 | J18: 239 | K18: 244 | L18: 220 | M18: 212 | N18: 222 | O18: 209 | P18: 232 | Q18: 237 | R18: 230 | S18: 212 | V18: =PI()*(U18/2)^2 -> 0
C19: Processing Tank 1 | E19: 250.58203 | F19: =AVERAGE(H19:S19) -> 223.5 | G19: mg/L | H19: 250 | I19: 249 | J19: 234 | K19: 240 | L19: 187 | M19: 212 | N19: 222 | O19: 203 | P19: 227 | Q19: 232 | R19: 216 | S19: 210 | V19: =PI()*(U19/2)^2 -> 0
C20: Processing Tank 2 | E20: 234.92301 | F20: =AVERAGE(H20:S20) -> 214.91667 | G20: mg/L | H20: 239 | I20: 219 | J20: 216 | K20: 224 | L20: 203 | M20: 213 | N20: 211 | O20: 212 | P20: 227 | Q20: 216 | R20: 209 | S20: 190 | V20: =PI()*(U20/2)^2 -> 0
C21: Processing Tank 3 | E21: 220.52366 | F21: =AVERAGE(H21:S21) -> 216.58333 | G21: mg/L | H21: 233 | I21: 229 | J21: 230 | K21: 225 | L21: 206 | M21: 211 | N21: 203 | O21: 207 | P21: 218 | Q21: 214 | R21: 231 | S21: 192 | V21: =PI()*(U21/2)^2 -> 0
C22: Processing Tank 4 | E22: 220.47533 | F22: =AVERAGE(H22:S22) -> 206.08333 | G22: mg/L | H22: 229 | I22: 206 | J22: 198 | K22: 218 | L22: 197 | M22: 203 | N22: 195 | O22: 204 | P22: 225 | Q22: 204 | R22: 205 | S22: 189 | V22: =PI()*(U22/2)^2 -> 0
C23: Processing Tank 5 | E23: 210.1742 | F23: =AVERAGE(H23:S23) -> 203.08333 | G23: mg/L | H23: 215 | I23: 207 | J23: 211 | K23: 214 | L23: 199 | M23: 205 | N23: 196 | O23: 192 | P23: 216 | Q23: 202 | R23: 201 | S23: 179 | V23: =PI()*(U23/2)^2 -> 0
C24: Processing Tank 6 | E24: 218.45554 | F24: =AVERAGE(H24:S24) -> 205.91667 | G24: mg/L | H24: 227 | I24: 196 | J24: 212 | K24: 210 | L24: 198 | M24: 200 | N24: 213 | O24: 199 | P24: 210 | Q24: 212 | R24: 203 | S24: 191 | V24: =PI()*(U24/2)^2 -> 0
C25: Processing Tank 7 | E25: 210.87266 | F25: =AVERAGE(H25:S25) -> 208 | G25: mg/L | H25: 220 | I25: 205 | J25: 219 | K25: 216 | L25: 200 | M25: 200 | N25: 217 | O25: 216 | P25: 204 | Q25: 210 | R25: 201 | S25: 188 | V25: =PI()*(U25/2)^2 -> 0
C26: Processing Tank 501 | E26: 393.58228 | F26: =AVERAGE(H26:S26) -> 412.08333 | G26: mg/L | H26: 360 | I26: 402 | J26: 392 | K26: 427 | L26: 410 | M26: 412 | N26: 410 | O26: 427 | P26: 416 | Q26: 422 | R26: 451 | S26: 416 | V26: =PI()*(U26/2)^2 -> 0
C27: Processing Tank 502 | E27: 318.57233 | F27: =AVERAGE(H27:S27) -> 318.41667 | G27: mg/L | H27: 309 | I27: 287 | J27: 325 | K27: 319 | L27: 299 | M27: 328 | N27: 320 | O27: 298 | P27: 321 | Q27: 324 | R27: 361 | S27: 330 | V27: =PI()*(U27/2)^2 -> 0
C28: Processing Tank 503 | E28: 306.18612 | F28: =AVERAGE(H28:S28) -> 282.5 | G28: mg/L | H28: 293 | I28: 263 | J28: 299 | K28: 284 | L28: 251 | M28: 269 | N28: 282 | O28: 262 | P28: 291 | Q28: 292 | R28: 309 | S28: 295 | V28: =PI()*(U28/2)^2 -> 0
... C31: Processing Tank 506 | E31: 280.51489 | F31: =AVERAGE(H31:S31) -> 269 | G31: mg/L | H31: 269 | I31: 286 | J31: 282 | K31: 280 | L31: 255 | M31: 253 | N31: 263 | O31: 250 | P31: 287 | Q31: 286 | R31: 265 | S31: 252 | V31: =PI()*(U31/2)^2 -> 0
F32: =AVERAGE(H32:S32) -> #DIV/0! | G32: mg/L | V32: =PI()*(U32/2)^2 -> 0
F33: =AVERAGE(H33:S33) -> #DIV/0! | G33: mg/L | V33: =PI()*(U33/2)^2 -> 0
C35: Average | E35: 210.66753 | F35: =AVERAGE(H35:S35) -> 257.25 | G35: mg/L | H35: =AVERAGE(H17:H33) -> 264.2 | I35: =AVERAGE(I17:I33) -> 258.4 | J35: =AVERAGE(J17:J33) -> 264.26667 | K35: =AVERAGE(K17:K33) -> 266 | L35: =AVERAGE(L17:L33) -> 242.4 | M35: =AVERAGE(M17:M33) -> 250.53333 | N35: =AVERAGE(N17:N33) -> 256.06667 | O35: =AVERAGE(O17:O33) -> 248.6 | ... S35: =AVERAGE(S17:S33) -> 245.8
C37: pH
E38: FY2023 Average | F38: FY2024 Average | G38: Unit | H38: Monthly Amount
H39: Jul | I39: Aug | J39: Sep | K39: Oct | L39: Nov | M39: Dec | N39: Jan | O39: Feb | P39: Mar | Q39: Apr | R39: May | S39: Jun
C40: =C17 -> Processing Tank 101 | E40: 10.614167 | F40: =AVERAGE(H40:S40) -> 10.560833 | G40: pH | H40: 10.77 | I40: 10.79 | J40: 10.62 | K40: 10.62 | L40: 10.59 | M40: 10.47 | N40: 10.51 | O40: 10.43 | P40: 10.39 | Q40: 10.51 | R40: 10.54 | S40: 10.49
C41: =C18 -> Processing Tank 102 | E41: 0 | F41: =AVERAGE(H41:S41) -> 10.6175 | G41: pH | H41: 10.78 | I41: 10.79 | J41: 10.65 | K41: 10.67 | L41: 10.63 | M41: 10.52 | N41: 10.78 | O41: 10.44 | P41: 10.35 | Q41: 10.61 | R41: 10.64 | S41: 10.55
C42: =C19 -> Processing Tank 1 | E42: 10.601667 | F42: =AVERAGE(H42:S42) -> 10.591667 | G42: pH | H42: 10.81 | I42: 10.81 | J42: 10.55 | K42: 10.69 | L42: 10.61 | M42: 10.49 | N42: 10.57 | O42: 10.44 | P42: 10.39 | Q42: 10.56 | R42: 10.61 | S42: 10.57
C43: =C20 -> Processing Tank 2 | E43: 10.539167 | F43: =AVERAGE(H43:S43) -> 10.545 | G43: pH | H43: 10.68 | I43: 10.71 | J43: 10.59 | K43: 10.63 | L43: 10.61 | M43: 10.46 | N43: 10.53 | O43: 10.44 | P43: 10.32 | Q43: 10.52 | R43: 10.56 | S43: 10.49
C44: =C21 -> Processing Tank 3 | E44: 10.55 | F44: =AVERAGE(H44:S44) -> 10.593333 | G44: pH | H44: 10.79 | I44: 10.76 | J44: 10.59 | K44: 10.67 | L44: 10.7 | M44: 10.54 | N44: 10.59 | O44: 10.42 | P44: 10.35 | Q44: 10.56 | R44: 10.58 | S44: 10.57
C45: =C22 -> Processing Tank 4 | E45: 10.505833 | F45: =AVERAGE(H45:S45) -> 10.548333 | G45: pH | H45: 10.72 | I45: 10.66 | J45: 10.56 | K45: 10.62 | L45: 10.6 | M45: 10.5 | N45: 10.51 | O45: 10.43 | P45: 10.37 | Q45: 10.53 | R45: 10.56 | S45: 10.52
C46: =C23 -> Processing Tank 5 | E46: 10.525833 | F46: =AVERAGE(H46:S46) -> 10.561667 | G46: pH | H46: 10.73 | I46: 10.74 | J46: 10.55 | K46: 10.67 | L46: 10.64 | M46: 10.49 | N46: 10.53 | O46: 10.43 | P46: 10.33 | Q46: 10.55 | R46: 10.57 | S46: 10.51
C47: =C24 -> Processing Tank 6 | E47: 10.535833 | F47: =AVERAGE(H47:S47) -> 10.559167 | G47: pH | H47: 10.67 | I47: 10.69 | J47: 10.61 | K47: 10.67 | L47: 10.64 | M47: 10.51 | N47: 10.44 | O47: 10.51 | P47: 10.36 | Q47: 10.53 | R47: 10.59 | S47: 10.49
C48: =C25 -> Processing Tank 7 | E48: 11.157273 | F48: =AVERAGE(H48:S48) -> 10.5 | G48: pH | H48: 10.62 | I48: 10.67 | J48: 10.57 | K48: 10.56 | L48: 10.58 | M48: 10.46 | N48: 10.38 | O48: 10.42 | P48: 10.29 | Q48: 10.49 | R48: 10.51 | S48: 10.45
C49: =C26 -> Processing Tank 501 | E49: 11.14 | F49: =AVERAGE(H49:S49) -> 11.066667 | G49: pH | H49: 11.16 | I49: 11.24 | J49: 11.23 | K49: 11.1 | L49: 11.09 | M49: 11.03 | N49: 10.91 | O49: 10.92 | P49: 11 | Q49: 11.04 | R49: 11.05 | S49: 11.03
C50: =C27 -> Processing Tank 502 | E50: 10.921818 | F50: =AVERAGE(H50:S50) -> 10.854167 | G50: pH | H50: 11 | I50: 10.98 | J50: 11.02 | K50: 10.87 | L50: 10.85 | M50: 10.84 | N50: 10.75 | O50: 10.72 | P50: 10.7 | Q50: 10.81 | R50: 10.87 | S50: 10.84
C51: =C28 -> Processing Tank 503 | E51: 10.85 | F51: =AVERAGE(H51:S51) -> 10.770833 | G51: pH | H51: 10.94 | I51: 10.95 | J51: 10.91 | K51: 10.82 | L51: 10.75 | M51: 10.73 | N51: 10.64 | O51: 10.62 | P51: 10.6 | Q51: 10.7 | R51: 10.79 | S51: 10.8
... C54: =C31 -> Processing Tank 506 | E54: 10.693333 | F54: =AVERAGE(H54:S54) -> 10.6725 | G54: pH | H54: 10.84 | I54: 10.88 | J54: 10.72 | K54: 10.74 | L54: 10.68 | M54: 10.61 | N54: 10.62 | O54: 10.51 | P54: 10.47 | Q54: 10.65 | R54: 10.69 | S54: 10.66
C55: =C32 -> 0 | F55: =AVERAGE(H55:S55) -> #DIV/0! | G55: pH
C56: =C33 -> 0 | F56: =AVERAGE(H56:S56) -> #DIV/0! | G56: pH
C57: Added Lime during the month | H57: [select] | I57: [select] | J57: [select] | K57: [select] | L57: [select] | M57: [select] | N57: [select] | O57: [select] | P57: [select] | Q57: [select] | R57: [select] | S57: [select]
C58: Added Cyanide during the month | H58: [select] | I58: [select] | J58: [select] | K58: [select] | L58: [select] | M58: [select] | N58: [select] | O58: [select] | P58: [select] | Q58: [select] | R58: [select] | S58: [select]
C60: Average | E60: 10.426528 | F60: =AVERAGE(H60:S60) -> 10.667778 | G60: pH | H60: =AVERAGE(H40:H54) -> 10.833333 | I60: =AVERAGE(I40:I54) -> 10.846 | J60: =AVERAGE(J40:J54) -> 10.714 | K60: =AVERAGE(K40:K54) -> 10.734 | L60: =AVERAGE(L40:L54) -> 10.705333 | M60: =AVERAGE(M40:M54) -> 10.605333 | N60: =AVERAGE(N40:N54) -> 10.609333 | O60: =AVERAGE(O40:O54) -> 10.544 | ... S60: =AVERAGE(S40:S54) -> 10.628
C62: Operating Hours (1)
E63: FY2023 Total | F63: FY2024 Total | G63: Unit | H63: Monthly Amount
H64: Jul | I64: Aug | J64: Sep | K64: Oct | L64: Nov | M64: Dec | N64: Jan | O64: Feb | P64: Mar | Q64: Apr | R64: May | S64: Jun
C65: =C17 -> Processing Tank 101 | E65: 8228 | F65: =SUM(H65:S65) -> 8576 | G65: hr | H65: 744 | I65: 744 | J65: 720 | K65: 536 | L65: 720 | M65: 744 | N65: 744 | O65: 696 | P65: 744 | Q65: 720 | R65: 744 | S65: 720
C66: =C18 -> Processing Tank 102 | E66: 0 | F66: =SUM(H66:S66) -> 8784 | G66: hr | H66: 744 | I66: 744 | J66: 720 | K66: 744 | L66: 720 | M66: 744 | N66: 744 | O66: 696 | P66: 744 | Q66: 720 | R66: 744 | S66: 720
C67: =C19 -> Processing Tank 1 | E67: 8747 | F67: =SUM(H67:S67) -> 8784 | G67: hr | H67: 744 | I67: 744 | J67: 720 | K67: 744 | L67: 720 | M67: 744 | N67: 744 | O67: 696 | P67: 744 | Q67: 720 | R67: 744 | S67: 720
C68: =C20 -> Processing Tank 2 | E68: 8742 | F68: =SUM(H68:S68) -> 8784 | G68: hr | H68: 744 | I68: 744 | J68: 720 | K68: 744 | L68: 720 | M68: 744 | N68: 744 | O68: 696 | P68: 744 | Q68: 720 | R68: 744 | S68: 720
C69: =C21 -> Processing Tank 3 | E69: 8744 | F69: =SUM(H69:S69) -> 8784 | G69: hr | H69: 744 | I69: 744 | J69: 720 | K69: 744 | L69: 720 | M69: 744 | N69: 744 | O69: 696 | P69: 744 | Q69: 720 | R69: 744 | S69: 720
C70: =C22 -> Processing Tank 4 | E70: 8746 | F70: =SUM(H70:S70) -> 8784 | G70: hr | H70: 744 | I70: 744 | J70: 720 | K70: 744 | L70: 720 | M70: 744 | N70: 744 | O70: 696 | P70: 744 | Q70: 720 | R70: 744 | S70: 720
C71: =C23 -> Processing Tank 5 | E71: 8738 | F71: =SUM(H71:S71) -> 8784 | G71: hr | H71: 744 | I71: 744 | J71: 720 | K71: 744 | L71: 720 | M71: 744 | N71: 744 | O71: 696 | P71: 744 | Q71: 720 | R71: 744 | S71: 720
C72: =C24 -> Processing Tank 6 | E72: 8745 | F72: =SUM(H72:S72) -> 8716 | G72: hr | H72: 744 | I72: 744 | J72: 720 | K72: 744 | L72: 720 | M72: 744 | N72: 744 | O72: 674 | P72: 744 | Q72: 706 | R72: 712 | S72: 720
C73: =C25 -> Processing Tank 7 | E73: 8739 | F73: =SUM(H73:S73) -> 8784 | G73: hr | H73: 744 | I73: 744 | J73: 720 | K73: 744 | L73: 720 | M73: 744 | N73: 744 | O73: 696 | P73: 744 | Q73: 720 | R73: 744 | S73: 720
C74: =C26 -> Processing Tank 501 | E74: 7599 | F74: =SUM(H74:S74) -> 7748 | G74: hr | H74: 744 | I74: 744 | J74: 720 | K74: 556 | L74: 50 | M74: 566 | N74: 744 | O74: 696 | P74: 744 | Q74: 720 | R74: 744 | S74: 720
C75: =C27 -> Processing Tank 502 | E75: 7234 | F75: =SUM(H75:S75) -> 8782 | G75: hr | H75: 744 | I75: 744 | J75: 720 | K75: 744 | L75: 718 | M75: 744 | N75: 744 | O75: 696 | P75: 744 | Q75: 720 | R75: 744 | S75: 720
C76: =C28 -> Processing Tank 503 | E76: 7909 | F76: =SUM(H76:S76) -> 8782 | G76: hr | H76: 744 | I76: 744 | J76: 720 | K76: 744 | L76: 718 | M76: 744 | N76: 744 | O76: 696 | P76: 744 | Q76: 720 | R76: 744 | S76: 720
... C79: =C31 -> Processing Tank 506 | E79: 7907 | F79: =SUM(H79:S79) -> 8782 | G79: hr | H79: 744 | I79: 744 | J79: 720 | K79: 744 | L79: 718 | M79: 744 | N79: 744 | O79: 696 | P79: 744 | Q79: 720 | R79: 744 | S79: 720
C80: =C32 -> 0 | F80: =SUM(H80:S80) -> 0 | G80: hr
C81: =C33 -> 0 | F81: =SUM(H81:S81) -> 0 | G81: hr
C83: Total | E83: 115893 | F83: 130438 | G83: hr | H83: 11160 | I83: 11160 | J83: 10800 | K83: 10764 | L83: 10120 | M83: 10982 | N83: 11160 | O83: 10418 | P83: 11160 | Q83: 10786 | R83: 11128 | S83: 10800
C86: (1) The leach tanks are in operational status when the leach tanks are actively processing slurry and cyanide, and/or when process technicians are measuring titrable free CN (or any other CN monitoring) in the tanks.
C87: If only the first and last tank measurements are available, the intermediate tanks will be estimated based on a linear interpolation

Sheet CWF - Materials and Chemicals
C3: Ravenswood Operations | E3: Enter industrial products delivered to site or send raw data to Greenbase Account Lead. Greenbase will select any chemicals that contain or produce any NPI listed substances
C4: 01/07/2023 - 30/06/2024 | E4: Include all NPI chemicals where more than one tonne has been used, except for substances that contain Mercury (Include from 0 up)
E5: Include % concentration/solution for example for acids, sodium cyanide, etc.
E6: A list can be provided as a guide only, add any relevant substances as identified
J7: Obtain export of stock issues for materials/chemicals from Pronto. Create Pivot table to group each material/chemical and show monthly stock issues. Update values in red. Concrete data comes Towers Concrete - check with projects to see if any other concrete suppliers were used.
D9: Notes | E9: Data Source | F9: FY2023 Quantity | G9: FY2024 Quantity | H9: units
C10: Concrete Processed | D10: Estimated Density 2.41 tonnes/m3 | E10: Requested from Towers Concrete | F10: 5867 | G10: 260 | H10: m3
F11: 14139.47 | G11: =G10*2.41 -> 626.6 | H11: Tonne
C12: Materials
C14: Industrial Products Used Onsite and Concentration | D14: Manufacturer or Commercial Name | E14: Density, % Concentration, etc | F14: FY2023 Quantity | G14: FY2024 Quantity | H14: Unit | I14: Monthly Quantity | V14: Data Source
I15: Jul | J15: Aug | K15: Sep | L15: Oct | M15: Nov | N15: Dec | O15: Jan | P15: Feb | Q15: Mar | R15: Apr | S15: May | T15: Jun
C16: Coolant (Ethylene Glycol) | D16: Cummins Premix HD Premium N Cool 50/50 1000L IBC, Coolguard John Deere 10LT | F16: 17000 | G16: =SUM(I16:T16) -> 13000 | H16: L | J16: 1000 | L16: 2000 | N16: 1000 | O16: 2000 | P16: 2000 | Q16: 2000 | R16: 1000 | S16: 1000 | T16: 1000 | V16: Pronto - Stock Issues - 120407 1,000L IBC (170332U), 126253 (20L)
C17: Coolant (Ethylene Glycol) | D17: GB Calculated | E17: Assumed 50% ethylene glycol in coolant | F17: 8500 | G17: =SUM(I17:T17) -> 6500 | H17: [select] | I17: =I16*0.5 -> 0 | J17: =J16*0.5 -> 500 | K17: =K16*0.5 -> 0 | L17: =L16*0.5 -> 1000 | M17: =M16*0.5 -> 0 | N17: =N16*0.5 -> 500 | O17: =O16*0.5 -> 1000 | P17: =P16*0.5 -> 1000 | ... T17: =T16*0.5 -> 500 | V17: Pronto - Stock Issues
C18: Hydrochloric Acid (HCl) (30-32%) | D18: Australian Chemicals, 20L drum | E18: 30-32% | F18: 56 | G18: =SUM(I18:T18) -> 940 | H18: L | I18: 80 | J18: 20 | K18: 120 | L18: 40 | N18: 140 | O18: 120 | P18: 80 | Q18: 80 | R18: 180 | S18: 40 | T18: 40 | V18: Pronto- Stock Issues - 100991 20L (184010), (987570U 1,000 IBC) 101398 2.5L
C19: Hydrochloric Acid (HCl) (9% Dilute) | D19: ACID HYDROCHLORIC DILUTE 9% 1000L IBC | E19: 9% Dilute | F19: 9000 | G19: =SUM(I19:T19) -> 8000 | H19: L | J19: 1000 | K19: 1000 | L19: 1000 | M19: 1000 | R19: 1000 | S19: 3000 | V19: Pronto - Stock Issues - 123339; 1000L IBC
C20: Hydrochloric Acid (HCl) (min 32% strength) | D20: Australian Chemicals - bulk supplied | E20: min 32% strength | F20: 231795.1 | G20: =SUM(I20:T20) -> 458439.83 | H20: kg | I20: 15349.9 | J20: 23000 | K20: 41187 | L20: 29564.45 | M20: 26853.5 | N20: 27385.21 | O20: 40769.22 | P20: 106367.24 | Q20: 35751.35 | R20: 40198.94 | S20: 28998.68 | T20: 43014.34 | V20: Pronto - Stock Issues - 103203
C21: LPG (Bottles) | D21: BOC Gases Australia Ltd | F21: 486 | G21: =SUM(I21:T21) -> 0 | H21: kg | V21: Pronto - Stock Issues
C22: LPG (Bulk) | D22: Origin Energy - bulk supplied | F22: 271610.8 | G22: =SUM(I22:T22) -> 793257.1 | H22: L | I22: 42028.9 | J22: 62722.7 | K22: 45553.9 | L22: 32935.2 | M22: 78270.2 | N22: 32812.2 | O22: 59135.1 | P22: 160690.8 | Q22: 85282.6 | R22: 58889.8 | S22: 53056.5 | T22: 81879.2 | V22: Pronto- Stock Issues - 103570 (772256)
C23: LPG (Cylinder) | D23: BOC Gases Australia Ltd | F23: 650 | G23: =SUM(I23:T23) -> 522 | H23: kg | I23: 54 | J23: 54 | K23: 54 | L23: 72 | M23: 18 | O23: 72 | P23: 126 | Q23: 36 | R23: 18 | S23: 18 | V23: Pronto- Stock Issues - 103071 - PROPANE HANDIGAS Q SIZE 18KG
C24: LPG (Bottles) | D24: GB Calculated | F24: 1274.5098 | G24: =SUM(I24:T24) -> 1023.5294 | H24: L | I24: =I23/'Additional Data Entry'!$D$10 -> 105.88235 | J24: =J23/'Additional Data Entry'!$D$10 -> 105.88235 | K24: =K23/'Additional Data Entry'!$D$10 -> 105.88235 | L24: =L23/'Additional Data Entry'!$D$10 -> 141.17647 | M24: =M23/'Additional Data Entry'!$D$10 -> 35.294118 | N24: =N23/'Additional Data Entry'!$D$10 -> 0 | O24: =O23/'Additional Data Entry'!$D$10 -> 141.17647 | P24: =P23/'Additional Data Entry'!$D$10 -> 247.05882 | ... T24: =T23/'Additional Data Entry'!$D$10 -> 0 | V24: Pronto - Stock Issues
C25: Nitric Acid (HNO3) | D25: Australian Chemicals, Labtek | E25: 0.7 | F25: 180 | G25: =SUM(I25:T25) -> 0 | H25: L | V25: Pronto - Stock Issues - 100992 15L (1840280), 101399 2.5L
C26: Sodium Hypochlorite 31% Chlorine | D26: Australian Chemicals | E26: Density of 1.1kg/L | F26: 13000 | G26: =SUM(I26:T26) -> 21000 | H26: L | I26: 2000 | J26: 1000 | K26: 1000 | L26: 4000 | M26: 2000 | N26: 3000 | O26: 1000 | P26: 2000 | Q26: 2000 | R26: 2000 | S26: 1000 | V26: Pronto - Stock Issues - 104165 (1000L), 104164 (200L)
C27: Sodium Cyanide (NaCN) | D27: Orica | E27: 30-33% W/W | F27: 2952858.8 | G27: =SUM(I27:T27) -> 5327094.8 | H27: L | I27: 334473 | J27: 295083.8 | K27: 292366.52 | L27: 388488.5 | M27: 423118.35 | N27: 420192.54 | O27: 402031.36 | P27: 1177858.4 | Q27: 392042.46 | R27: 423101.62 | S27: 392441.15 | T27: 385897.18 | V27: Pronto - Stock Issues - 103430 (707562)
C28: Acetone Solvent | D28: Labtek | F28: 60 | G28: =SUM(I28:T28) -> 20 | H28: L | Q28: 20 | V28: Pronto - Stock Issues - 100798
C29: Alum Solution 46% 1300kg pod | D29: Waste Water Works | G29: =SUM(I29:T29) -> 93600 | H29: kg | I29: 7800 | J29: 7800 | K29: 6500 | L29: 7800 | M29: 9100 | N29: 5200 | O29: 10400 | P29: 10400 | Q29: 7800 | R29: 7800 | S29: 6500 | T29: 6500 | V29: Pronto - Stock Issues - 103466
C30: Sulphuric Acid 60% | D30: SULPHURIC ACID 60% 300kg DRUM; Labtek | G30: =SUM(I30:T30) -> 300 | H30: kg | O30: 300 | V30: Pronto - Stock Issues - 102247
C31: Methylated Spirits | D31: Blackwoods | G31: =SUM(I31:T31) -> 48 | H31: L | I31: 8 | K31: 8 | L31: 4 | O31: 12 | P31: 4 | Q31: 4 | R31: 8 | V31: Pronto - Stock Issues - 101241
C32: Diesel | D32: Chevron - bulk supplied | G32: =SUM(I32:T32) -> 50936469 | H32: L | I32: 3983179 | J32: 3498034 | K32: 3913688 | L32: 4557361 | M32: 4415005.5 | N32: 4591030.9 | O32: 4056087.2 | P32: 4138716 | Q32: 4021231 | R32: 4799522 | S32: 4359553 | T32: 4603061 | V32: Pronto - Stock Issues - 103206 (703132)
C33: Cement (Bags) | D33: Universal 7 Day Hardware | G33: =SUM(I33:T33) -> 3820 | H33: kg | I33: 200 | J33: 540 | K33: 200 | L33: 600 | P33: 680 | S33: 1600 | V33: Pronto - Stock Issues - 103077
C34: Sodium Hydroxide (NAOH) (Caustic) 49.7 - 50.3% - Bulk Liquid | D34: Australian Chemicals | G34: =SUM(I34:T34) -> 619896 | H34: kg | I34: 41364 | J34: 33290 | K34: 35980 | L34: 37310 | M34: 49700 | N34: 44869 | O34: 51030 | P34: 140830 | Q34: 33080 | R34: 44940 | S34: 45923 | T34: 61580 | V34: Pronto - Stock Issues - 103205, 122470
C35: Sulfamic Acid | D35: Australian Chemicals | G35: =SUM(I35:T35) -> 350 | H35: kg | I35: 75 | L35: 25 | M35: 125 | P35: 25 | R35: 25 | T35: 75 | V35: Pronto - Stock Issues - 103424
C36: Potassium Nitrate | D36: Rowe Scientific | G36: =SUM(I36:T36) -> 25 | H36: kg | N36: 25 | V36: Pronto - Stock Issues - 100761
C37: Silica (pulverised) | D37: Rowe Scientific | G37: =SUM(I37:T37) -> 300 | H37: kg | J37: 25 | K37: 25 | L37: 25 | M37: 50 | N37: 25 | O37: 25 | P37: 25 | Q37: 50 | S37: 25 | T37: 25 | V37: Pronto - Stock Issues - 102625
C38: Lime | D38: Cement Australia | G38: =SUM(I38:T38) -> 9686.15 | H38: kg | I38: 552.74 | J38: 606.81 | K38: 602.57 | L38: 685.82 | M38: 769.58 | N38: 933.88 | O38: 704.02 | P38: 2117.64 | Q38: 585.59 | R38: 800.63 | S38: 688.72 | T38: 638.15 | V38: Pronto - Stock Issues - 101673
G39: =SUM(I39:T39) -> 0 | H39: Tonne
C41: NGER Reporting | I41: Jul | J41: Aug | K41: Sep | L41: Oct | M41: Nov | N41: Dec | O41: Jan | P41: Feb | Q41: Mar | R41: Apr | S41: May | T41: Jun
C42: Acetylene (HC2H) | D42: BOC Gases Australia Ltd | F42: 632.4 | G42: =SUM(I42:T42) -> 591.4 | H42: m3 | I42: 37.6 | J42: 73.2 | K42: 14 | L42: 82.2 | M42: 55.4 | N42: 35 | O42: 63 | P42: 28 | Q42: 91 | R42: 14 | S42: 56 | T42: 42 | V42: Pronto - Stock Issues - 100192 7m3 (17616U), 102260 7m3 (19166U), 100701 3.2m3 (78303), 100214 1.0m3
C43: Total Other Oil purchased (excluding Hydraulic) | D43: VIVA Energy, Hitachi | F43: 56645.8 | G43: =SUM(I43:T43) -> 66471 | H43: L | I43: 5939 | J43: 7881 | K43: 4638 | L43: 800 | M43: 2537 | N43: 4642 | O43: 3388 | P43: 8978 | Q43: 10959 | R43: 7064 | S43: 6266 | T43: 3379 | V43: Pronto - Stock Issues - 'OIL,GEAR' - 120270 (1000L), 101036 (209L), 100330 (20L), 101605 (20L), 122561 (20L) 100379 (950L), 103652 (1000L), 127210 (1000L), 128162 (200L), 101608 (209L), 101290 (209L), 127405 (1000L), 101308 (8.9L), 101606 (209L), 101607 (20L), 101307 (208L), 126312 (209L), 100087 (20L), 124778 (1000L), 101036 - new addition
C44: Total Other Oil purchased (excluding Hydraulic) | D44: VIVA Energy | F44: 7 | G44: =SUM(I44:T44) -> 226.5 | H44: L | N44: 14 | P44: 3.5 | T44: 209 | V44: Pronto - Stock Issues - 'OIL,ENGINE', - 102911 (3.5L), 122690 (1000L), 124799 (1000L)
C45: Total Other Oil purchased (excluding Hydraulic) | D45: VIVA Energy, Jett Industries | F45: 60 | G45: =SUM(I45:T45) -> 50 | H45: L | N45: 5 | P45: 20 | Q45: 20 | R45: 5 | V45: Pronto - Stock Issues - 'OIL,AIR' - 103734 (20L), 124995 (5L)
C46: Total Other Oil purchased (excluding Hydraulic) | D46: VIVA Energy | F46: 80 | G46: =SUM(I46:T46) -> 120 | H46: L | K46: 40 | Q46: 40 | S46: 40 | V46: Pronto - Stock Issues - 'OIL, TRANS' - 125457 (20L)
C47: Total Other Oil purchased (excluding Hydraulic) | D47: VIVA Energy, Berendsen, Blackwoods | F47: 15 | G47: =SUM(I47:T47) -> 5 | H47: L | Q47: 5 | V47: Pronto - Stock Issues - 'OIL, RTA' - 101582 (5L); 'OIL INSULATING' - 101588 (209L), 'OIL ROCK DRILL' - 101961 (20L)
C48: Grease Purchased | D48: VIVA Energy, Blackwoods, Applied Industrial Technologies | F48: 747326.9 | G48: =SUM(I48:T48) -> 1429128.4 | H48: kg | I48: 71190 | J48: 64154 | K48: 57374 | L48: 88980 | M48: 75926 | N48: 469774 | O48: 53348 | P48: 99888.4 | Q48: 121319 | R48: 136640 | S48: 108635 | T48: 81900 | V48: Pronto - Stock Issues - 'GREASE,BEARING:' % 'GREASE,EXPOSED GEAR:' % 'GREASE, EXTREME PRESSURE:' % 'GREASE,GENERAL PURPOSE:' % 'GREASE,GEN PURPOSE' % 'GREASE,SBX2:' % 'GREASE,SPECIAL PURPOSE:' % 'GREASE, SBX2:' % ' GREASE,HIGH TEMP' % 100004 (180KG), 101578 (450G), 126311 (1000KG), 102910 (18KG), 101580 (450G), 101579 (18KG), 122403 (180KG), 122449 (420G), 900351 (80KG), 101472 (110G), 123620 (180KG), 101581 (450G), 103568 (450G), 122718 (18KG)
C49: Hydraulic Oil Purchased | D49: VIVA Energy, Hitachi | F49: 171864 | G49: =SUM(I49:T49) -> 124299 | H49: L | I49: 7000 | J49: 12418 | K49: 15209 | L49: 10209 | M49: 12209 | N49: 7209 | O49: 10209 | P49: 17000 | Q49: 8209 | R49: 8000 | S49: 3418 | T49: 13209 | V49: Pronto - 'OIL,HYDRAULIC' - 122929 (1000L), 125456 (1000L), 127922 (209L), 124972 (1000L), 122716 (1000L), 122715 (209L), 126696 (1000L), 103552 (209L), 122926 (1000L)
C52: Paste raw data below:
C54: Item Code | D54: Product Group | E54: UOM | F54: Trans Date | G54: Trans Type | H54: Quantity | J54: Sum of Calculated Amount | K54: Column Labels
C55: 100761 - POTASSIUM NITRATE HAIFA 25KG BAG | D55: CHEM - CHEMICALS | E55: Bag | F55: 45089 | G55: Stocktake | H55: 0 | K55: 2023 | Q55: 2024 | W55: 2024 Total | X55: Grand Total
C56: 100761 - POTASSIUM NITRATE HAIFA 25KG BAG - Total | H56: 0 | K56: Jul | L56: Aug | M56: Sep | N56: Oct | O56: Nov | P56: Dec | Q56: Jan | R56: Feb | S56: Mar | T56: Apr | U56: May | V56: Jun
C57: 100798 - ACETONE SOLVENT 20L | D57: LABC - LAB CONSUMABLES, GAS & CHEMLS | E57: Drum | F57: 45084 | G57: Purchase Order | H57: 2 | J57: Row Labels
C58: 100798 - ACETONE SOLVENT 20L | D58: LABC - LAB CONSUMABLES, GAS & CHEMLS | F58: 45089 | G58: Stocktake | H58: 0 | J58: BOC Gases Australia Ltd | K58: 37.6 | L58: 73.2 | M58: 14 | N58: 82.2 | O58: 55.4 | P58: 35 | Q58: 63 | R58: 28 | S58: 91 | T58: 14 | U58: 56 | V58: 42 | W58: 294 | X58: 591.4
C59: 100798 - ACETONE SOLVENT 20L | D59: LABC - LAB CONSUMABLES, GAS & CHEMLS | F59: 31/03/2024 | G59: Component Used | H59: -1 | J59: VIVA Energy | P59: 14 | R59: 3.5 | V59: 209 | W59: 212.5 | X59: 226.5
C60: 100798 - ACETONE SOLVENT 20L - Total | H60: 1 | J60: VIVA Energy, Berendsen, Blackwoods | S60: 5 | W60: 5 | X60: 5
C61: 100991 - HYDROCHLORIC ACID REAGENT 32% TECHNICAL GRADE 20L DRUM | D61: LABC - LAB CONSUMABLES, GAS & CHEMLS | E61: Drum | F61: 44964 | G61: Component Used | H61: -2 | J61: VIVA Energy, Blackwoods, Applied Industrial Technologies | K61: 71190 | L61: 63974 | M61: 57374 | N61: 88980 | O61: 75926 | P61: 112330.4 | Q61: 53168 | R61: 99708.4 | S61: 120958.8 | T61: 136640 | U61: 108454.8 | V61: 81900 | W61: 600830 | X61: 1070604.4
C62: 100991 - HYDROCHLORIC ACID REAGENT 32% TECHNICAL GRADE 20L DRUM | D62: LABC - LAB CONSUMABLES, GAS & CHEMLS | F62: 45145 | G62: Purchase Order | H62: 10 | J62: VIVA Energy, Hitachi | K62: 5939 | L62: 7881 | M62: 4638 | N62: 800 | O62: 2537 | P62: 4642 | Q62: 3388 | R62: 8978 | S62: 10959 | T62: 7064 | U62: 6266 | V62: 3379 | W62: 40034 | X62: 66471
C63: 100991 - HYDROCHLORIC ACID REAGENT 32% TECHNICAL GRADE 20L DRUM | D63: LABC - LAB CONSUMABLES, GAS & CHEMLS | F63: 21/07/2023 | G63: Component Used | H63: -1 | J63: VIVA Energy, Jett Industries | P63: 5 | T63: 5 | W63: 5 | X63: 10
C64: 100991 - HYDROCHLORIC ACID REAGENT 32% TECHNICAL GRADE 20L DRUM | D64: LABC - LAB CONSUMABLES, GAS & CHEMLS | F64: 24/07/2023 | G64: Component Used | H64: -1 | J64: VIVA Energy, Jett Industries | R64: 20 | S64: 20 | W64: 40 | X64: 40
C65: 100991 - HYDROCHLORIC ACID REAGENT 32% TECHNICAL GRADE 20L DRUM | D65: LABC - LAB CONSUMABLES, GAS & CHEMLS | F65: 15/08/2023 | G65: Component Used | H65: -1 | J65: VIVA Energy, Blackwoods, Applied Industrial Technologies | M65: 180 | R65: 180 | S65: 180 | T65: 360 | V65: 180 | W65: 900 | X65: 1080
C66: 100991 - HYDROCHLORIC ACID REAGENT 32% TECHNICAL GRADE 20L DRUM | D66: LABC - LAB CONSUMABLES, GAS & CHEMLS | F66: 44966 | G66: Component Used | H66: -2 | J66: VIVA Energy, Hitachi - Hydraulic Oil | K66: 7000 | L66: 12418 | M66: 15209 | N66: 10209 | O66: 12209 | P66: 7209 | Q66: 10209 | R66: 17000 | S66: 8209 | T66: 8000 | U66: 3418 | V66: 13209 | W66: 60045 | X66: 124299
C67: 100991 - HYDROCHLORIC ACID REAGENT 32% TECHNICAL GRADE 20L DRUM | D67: LABC - LAB CONSUMABLES, GAS & CHEMLS | F67: 45269 | G67: Component Used | H67: -1 | J67: VIVA Energy - 'OIL, TRANS' - 125457 (20L) | M67: 40 | S67: 40 | U67: 40 | W67: 80 | X67: 120
C68: 100991 - HYDROCHLORIC ACID REAGENT 32% TECHNICAL GRADE 20L DRUM | D68: LABC - LAB CONSUMABLES, GAS & CHEMLS | F68: 14/09/2023 | G68: Component Used | H68: -1 | J68: Grand Total | K68: 84166.6 | L68: 84346.2 | M68: 77455 | N68: 100071.2 | O68: 90727.4 | P68: 124235.4 | Q68: 66828 | R68: 125917.9 | S68: 140462.8 | T68: 152083 | U68: 118234.8 | V68: 98919 | W68: 702445.5 | X68: 1263447.3
C69: 100991 - HYDROCHLORIC ACID REAGENT 32% TECHNICAL GRADE 20L DRUM | D69: LABC - LAB CONSUMABLES, GAS & CHEMLS | F69: 14/09/2023 | G69: Component Used | H69: -2
C70: 100991 - HYDROCHLORIC ACID REAGENT 32% TECHNICAL GRADE 20L DRUM | D70: LABC - LAB CONSUMABLES, GAS & CHEMLS | F70: 17/10/2023 | G70: Component Used | H70: -2 | J70: Sum of Calculated | K70: Column Labels
C71: 100991 - HYDROCHLORIC ACID REAGENT 32% TECHNICAL GRADE 20L DRUM | D71: LABC - LAB CONSUMABLES, GAS & CHEMLS | F71: 24/10/2023 | G71: Purchase Order | H71: 10 | K71: <31/07/2023 | L71: Jan | M71: Feb | N71: Mar | O71: Apr | P71: May | Q71: Jun | R71: Jul | S71: Aug | T71: Sep | U71: Oct | V71: Nov | W71: Dec | X71: Grand Total
C72: 100991 - HYDROCHLORIC ACID REAGENT 32% TECHNICAL GRADE 20L DRUM | D72: LABC - LAB CONSUMABLES, GAS & CHEMLS | F72: 45089 | G72: Stocktake | H72: 1 | J72: Row Labels
C73: 100991 - HYDROCHLORIC ACID REAGENT 32% TECHNICAL GRADE 20L DRUM | D73: LABC - LAB CONSUMABLES, GAS & CHEMLS | F73: 45119 | G73: Component Used | H73: -1 | J73: LPG | K73: 674986.9 | L73: 59135.1 | M73: 42420.6 | N73: 85282.6 | O73: 58889.8 | P73: 53056.5 | Q73: 81879.2 | R73: 42028.9 | S73: 62722.7 | T73: 45553.9 | U73: 32935.2 | V73: 78270.2 | W73: 32812.2 | X73: 1349973.8
C74: 100991 - HYDROCHLORIC ACID REAGENT 32% TECHNICAL GRADE 20L DRUM | D74: LABC - LAB CONSUMABLES, GAS & CHEMLS | F74: 13/12/2023 | G74: Component Used | H74: -1 | J74: 31/07/2023 | K74: 674986.9 | X74: 674986.9
C75: 100991 - HYDROCHLORIC ACID REAGENT 32% TECHNICAL GRADE 20L DRUM | D75: LABC - LAB CONSUMABLES, GAS & CHEMLS | F75: 17/12/2023 | G75: Component Used | H75: -2 | J75: 2023 | R75: 42028.9 | S75: 62722.7 | T75: 45553.9 | U75: 32935.2 | V75: 78270.2 | W75: 32812.2 | X75: 294323.1
C76: 100991 - HYDROCHLORIC ACID REAGENT 32% TECHNICAL GRADE 20L DRUM | D76: LABC - LAB CONSUMABLES, GAS & CHEMLS | F76: 21/12/2023 | G76: Component Used | H76: -1 | J76: 2024 | L76: 59135.1 | M76: 42420.6 | N76: 85282.6 | O76: 58889.8 | P76: 53056.5 | Q76: 81879.2 | X76: 380663.8
